Workbook

Sheet About
A1: SoEDtICoS Share of Electricity Demand that Is Cost of Service
A2: Scope: state of PA | Data year: 2024
A4: Source: | B4: Retail electricity sales by serving entity (utility / marketer / CCA)
B5: U.S. Energy Information Administration (EIA)
B6: Form EIA-861 detailed data, Sales_Ult_Cust_2024.xlsx (sheet 'States')
B7: 2024
B8: https://www.eia.gov/electricity/data/eia861/
B9: Cost-of-service share = cost-of-service MWh / (cost-of-service + procurement) MWh for this jurisdiction. Ties to EIA published retail sales (Bundled+Energy).
A11: Notes:
A12: Classification | B12: LSE-based: cost-of-service = bundled sales of munis, cooperatives, federal/state/political-subdivision utilities, plus IOUs in non-restructured states (and the TX override utilities). Procurement = marketers, CCAs, any 'Energy' service-type sales, and IOUs in restructured states.
A13: Double-count fix | B13: Only Service Type Bundled or Energy enter the totals; 'Delivery' rows (the wires half of choice load) are classified 'excluded'.
A14: Exclusions | B14: EIA 'Adjustment' rows and 'Behind the Meter' ownership are excluded.
A15: Time profile | B15: Held FLAT 2021-2050 at the latest-year cost-of-service share. The analysis measures a single recent year; no independent forward projection is made.
A16: Restructured + overrides | B16: Editable on the Parameters tab. Non-ERCOT TX IOUs (util #s 55937/17718/17698/5701) are held cost-of-service.
A17: How it computes | B17: Source tab 'bucket' column classifies each row (reads Parameters via COUNTIF); the Share tab sums via SUMIFS; the SoEDtICoS tab = ROUND(share,3) flat across years. Edit Parameters and the EPS value recomputes.
A18: Caveat | B18: Staff-review input; verify against EIA primary sources. Restructured list and TX overrides are adjustable assumptions.

Sheet Parameters
A1: Parameters (editable — outputs recompute)
A3: Fully Restructured States | B3: Override Utility # | C3: Override Utility Name (reference)
A4: CT | B4: 55937 | C4: Entergy Texas Inc.
A5: DC | B5: 17718 | C5: Southwestern Public Service Co
A6: DE | B6: 17698 | C6: Southwestern Electric Power Co
A7: IL | B7: 5701 | C7: El Paso Electric Co
A8: MA
A9: MD
A10: ME
A11: NH
A12: NJ
A13: NY
A14: OH
A15: PA
A16: RI
A17: TX

Sheet EIA-861 Sales 2024
A1: Utility Characteristics | J1: RESIDENTIAL | M1: COMMERCIAL | P1: INDUSTRIAL | S1: TRANSPORTATION | V1: TOTAL
J2: Revenues | K2: Sales | L2: Customers | M2: Revenues | N2: Sales | O2: Customers | P2: Revenues | Q2: Sales | R2: Customers | S2: Revenues | T2: Sales | U2: Customers | V2: Revenues | W2: Sales | X2: Customers
A3: Data Year | B3: Utility Number | C3: Utility Name | D3: Part | E3: Service Type | F3: Data Type O = Observed I = Imputed | G3: State | H3: Ownership | I3: BA Code | J3: Thousand Dollars | K3: Megawatthours | L3: Count | M3: Thousand Dollars | N3: Megawatthours | O3: Count | P3: Thousand Dollars | Q3: Megawatthours | R3: Count | S3: Thousand Dollars | T3: Megawatthours | U3: Count | V3: Thousand Dollars | W3: Megawatthours | X3: Count | Y3: sales_mwh (derived) | Z3: bucket (derived)
A4: 2024 | B4: 113 | C4: Agway Energy Services, LLC | D4: B | E4: Energy | F4: O | G4: PA | H4: Retail Power Marketer | I4: PJM | J4: 972.7 | K4: 8449 | L4: 945 | M4: 95.2 | N4: 918 | O4: 46 | P4: 0 | Q4: 0 | R4: 0 | S4: 0 | T4: 0 | U4: 0 | V4: 1067.9 | W4: 9367 | X4: 991 | Y4: =IF(ISNUMBER($W4),$W4,0) | Z4: =IF(ISNUMBER(SEARCH("Adjustment",$C4)),"excluded",IF($H4="Behind the Meter","excluded",IF(NOT(OR($E4="Bundled",$E4="Energy")),"excluded",IF(OR($H4="Retail Power Marketer",$H4="Community Choice Aggregator",$E4="Energy"),"procurement",IF(OR($H4="Municipal",$H4="Cooperative",$H4="Federal",$H4="State",$H4="Political Subdivision"),"cost_service",IF($H4="Investor Owned",IF(AND(COUNTIF(Parameters!$A$4:$A$33,$G4)>0,COUNTIF(Parameters!$B$4:$B$33,$B4)=0),"procurement","cost_service"),"unclassified"))))))
A5: 2024 | B5: 1611 | C5: Messer Energy Services, Inc. | D5: B | E5: Energy | F5: O | G5: PA | H5: Retail Power Marketer | I5: PJM | J5: 0 | K5: 0 | L5: 0 | M5: 0 | N5: 0 | O5: 0 | P5: 29609 | Q5: 561049 | R5: 3 | S5: 0 | T5: 0 | U5: 0 | V5: 29609 | W5: 561049 | X5: 3 | Y5: =IF(ISNUMBER($W5),$W5,0) | Z5: =IF(ISNUMBER(SEARCH("Adjustment",$C5)),"excluded",IF($H5="Behind the Meter","excluded",IF(NOT(OR($E5="Bundled",$E5="Energy")),"excluded",IF(OR($H5="Retail Power Marketer",$H5="Community Choice Aggregator",$E5="Energy"),"procurement",IF(OR($H5="Municipal",$H5="Cooperative",$H5="Federal",$H5="State",$H5="Political Subdivision"),"cost_service",IF($H5="Investor Owned",IF(AND(COUNTIF(Parameters!$A$4:$A$33,$G5)>0,COUNTIF(Parameters!$B$4:$B$33,$B5)=0),"procurement","cost_service"),"unclassified"))))))
A6: 2024 | B6: 3329 | C6: Borough of Chambersburg | D6: A | E6: Bundled | F6: O | G6: PA | H6: Municipal | I6: PJM | J6: 11653.3 | K6: 97501 | L6: 9914 | M6: 12992.2 | N6: 119572 | O6: 1783 | P6: 9324.8 | Q6: 107070 | R6: 21 | S6: 0 | T6: 0 | U6: 0 | V6: 33970.3 | W6: 324143 | X6: 11718 | Y6: =IF(ISNUMBER($W6),$W6,0) | Z6: =IF(ISNUMBER(SEARCH("Adjustment",$C6)),"excluded",IF($H6="Behind the Meter","excluded",IF(NOT(OR($E6="Bundled",$E6="Energy")),"excluded",IF(OR($H6="Retail Power Marketer",$H6="Community Choice Aggregator",$E6="Energy"),"procurement",IF(OR($H6="Municipal",$H6="Cooperative",$H6="Federal",$H6="State",$H6="Political Subdivision"),"cost_service",IF($H6="Investor Owned",IF(AND(COUNTIF(Parameters!$A$4:$A$33,$G6)>0,COUNTIF(Parameters!$B$4:$B$33,$B6)=0),"procurement","cost_service"),"unclassified"))))))
A7: 2024 | B7: 3597 | C7: Citizens Electric Co - (PA) | D7: A | E7: Bundled | F7: O | G7: PA | H7: Investor Owned | I7: PJM | J7: 11121 | K7: 81599 | L7: 5958 | M7: 3124 | N7: 22397 | O7: 1128 | P7: 1182 | Q7: 9598 | R7: 22 | S7: 0 | T7: 0 | U7: 0 | V7: 15427 | W7: 113594 | X7: 7108 | Y7: =IF(ISNUMBER($W7),$W7,0) | Z7: =IF(ISNUMBER(SEARCH("Adjustment",$C7)),"excluded",IF($H7="Behind the Meter","excluded",IF(NOT(OR($E7="Bundled",$E7="Energy")),"excluded",IF(OR($H7="Retail Power Marketer",$H7="Community Choice Aggregator",$E7="Energy"),"procurement",IF(OR($H7="Municipal",$H7="Cooperative",$H7="Federal",$H7="State",$H7="Political Subdivision"),"cost_service",IF($H7="Investor Owned",IF(AND(COUNTIF(Parameters!$A$4:$A$33,$G7)>0,COUNTIF(Parameters!$B$4:$B$33,$B7)=0),"procurement","cost_service"),"unclassified"))))))
A8: 2024 | B8: 3597 | C8: Citizens Electric Co - (PA) | D8: C | E8: Delivery | F8: O | G8: PA | H8: Investor Owned | I8: PJM | J8: 5 | K8: 124 | L8: 5 | M8: 107 | N8: 3492 | O8: 43 | P8: 532 | Q8: 33691 | R8: 18 | S8: 0 | T8: 0 | U8: 0 | V8: 644 | W8: 37307 | X8: 66 | Y8: =IF(ISNUMBER($W8),$W8,0) | Z8: =IF(ISNUMBER(SEARCH("Adjustment",$C8)),"excluded",IF($H8="Behind the Meter","excluded",IF(NOT(OR($E8="Bundled",$E8="Energy")),"excluded",IF(OR($H8="Retail Power Marketer",$H8="Community Choice Aggregator",$E8="Energy"),"procurement",IF(OR($H8="Municipal",$H8="Cooperative",$H8="Federal",$H8="State",$H8="Political Subdivision"),"cost_service",IF($H8="Investor Owned",IF(AND(COUNTIF(Parameters!$A$4:$A$33,$G8)>0,COUNTIF(Parameters!$B$4:$B$33,$B8)=0),"procurement","cost_service"),"unclassified"))))))
A9: 2024 | B9: 4100 | C9: Just Energy Solutions Inc. | D9: B | E9: Energy | F9: O | G9: PA | H9: Retail Power Marketer | I9: PJM | J9: 5590.5 | K9: 47987 | L9: 5454 | M9: 1919.2 | N9: 11602 | O9: 1625 | P9: 0 | Q9: 0 | R9: 0 | S9: 0 | T9: 0 | U9: 0 | V9: 7509.7 | W9: 59589 | X9: 7079 | Y9: =IF(ISNUMBER($W9),$W9,0) | Z9: =IF(ISNUMBER(SEARCH("Adjustment",$C9)),"excluded",IF($H9="Behind the Meter","excluded",IF(NOT(OR($E9="Bundled",$E9="Energy")),"excluded",IF(OR($H9="Retail Power Marketer",$H9="Community Choice Aggregator",$E9="Energy"),"procurement",IF(OR($H9="Municipal",$H9="Cooperative",$H9="Federal",$H9="State",$H9="Political Subdivision"),"cost_service",IF($H9="Investor Owned",IF(AND(COUNTIF(Parameters!$A$4:$A$33,$G9)>0,COUNTIF(Parameters!$B$4:$B$33,$B9)=0),"procurement","cost_service"),"unclassified"))))))
A10: 2024 | B10: 5487 | C10: Duquesne Light Co | D10: A | E10: Bundled | F10: O | G10: PA | H10: Investor Owned | I10: PJM | J10: 685304 | K10: 3151995 | L10: 434171 | M10: 159148 | N10: 999403 | O10: 38515 | P10: 8532 | Q10: 63936 | R10: 332 | S10: . | T10: . | U10: . | V10: 852984 | W10: 4215334 | X10: 473018 | Y10: =IF(ISNUMBER($W10),$W10,0) | Z10: =IF(ISNUMBER(SEARCH("Adjustment",$C10)),"excluded",IF($H10="Behind the Meter","excluded",IF(NOT(OR($E10="Bundled",$E10="Energy")),"excluded",IF(OR($H10="Retail Power Marketer",$H10="Community Choice Aggregator",$E10="Energy"),"procurement",IF(OR($H10="Municipal",$H10="Cooperative",$H10="Federal",$H10="State",$H10="Political Subdivision"),"cost_service",IF($H10="Investor Owned",IF(AND(COUNTIF(Parameters!$A$4:$A$33,$G10)>0,COUNTIF(Parameters!$B$4:$B$33,$B10)=0),"procurement","cost_service"),"unclassified"))))))
A11: 2024 | B11: 5487 | C11: Duquesne Light Co | D11: C | E11: Delivery | F11: O | G11: PA | H11: Investor Owned | I11: PJM | J11: 99094 | K11: 877741 | L11: 116234 | M11: 165180 | N11: 4708846 | O11: 23855 | P11: 38301 | Q11: 2945306 | R11: 680 | S11: 1328 | T11: 14216 | U11: 1 | V11: 303903 | W11: 8546109 | X11: 140770 | Y11: =IF(ISNUMBER($W11),$W11,0) | Z11: =IF(ISNUMBER(SEARCH("Adjustment",$C11)),"excluded",IF($H11="Behind the Meter","excluded",IF(NOT(OR($E11="Bundled",$E11="Energy")),"excluded",IF(OR($H11="Retail Power Marketer",$H11="Community Choice Aggregator",$E11="Energy"),"procurement",IF(OR($H11="Municipal",$H11="Cooperative",$H11="Federal",$H11="State",$H11="Political Subdivision"),"cost_service",IF($H11="Investor Owned",IF(AND(COUNTIF(Parameters!$A$4:$A$33,$G11)>0,COUNTIF(Parameters!$B$4:$B$33,$B11)=0),"procurement","cost_service"),"unclassified"))))))
A12: 2024 | B12: 5880 | C12: Energy Coop of New York, Inc | D12: B | E12: Energy | F12: O | G12: PA | H12: Retail Power Marketer | I12: PJM | J12: 179 | K12: 1802 | L12: 156 | M12: 678 | N12: 9633 | O12: 158 | P12: 0 | Q12: 0 | R12: 0 | S12: 0 | T12: 0 | U12: 0 | V12: 857 | W12: 11435 | X12: 314 | Y12: =IF(ISNUMBER($W12),$W12,0) | Z12: =IF(ISNUMBER(SEARCH("Adjustment",$C12)),"excluded",IF($H12="Behind the Meter","excluded",IF(NOT(OR($E12="Bundled",$E12="Energy")),"excluded",IF(OR($H12="Retail Power Marketer",$H12="Community Choice Aggregator",$E12="Energy"),"procurement",IF(OR($H12="Municipal",$H12="Cooperative",$H12="Federal",$H12="State",$H12="Political Subdivision"),"cost_service",IF($H12="Investor Owned",IF(AND(COUNTIF(Parameters!$A$4:$A$33,$G12)>0,COUNTIF(Parameters!$B$4:$B$33,$B12)=0),"procurement","cost_service"),"unclassified"))))))
A13: 2024 | B13: 6458 | C13: Energy Harbor Corp. | D13: B | E13: Energy | F13: O | G13: PA | H13: Retail Power Marketer | I13: PJM | J13: 134640.8 | K13: 1245709 | L13: 105658 | M13: 58831.6 | N13: 893102 | O13: 3436 | P13: 134045.8 | Q13: 2707802 | R13: 127 | S13: 0 | T13: 0 | U13: 0 | V13: 327518.2 | W13: 4846613 | X13: 109221 | Y13: =IF(ISNUMBER($W13),$W13,0) | Z13: =IF(ISNUMBER(SEARCH("Adjustment",$C13)),"excluded",IF($H13="Behind the Meter","excluded",IF(NOT(OR($E13="Bundled",$E13="Energy")),"excluded",IF(OR($H13="Retail Power Marketer",$H13="Community Choice Aggregator",$E13="Energy"),"procurement",IF(OR($H13="Municipal",$H13="Cooperative",$H13="Federal",$H13="State",$H13="Political Subdivision"),"cost_service",IF($H13="Investor Owned",IF(AND(COUNTIF(Parameters!$A$4:$A$33,$G13)>0,COUNTIF(Parameters!$B$4:$B$33,$B13)=0),"procurement","cost_service"),"unclassified"))))))
A14: 2024 | B14: 7279 | C14: NextEra Energy Services, LLC | D14: B | E14: Energy | F14: O | G14: PA | H14: Retail Power Marketer | I14: PJM | J14: 17509.8 | K14: 124848 | L14: 11544 | M14: 88245.1 | N14: 1291326 | O14: 520 | P14: . | Q14: . | R14: . | S14: . | T14: . | U14: . | V14: 105754.9 | W14: 1416174 | X14: 12064 | Y14: =IF(ISNUMBER($W14),$W14,0) | Z14: =IF(ISNUMBER(SEARCH("Adjustment",$C14)),"excluded",IF($H14="Behind the Meter","excluded",IF(NOT(OR($E14="Bundled",$E14="Energy")),"excluded",IF(OR($H14="Retail Power Marketer",$H14="Community Choice Aggregator",$E14="Energy"),"procurement",IF(OR($H14="Municipal",$H14="Cooperative",$H14="Federal",$H14="State",$H14="Political Subdivision"),"cost_service",IF($H14="Investor Owned",IF(AND(COUNTIF(Parameters!$A$4:$A$33,$G14)>0,COUNTIF(Parameters!$B$4:$B$33,$B14)=0),"procurement","cost_service"),"unclassified"))))))
A15: 2024 | B15: 7554 | C15: Green Mountain Energy Company | D15: B | E15: Energy | F15: O | G15: PA | H15: Retail Power Marketer | I15: PJM | J15: 37241 | K15: 285360 | L15: 30875 | M15: 919 | N15: 11080 | O15: 13 | P15: 0 | Q15: 0 | R15: 0 | S15: 0 | T15: 0 | U15: 0 | V15: 38160 | W15: 296440 | X15: 30888 | Y15: =IF(ISNUMBER($W15),$W15,0) | Z15: =IF(ISNUMBER(SEARCH("Adjustment",$C15)),"excluded",IF($H15="Behind the Meter","excluded",IF(NOT(OR($E15="Bundled",$E15="Energy")),"excluded",IF(OR($H15="Retail Power Marketer",$H15="Community Choice Aggregator",$E15="Energy"),"procurement",IF(OR($H15="Municipal",$H15="Cooperative",$H15="Federal",$H15="State",$H15="Political Subdivision"),"cost_service",IF($H15="Investor Owned",IF(AND(COUNTIF(Parameters!$A$4:$A$33,$G15)>0,COUNTIF(Parameters!$B$4:$B$33,$B15)=0),"procurement","cost_service"),"unclassified"))))))
A16: 2024 | B16: 9949 | C16: Just Energy | D16: B | E16: Energy | F16: O | G16: PA | H16: Retail Power Marketer | I16: PJM | J16: 29825.8 | K16: 236938 | L16: 20938 | M16: 5.1 | N16: 45 | O16: 3 | P16: 0 | Q16: 0 | R16: 0 | S16: 0 | T16: 0 | U16: 0 | V16: 29830.9 | W16: 236983 | X16: 20941 | Y16: =IF(ISNUMBER($W16),$W16,0) | Z16: =IF(ISNUMBER(SEARCH("Adjustment",$C16)),"excluded",IF($H16="Behind the Meter","excluded",IF(NOT(OR($E16="Bundled",$E16="Energy")),"excluded",IF(OR($H16="Retail Power Marketer",$H16="Community Choice Aggregator",$E16="Energy"),"procurement",IF(OR($H16="Municipal",$H16="Cooperative",$H16="Federal",$H16="State",$H16="Political Subdivision"),"cost_service",IF($H16="Investor Owned",IF(AND(COUNTIF(Parameters!$A$4:$A$33,$G16)>0,COUNTIF(Parameters!$B$4:$B$33,$B16)=0),"procurement","cost_service"),"unclassified"))))))
A17: 2024 | B17: 13374 | C17: Constellation NewEnergy, Inc | D17: B | E17: Energy | F17: O | G17: PA | H17: Retail Power Marketer | I17: PJM | J17: 61610.7 | K17: 593218 | L17: 53821 | M17: 1380249.1 | N17: 19290687 | O17: 81982 | P17: 180491.1 | Q17: 2854913 | R17: 1102 | S17: 12008.3 | T17: 148548 | U17: 1 | V17: 1634359.2 | W17: 22887366 | X17: 136906 | Y17: =IF(ISNUMBER($W17),$W17,0) | Z17: =IF(ISNUMBER(SEARCH("Adjustment",$C17)),"excluded",IF($H17="Behind the Meter","excluded",IF(NOT(OR($E17="Bundled",$E17="Energy")),"excluded",IF(OR($H17="Retail Power Marketer",$H17="Community Choice Aggregator",$E17="Energy"),"procurement",IF(OR($H17="Municipal",$H17="Cooperative",$H17="Federal",$H17="State",$H17="Political Subdivision"),"cost_service",IF($H17="Investor Owned",IF(AND(COUNTIF(Parameters!$A$4:$A$33,$G17)>0,COUNTIF(Parameters!$B$4:$B$33,$B17)=0),"procurement","cost_service"),"unclassified"))))))
A18: 2024 | B18: 14715 | C18: PPL Electric Utilities Corp | D18: A | E18: Bundled | F18: O | G18: PA | H18: Investor Owned | I18: PJM | J18: 1380991.7 | K18: 8128207 | L18: 797773 | M18: 262203.9 | N18: 1886520 | O18: 93479 | P18: 16938.7 | Q18: 154926 | R18: 856 | S18: 0 | T18: 0 | U18: 0 | V18: 1660134.3 | W18: 10169653 | X18: 892108 | Y18: =IF(ISNUMBER($W18),$W18,0) | Z18: =IF(ISNUMBER(SEARCH("Adjustment",$C18)),"excluded",IF($H18="Behind the Meter","excluded",IF(NOT(OR($E18="Bundled",$E18="Energy")),"excluded",IF(OR($H18="Retail Power Marketer",$H18="Community Choice Aggregator",$E18="Energy"),"procurement",IF(OR($H18="Municipal",$H18="Cooperative",$H18="Federal",$H18="State",$H18="Political Subdivision"),"cost_service",IF($H18="Investor Owned",IF(AND(COUNTIF(Parameters!$A$4:$A$33,$G18)>0,COUNTIF(Parameters!$B$4:$B$33,$B18)=0),"procurement","cost_service"),"unclassified"))))))
A19: 2024 | B19: 14715 | C19: PPL Electric Utilities Corp | D19: C | E19: Delivery | F19: O | G19: PA | H19: Investor Owned | I19: PJM | J19: 374734.4 | K19: 6098417 | L19: 498110 | M19: 193575.7 | N19: 12010707 | O19: 95036 | P19: 36574 | Q19: 8345169 | R19: 2093 | S19: 0 | T19: 0 | U19: 0 | V19: 604884.1 | W19: 26454293 | X19: 595239 | Y19: =IF(ISNUMBER($W19),$W19,0) | Z19: =IF(ISNUMBER(SEARCH("Adjustment",$C19)),"excluded",IF($H19="Behind the Meter","excluded",IF(NOT(OR($E19="Bundled",$E19="Energy")),"excluded",IF(OR($H19="Retail Power Marketer",$H19="Community Choice Aggregator",$E19="Energy"),"procurement",IF(OR($H19="Municipal",$H19="Cooperative",$H19="Federal",$H19="State",$H19="Political Subdivision"),"cost_service",IF($H19="Investor Owned",IF(AND(COUNTIF(Parameters!$A$4:$A$33,$G19)>0,COUNTIF(Parameters!$B$4:$B$33,$B19)=0),"procurement","cost_service"),"unclassified"))))))
A20: 2024 | B20: 14940 | C20: PECO Energy Co | D20: A | E20: Bundled | F20: O | G20: PA | H20: Investor Owned | I20: PJM | J20: 1752341 | K20: 10840952 | L20: 1205013 | M20: 311773.5 | N20: 2648121 | O20: 99909 | P20: 42395 | Q20: 561116 | R20: 394 | S20: 0 | T20: 0 | U20: 0 | V20: 2106509.5 | W20: 14050189 | X20: 1305316 | Y20: =IF(ISNUMBER($W20),$W20,0) | Z20: =IF(ISNUMBER(SEARCH("Adjustment",$C20)),"excluded",IF($H20="Behind the Meter","excluded",IF(NOT(OR($E20="Bundled",$E20="Energy")),"excluded",IF(OR($H20="Retail Power Marketer",$H20="Community Choice Aggregator",$E20="Energy"),"procurement",IF(OR($H20="Municipal",$H20="Cooperative",$H20="Federal",$H20="State",$H20="Political Subdivision"),"cost_service",IF($H20="Investor Owned",IF(AND(COUNTIF(Parameters!$A$4:$A$33,$G20)>0,COUNTIF(Parameters!$B$4:$B$33,$B20)=0),"procurement","cost_service"),"unclassified"))))))
A21: 2024 | B21: 14940 | C21: PECO Energy Co | D21: C | E21: Delivery | F21: O | G21: PA | H21: Investor Owned | I21: PJM | J21: 285785.8 | K21: 2981893 | L21: 330805 | M21: 198915.2 | N21: 4945199 | O21: 67420 | P21: 187861.4 | Q21: 12964540 | R21: 2755 | S21: 7078.3 | T21: 469922 | U21: 3 | V21: 679640.7 | W21: 21361554 | X21: 400983 | Y21: =IF(ISNUMBER($W21),$W21,0) | Z21: =IF(ISNUMBER(SEARCH("Adjustment",$C21)),"excluded",IF($H21="Behind the Meter","excluded",IF(NOT(OR($E21="Bundled",$E21="Energy")),"excluded",IF(OR($H21="Retail Power Marketer",$H21="Community Choice Aggregator",$E21="Energy"),"procurement",IF(OR($H21="Municipal",$H21="Cooperative",$H21="Federal",$H21="State",$H21="Political Subdivision"),"cost_service",IF($H21="Investor Owned",IF(AND(COUNTIF(Parameters!$A$4:$A$33,$G21)>0,COUNTIF(Parameters!$B$4:$B$33,$B21)=0),"procurement","cost_service"),"unclassified"))))))
A22: 2024 | B22: 15045 | C22: Pike County Light & Power Co | D22: A | E22: Bundled | F22: O | G22: PA | H22: Investor Owned | I22: NYIS | J22: 5749.3 | K22: 28824 | L22: 3646 | M22: 7035 | N22: 40496 | O22: 799 | P22: 0 | Q22: 0 | R22: 0 | S22: 0 | T22: 0 | U22: 0 | V22: 12784.3 | W22: 69320 | X22: 4445 | Y22: =IF(ISNUMBER($W22),$W22,0) | Z22: =IF(ISNUMBER(SEARCH("Adjustment",$C22)),"excluded",IF($H22="Behind the Meter","excluded",IF(NOT(OR($E22="Bundled",$E22="Energy")),"excluded",IF(OR($H22="Retail Power Marketer",$H22="Community Choice Aggregator",$E22="Energy"),"procurement",IF(OR($H22="Municipal",$H22="Cooperative",$H22="Federal",$H22="State",$H22="Political Subdivision"),"cost_service",IF($H22="Investor Owned",IF(AND(COUNTIF(Parameters!$A$4:$A$33,$G22)>0,COUNTIF(Parameters!$B$4:$B$33,$B22)=0),"procurement","cost_service"),"unclassified"))))))
A23: 2024 | B23: 15045 | C23: Pike County Light & Power Co | D23: C | E23: Delivery | F23: O | G23: PA | H23: Investor Owned | I23: NYIS | J23: 629.8 | K23: 5368 | L23: 701 | M23: 714.6 | N23: 6934 | O23: 216 | P23: 0 | Q23: 0 | R23: 0 | S23: 0 | T23: 0 | U23: 0 | V23: 1344.4 | W23: 12302 | X23: 917 | Y23: =IF(ISNUMBER($W23),$W23,0) | Z23: =IF(ISNUMBER(SEARCH("Adjustment",$C23)),"excluded",IF($H23="Behind the Meter","excluded",IF(NOT(OR($E23="Bundled",$E23="Energy")),"excluded",IF(OR($H23="Retail Power Marketer",$H23="Community Choice Aggregator",$E23="Energy"),"procurement",IF(OR($H23="Municipal",$H23="Cooperative",$H23="Federal",$H23="State",$H23="Political Subdivision"),"cost_service",IF($H23="Investor Owned",IF(AND(COUNTIF(Parameters!$A$4:$A$33,$G23)>0,COUNTIF(Parameters!$B$4:$B$33,$B23)=0),"procurement","cost_service"),"unclassified"))))))
A24: 2024 | B24: 16840 | C24: Calpine Energy Solutions, LLC | D24: B | E24: Energy | F24: O | G24: PA | H24: Retail Power Marketer | I24: PJM | J24: 0 | K24: 0 | L24: 0 | M24: 241453.8 | N24: 4459656 | O24: 67 | P24: 19502.9 | Q24: 347804 | R24: 9 | S24: 0 | T24: 0 | U24: 0 | V24: 260956.7 | W24: 4807460 | X24: 76 | Y24: =IF(ISNUMBER($W24),$W24,0) | Z24: =IF(ISNUMBER(SEARCH("Adjustment",$C24)),"excluded",IF($H24="Behind the Meter","excluded",IF(NOT(OR($E24="Bundled",$E24="Energy")),"excluded",IF(OR($H24="Retail Power Marketer",$H24="Community Choice Aggregator",$E24="Energy"),"procurement",IF(OR($H24="Municipal",$H24="Cooperative",$H24="Federal",$H24="State",$H24="Political Subdivision"),"cost_service",IF($H24="Investor Owned",IF(AND(COUNTIF(Parameters!$A$4:$A$33,$G24)>0,COUNTIF(Parameters!$B$4:$B$33,$B24)=0),"procurement","cost_service"),"unclassified"))))))
A25: 2024 | B25: 18193 | C25: Direct Energy Business | D25: B | E25: Energy | F25: O | G25: PA | H25: Retail Power Marketer | I25: PJM | J25: 0 | K25: 0 | L25: 0 | M25: 135657.5 | N25: 1599928 | O25: 6331 | P25: 459153.2 | Q25: 6409008 | R25: 717 | S25: 0 | T25: 0 | U25: 0 | V25: 594810.7 | W25: 8008936 | X25: 7048 | Y25: =IF(ISNUMBER($W25),$W25,0) | Z25: =IF(ISNUMBER(SEARCH("Adjustment",$C25)),"excluded",IF($H25="Behind the Meter","excluded",IF(NOT(OR($E25="Bundled",$E25="Energy")),"excluded",IF(OR($H25="Retail Power Marketer",$H25="Community Choice Aggregator",$E25="Energy"),"procurement",IF(OR($H25="Municipal",$H25="Cooperative",$H25="Federal",$H25="State",$H25="Political Subdivision"),"cost_service",IF($H25="Investor Owned",IF(AND(COUNTIF(Parameters!$A$4:$A$33,$G25)>0,COUNTIF(Parameters!$B$4:$B$33,$B25)=0),"procurement","cost_service"),"unclassified"))))))
A26: 2024 | B26: 19107 | C26: ENGIE Resources LLC | D26: B | E26: Energy | F26: O | G26: PA | H26: Retail Power Marketer | I26: PJM | J26: 0 | K26: 0 | L26: 0 | M26: 280552.2 | N26: 4137884 | O26: 3424 | P26: 28086.1 | Q26: 414244 | R26: 343 | S26: 0 | T26: 0 | U26: 0 | V26: 308638.3 | W26: 4552128 | X26: 3767 | Y26: =IF(ISNUMBER($W26),$W26,0) | Z26: =IF(ISNUMBER(SEARCH("Adjustment",$C26)),"excluded",IF($H26="Behind the Meter","excluded",IF(NOT(OR($E26="Bundled",$E26="Energy")),"excluded",IF(OR($H26="Retail Power Marketer",$H26="Community Choice Aggregator",$E26="Energy"),"procurement",IF(OR($H26="Municipal",$H26="Cooperative",$H26="Federal",$H26="State",$H26="Political Subdivision"),"cost_service",IF($H26="Investor Owned",IF(AND(COUNTIF(Parameters!$A$4:$A$33,$G26)>0,COUNTIF(Parameters!$B$4:$B$33,$B26)=0),"procurement","cost_service"),"unclassified"))))))
... A32: 2024 | B32: 20659 | C32: WGL Energy Services, Inc. | D32: B | E32: Energy | F32: O | G32: PA | H32: Retail Power Marketer | I32: PJM | J32: 6386 | K32: 98555 | L32: 11403 | M32: 313159 | N32: 4489731 | O32: 21575 | P32: 0 | Q32: 0 | R32: 0 | S32: 0 | T32: 0 | U32: 0 | V32: 319545 | W32: 4588286 | X32: 32978 | Y32: =IF(ISNUMBER($W32),$W32,0) | Z32: =IF(ISNUMBER(SEARCH("Adjustment",$C32)),"excluded",IF($H32="Behind the Meter","excluded",IF(NOT(OR($E32="Bundled",$E32="Energy")),"excluded",IF(OR($H32="Retail Power Marketer",$H32="Community Choice Aggregator",$E32="Energy"),"procurement",IF(OR($H32="Municipal",$H32="Cooperative",$H32="Federal",$H32="State",$H32="Political Subdivision"),"cost_service",IF($H32="Investor Owned",IF(AND(COUNTIF(Parameters!$A$4:$A$33,$G32)>0,COUNTIF(Parameters!$B$4:$B$33,$B32)=0),"procurement","cost_service"),"unclassified"))))))
A33: 2024 | B33: 28802 | C33: Talen Energy Marketing, LLC | D33: B | E33: Energy | F33: O | G33: PA | H33: Retail Power Marketer | I33: PJM | J33: . | K33: . | L33: . | M33: . | N33: . | O33: . | P33: 1429 | Q33: 34777 | R33: 4 | S33: . | T33: . | U33: . | V33: 1429 | W33: 34777 | X33: 4 | Y33: =IF(ISNUMBER($W33),$W33,0) | Z33: =IF(ISNUMBER(SEARCH("Adjustment",$C33)),"excluded",IF($H33="Behind the Meter","excluded",IF(NOT(OR($E33="Bundled",$E33="Energy")),"excluded",IF(OR($H33="Retail Power Marketer",$H33="Community Choice Aggregator",$E33="Energy"),"procurement",IF(OR($H33="Municipal",$H33="Cooperative",$H33="Federal",$H33="State",$H33="Political Subdivision"),"cost_service",IF($H33="Investor Owned",IF(AND(COUNTIF(Parameters!$A$4:$A$33,$G33)>0,COUNTIF(Parameters!$B$4:$B$33,$B33)=0),"procurement","cost_service"),"unclassified"))))))
A34: 2024 | B34: 40167 | C34: Somerset Rural Elec Coop, Inc | D34: A | E34: Bundled | F34: O | G34: PA | H34: Cooperative | I34: PJM | J34: 17484 | K34: 125202 | L34: 12322 | M34: 6517 | N34: 52872 | O34: 1578 | P34: 1695 | Q34: 17226 | R34: 3 | S34: . | T34: . | U34: . | V34: 25696 | W34: 195300 | X34: 13903 | Y34: =IF(ISNUMBER($W34),$W34,0) | Z34: =IF(ISNUMBER(SEARCH("Adjustment",$C34)),"excluded",IF($H34="Behind the Meter","excluded",IF(NOT(OR($E34="Bundled",$E34="Energy")),"excluded",IF(OR($H34="Retail Power Marketer",$H34="Community Choice Aggregator",$E34="Energy"),"procurement",IF(OR($H34="Municipal",$H34="Cooperative",$H34="Federal",$H34="State",$H34="Political Subdivision"),"cost_service",IF($H34="Investor Owned",IF(AND(COUNTIF(Parameters!$A$4:$A$33,$G34)>0,COUNTIF(Parameters!$B$4:$B$33,$B34)=0),"procurement","cost_service"),"unclassified"))))))
A35: 2024 | B35: 40220 | C35: Adams Electric Cooperative Inc | D35: A | E35: Bundled | F35: O | G35: PA | H35: Cooperative | I35: PJM | J35: 64263 | K35: 445525 | L35: 32231 | M35: 11393 | N35: 86441 | O35: 2289 | P35: 4368 | Q35: 42873 | R35: 14 | S35: . | T35: . | U35: . | V35: 80024 | W35: 574839 | X35: 34534 | Y35: =IF(ISNUMBER($W35),$W35,0) | Z35: =IF(ISNUMBER(SEARCH("Adjustment",$C35)),"excluded",IF($H35="Behind the Meter","excluded",IF(NOT(OR($E35="Bundled",$E35="Energy")),"excluded",IF(OR($H35="Retail Power Marketer",$H35="Community Choice Aggregator",$E35="Energy"),"procurement",IF(OR($H35="Municipal",$H35="Cooperative",$H35="Federal",$H35="State",$H35="Political Subdivision"),"cost_service",IF($H35="Investor Owned",IF(AND(COUNTIF(Parameters!$A$4:$A$33,$G35)>0,COUNTIF(Parameters!$B$4:$B$33,$B35)=0),"procurement","cost_service"),"unclassified"))))))
A36: 2024 | B36: 40221 | C36: Bedford Rural Elec Coop, Inc | D36: A | E36: Bundled | F36: O | G36: PA | H36: Cooperative | I36: PJM | J36: 14457 | K36: 99379 | L36: 8837 | M36: 3947 | N36: 31218 | O36: 743 | P36: 10568 | Q36: 100908 | R36: 2 | S36: . | T36: . | U36: . | V36: 28972 | W36: 231505 | X36: 9582 | Y36: =IF(ISNUMBER($W36),$W36,0) | Z36: =IF(ISNUMBER(SEARCH("Adjustment",$C36)),"excluded",IF($H36="Behind the Meter","excluded",IF(NOT(OR($E36="Bundled",$E36="Energy")),"excluded",IF(OR($H36="Retail Power Marketer",$H36="Community Choice Aggregator",$E36="Energy"),"procurement",IF(OR($H36="Municipal",$H36="Cooperative",$H36="Federal",$H36="State",$H36="Political Subdivision"),"cost_service",IF($H36="Investor Owned",IF(AND(COUNTIF(Parameters!$A$4:$A$33,$G36)>0,COUNTIF(Parameters!$B$4:$B$33,$B36)=0),"procurement","cost_service"),"unclassified"))))))
A37: 2024 | B37: 40222 | C37: Valley Rural Electric Coop Inc | D37: A | E37: Bundled | F37: O | G37: PA | H37: Cooperative | I37: PJM | J37: 30509 | K37: 205157 | L37: 18180 | M37: 10919 | N37: 76843 | O37: 4403 | P37: 489 | Q37: 3955 | R37: 2 | S37: . | T37: . | U37: . | V37: 41917 | W37: 285955 | X37: 22585 | Y37: =IF(ISNUMBER($W37),$W37,0) | Z37: =IF(ISNUMBER(SEARCH("Adjustment",$C37)),"excluded",IF($H37="Behind the Meter","excluded",IF(NOT(OR($E37="Bundled",$E37="Energy")),"excluded",IF(OR($H37="Retail Power Marketer",$H37="Community Choice Aggregator",$E37="Energy"),"procurement",IF(OR($H37="Municipal",$H37="Cooperative",$H37="Federal",$H37="State",$H37="Political Subdivision"),"cost_service",IF($H37="Investor Owned",IF(AND(COUNTIF(Parameters!$A$4:$A$33,$G37)>0,COUNTIF(Parameters!$B$4:$B$33,$B37)=0),"procurement","cost_service"),"unclassified"))))))
A38: 2024 | B38: 40224 | C38: Central Electric Coop, Inc - (PA) | D38: A | E38: Bundled | F38: O | G38: PA | H38: Cooperative | I38: PJM | J38: 36790 | K38: 216051 | L38: 23629 | M38: 9073 | N38: 65626 | O38: 1966 | P38: 2451 | Q38: 21309 | R38: 9 | S38: . | T38: . | U38: . | V38: 48314 | W38: 302986 | X38: 25604 | Y38: =IF(ISNUMBER($W38),$W38,0) | Z38: =IF(ISNUMBER(SEARCH("Adjustment",$C38)),"excluded",IF($H38="Behind the Meter","excluded",IF(NOT(OR($E38="Bundled",$E38="Energy")),"excluded",IF(OR($H38="Retail Power Marketer",$H38="Community Choice Aggregator",$E38="Energy"),"procurement",IF(OR($H38="Municipal",$H38="Cooperative",$H38="Federal",$H38="State",$H38="Political Subdivision"),"cost_service",IF($H38="Investor Owned",IF(AND(COUNTIF(Parameters!$A$4:$A$33,$G38)>0,COUNTIF(Parameters!$B$4:$B$33,$B38)=0),"procurement","cost_service"),"unclassified"))))))
A39: 2024 | B39: 40289 | C39: Claverack Rural Elec Coop Inc | D39: A | E39: Bundled | F39: O | G39: PA | H39: Cooperative | I39: PJM | J39: 30449 | K39: 166838 | L39: 16742 | M39: 9650 | N39: 70184 | O39: 2365 | P39: 7024 | Q39: 77359 | R39: 4 | S39: . | T39: . | U39: . | V39: 47123 | W39: 314381 | X39: 19111 | Y39: =IF(ISNUMBER($W39),$W39,0) | Z39: =IF(ISNUMBER(SEARCH("Adjustment",$C39)),"excluded",IF($H39="Behind the Meter","excluded",IF(NOT(OR($E39="Bundled",$E39="Energy")),"excluded",IF(OR($H39="Retail Power Marketer",$H39="Community Choice Aggregator",$E39="Energy"),"procurement",IF(OR($H39="Municipal",$H39="Cooperative",$H39="Federal",$H39="State",$H39="Political Subdivision"),"cost_service",IF($H39="Investor Owned",IF(AND(COUNTIF(Parameters!$A$4:$A$33,$G39)>0,COUNTIF(Parameters!$B$4:$B$33,$B39)=0),"procurement","cost_service"),"unclassified"))))))
A40: 2024 | B40: 40290 | C40: Tri-County Rural Elec Coop Inc (PA) | D40: A | E40: Bundled | F40: O | G40: PA | H40: Cooperative | I40: PJM | J40: 24934 | K40: 124161 | L40: 18206 | M40: 7686 | N40: 59371 | O40: 1352 | P40: 3121 | Q40: 33664 | R40: 4 | S40: . | T40: . | U40: . | V40: 35741 | W40: 217196 | X40: 19562 | Y40: =IF(ISNUMBER($W40),$W40,0) | Z40: =IF(ISNUMBER(SEARCH("Adjustment",$C40)),"excluded",IF($H40="Behind the Meter","excluded",IF(NOT(OR($E40="Bundled",$E40="Energy")),"excluded",IF(OR($H40="Retail Power Marketer",$H40="Community Choice Aggregator",$E40="Energy"),"procurement",IF(OR($H40="Municipal",$H40="Cooperative",$H40="Federal",$H40="State",$H40="Political Subdivision"),"cost_service",IF($H40="Investor Owned",IF(AND(COUNTIF(Parameters!$A$4:$A$33,$G40)>0,COUNTIF(Parameters!$B$4:$B$33,$B40)=0),"procurement","cost_service"),"unclassified"))))))
A41: 2024 | B41: 40292 | C41: REA Energy Coop Inc | D41: A | E41: Bundled | F41: O | G41: PA | H41: Cooperative | I41: PJM | J41: 33963 | K41: 233726 | L41: 20932 | M41: 8050 | N41: 64486 | O41: 1891 | P41: 9275 | Q41: 81845 | R41: 13 | S41: . | T41: . | U41: . | V41: 51288 | W41: 380057 | X41: 22836 | Y41: =IF(ISNUMBER($W41),$W41,0) | Z41: =IF(ISNUMBER(SEARCH("Adjustment",$C41)),"excluded",IF($H41="Behind the Meter","excluded",IF(NOT(OR($E41="Bundled",$E41="Energy")),"excluded",IF(OR($H41="Retail Power Marketer",$H41="Community Choice Aggregator",$E41="Energy"),"procurement",IF(OR($H41="Municipal",$H41="Cooperative",$H41="Federal",$H41="State",$H41="Political Subdivision"),"cost_service",IF($H41="Investor Owned",IF(AND(COUNTIF(Parameters!$A$4:$A$33,$G41)>0,COUNTIF(Parameters!$B$4:$B$33,$B41)=0),"procurement","cost_service"),"unclassified"))))))
A42: 2024 | B42: 40293 | C42: Northwestern Rural E C A, Inc - (PA) | D42: A | E42: Bundled | F42: O | G42: PA | H42: Cooperative | I42: PJM | J42: 30333 | K42: 194697 | L42: 18190 | M42: 6260 | N42: 43111 | O42: 1428 | P42: 1099 | Q42: 10760 | R42: 3 | S42: . | T42: . | U42: . | V42: 37692 | W42: 248568 | X42: 19621 | Y42: =IF(ISNUMBER($W42),$W42,0) | Z42: =IF(ISNUMBER(SEARCH("Adjustment",$C42)),"excluded",IF($H42="Behind the Meter","excluded",IF(NOT(OR($E42="Bundled",$E42="Energy")),"excluded",IF(OR($H42="Retail Power Marketer",$H42="Community Choice Aggregator",$E42="Energy"),"procurement",IF(OR($H42="Municipal",$H42="Cooperative",$H42="Federal",$H42="State",$H42="Political Subdivision"),"cost_service",IF($H42="Investor Owned",IF(AND(COUNTIF(Parameters!$A$4:$A$33,$G42)>0,COUNTIF(Parameters!$B$4:$B$33,$B42)=0),"procurement","cost_service"),"unclassified"))))))
A43: 2024 | B43: 49730 | C43: American PowerNet | D43: B | E43: Energy | F43: O | G43: PA | H43: Retail Power Marketer | I43: PJM | J43: 0 | K43: 0 | L43: 0 | M43: 26552.7 | N43: 442499 | O43: 14 | P43: 14050.6 | Q43: 224081 | R43: 6 | S43: 0 | T43: 0 | U43: 0 | V43: 40603.3 | W43: 666580 | X43: 20 | Y43: =IF(ISNUMBER($W43),$W43,0) | Z43: =IF(ISNUMBER(SEARCH("Adjustment",$C43)),"excluded",IF($H43="Behind the Meter","excluded",IF(NOT(OR($E43="Bundled",$E43="Energy")),"excluded",IF(OR($H43="Retail Power Marketer",$H43="Community Choice Aggregator",$E43="Energy"),"procurement",IF(OR($H43="Municipal",$H43="Cooperative",$H43="Federal",$H43="State",$H43="Political Subdivision"),"cost_service",IF($H43="Investor Owned",IF(AND(COUNTIF(Parameters!$A$4:$A$33,$G43)>0,COUNTIF(Parameters!$B$4:$B$33,$B43)=0),"procurement","cost_service"),"unclassified"))))))
A44: 2024 | B44: 49746 | C44: The Energy Coop | D44: B | E44: Energy | F44: O | G44: PA | H44: Cooperative | I44: PJM | J44: 2594.4 | K44: 18866 | L44: 2515 | M44: 240.7 | N44: 1794 | O44: 144 | P44: 0 | Q44: 0 | R44: 0 | S44: 0 | T44: 0 | U44: 0 | V44: 2835.1 | W44: 20660 | X44: 2659 | Y44: =IF(ISNUMBER($W44),$W44,0) | Z44: =IF(ISNUMBER(SEARCH("Adjustment",$C44)),"excluded",IF($H44="Behind the Meter","excluded",IF(NOT(OR($E44="Bundled",$E44="Energy")),"excluded",IF(OR($H44="Retail Power Marketer",$H44="Community Choice Aggregator",$E44="Energy"),"procurement",IF(OR($H44="Municipal",$H44="Cooperative",$H44="Federal",$H44="State",$H44="Political Subdivision"),"cost_service",IF($H44="Investor Owned",IF(AND(COUNTIF(Parameters!$A$4:$A$33,$G44)>0,COUNTIF(Parameters!$B$4:$B$33,$B44)=0),"procurement","cost_service"),"unclassified"))))))
A45: 2024 | B45: 50046 | C45: Texas Retail Energy, LLC | D45: B | E45: Energy | F45: O | G45: PA | H45: Retail Power Marketer | I45: PJM | J45: 0 | K45: 0 | L45: 0 | M45: 39085.2 | N45: 552152 | O45: 217 | P45: 0 | Q45: 0 | R45: 0 | S45: 0 | T45: 0 | U45: 0 | V45: 39085.2 | W45: 552152 | X45: 217 | Y45: =IF(ISNUMBER($W45),$W45,0) | Z45: =IF(ISNUMBER(SEARCH("Adjustment",$C45)),"excluded",IF($H45="Behind the Meter","excluded",IF(NOT(OR($E45="Bundled",$E45="Energy")),"excluded",IF(OR($H45="Retail Power Marketer",$H45="Community Choice Aggregator",$E45="Energy"),"procurement",IF(OR($H45="Municipal",$H45="Cooperative",$H45="Federal",$H45="State",$H45="Political Subdivision"),"cost_service",IF($H45="Investor Owned",IF(AND(COUNTIF(Parameters!$A$4:$A$33,$G45)>0,COUNTIF(Parameters!$B$4:$B$33,$B45)=0),"procurement","cost_service"),"unclassified"))))))
A46: 2024 | B46: 50153 | C46: APN Starfirst, L.P. | D46: B | E46: Energy | F46: O | G46: PA | H46: Retail Power Marketer | I46: PJM | J46: 0 | K46: 0 | L46: 0 | M46: 0 | N46: 0 | O46: 0 | P46: 2036.7 | Q46: 41301 | R46: 3 | S46: 0 | T46: 0 | U46: 0 | V46: 2036.7 | W46: 41301 | X46: 3 | Y46: =IF(ISNUMBER($W46),$W46,0) | Z46: =IF(ISNUMBER(SEARCH("Adjustment",$C46)),"excluded",IF($H46="Behind the Meter","excluded",IF(NOT(OR($E46="Bundled",$E46="Energy")),"excluded",IF(OR($H46="Retail Power Marketer",$H46="Community Choice Aggregator",$E46="Energy"),"procurement",IF(OR($H46="Municipal",$H46="Cooperative",$H46="Federal",$H46="State",$H46="Political Subdivision"),"cost_service",IF($H46="Investor Owned",IF(AND(COUNTIF(Parameters!$A$4:$A$33,$G46)>0,COUNTIF(Parameters!$B$4:$B$33,$B46)=0),"procurement","cost_service"),"unclassified"))))))
A47: 2024 | B47: 54820 | C47: Direct Energy Services | D47: B | E47: Energy | F47: O | G47: PA | H47: Retail Power Marketer | I47: NYIS | J47: 667.8 | K47: 5283 | L47: 717 | M47: 691.8 | N47: 7049 | O47: 113 | P47: 0 | Q47: 0 | R47: 0 | S47: 0 | T47: 0 | U47: 0 | V47: 1359.6 | W47: 12332 | X47: 830 | Y47: =IF(ISNUMBER($W47),$W47,0) | Z47: =IF(ISNUMBER(SEARCH("Adjustment",$C47)),"excluded",IF($H47="Behind the Meter","excluded",IF(NOT(OR($E47="Bundled",$E47="Energy")),"excluded",IF(OR($H47="Retail Power Marketer",$H47="Community Choice Aggregator",$E47="Energy"),"procurement",IF(OR($H47="Municipal",$H47="Cooperative",$H47="Federal",$H47="State",$H47="Political Subdivision"),"cost_service",IF($H47="Investor Owned",IF(AND(COUNTIF(Parameters!$A$4:$A$33,$G47)>0,COUNTIF(Parameters!$B$4:$B$33,$B47)=0),"procurement","cost_service"),"unclassified"))))))
A48: 2024 | B48: 54820 | C48: Direct Energy Services | D48: B | E48: Energy | F48: O | G48: PA | H48: Retail Power Marketer | I48: PJM | J48: 89536.5 | K48: 888673 | L48: 77715 | M48: 7912.1 | N48: 81644 | O48: 5677 | P48: 0 | Q48: 0 | R48: 0 | S48: 0 | T48: 0 | U48: 0 | V48: 97448.6 | W48: 970317 | X48: 83392 | Y48: =IF(ISNUMBER($W48),$W48,0) | Z48: =IF(ISNUMBER(SEARCH("Adjustment",$C48)),"excluded",IF($H48="Behind the Meter","excluded",IF(NOT(OR($E48="Bundled",$E48="Energy")),"excluded",IF(OR($H48="Retail Power Marketer",$H48="Community Choice Aggregator",$E48="Energy"),"procurement",IF(OR($H48="Municipal",$H48="Cooperative",$H48="Federal",$H48="State",$H48="Political Subdivision"),"cost_service",IF($H48="Investor Owned",IF(AND(COUNTIF(Parameters!$A$4:$A$33,$G48)>0,COUNTIF(Parameters!$B$4:$B$33,$B48)=0),"procurement","cost_service"),"unclassified"))))))
A49: 2024 | B49: 54862 | C49: Champion Energy Services | D49: B | E49: Energy | F49: O | G49: PA | H49: Retail Power Marketer | I49: PJM | J49: 0 | K49: 0 | L49: 0 | M49: 55114.9 | N49: 1142452 | O49: 2705 | P49: 0 | Q49: 0 | R49: 0 | S49: 0 | T49: 0 | U49: 0 | V49: 55114.9 | W49: 1142452 | X49: 2705 | Y49: =IF(ISNUMBER($W49),$W49,0) | Z49: =IF(ISNUMBER(SEARCH("Adjustment",$C49)),"excluded",IF($H49="Behind the Meter","excluded",IF(NOT(OR($E49="Bundled",$E49="Energy")),"excluded",IF(OR($H49="Retail Power Marketer",$H49="Community Choice Aggregator",$E49="Energy"),"procurement",IF(OR($H49="Municipal",$H49="Cooperative",$H49="Federal",$H49="State",$H49="Political Subdivision"),"cost_service",IF($H49="Investor Owned",IF(AND(COUNTIF(Parameters!$A$4:$A$33,$G49)>0,COUNTIF(Parameters!$B$4:$B$33,$B49)=0),"procurement","cost_service"),"unclassified"))))))
A50: 2024 | B50: 55722 | C50: AEP Energy | D50: B | E50: Energy | F50: O | G50: PA | H50: Retail Power Marketer | I50: PJM | J50: 104263.6 | K50: 1122832 | L50: 89725 | M50: 167973.3 | N50: 2661455 | O50: 8263 | P50: 0 | Q50: 0 | R50: 0 | S50: 0 | T50: 0 | U50: 0 | V50: 272236.9 | W50: 3784287 | X50: 97988 | Y50: =IF(ISNUMBER($W50),$W50,0) | Z50: =IF(ISNUMBER(SEARCH("Adjustment",$C50)),"excluded",IF($H50="Behind the Meter","excluded",IF(NOT(OR($E50="Bundled",$E50="Energy")),"excluded",IF(OR($H50="Retail Power Marketer",$H50="Community Choice Aggregator",$E50="Energy"),"procurement",IF(OR($H50="Municipal",$H50="Cooperative",$H50="Federal",$H50="State",$H50="Political Subdivision"),"cost_service",IF($H50="Investor Owned",IF(AND(COUNTIF(Parameters!$A$4:$A$33,$G50)>0,COUNTIF(Parameters!$B$4:$B$33,$B50)=0),"procurement","cost_service"),"unclassified"))))))
A51: 2024 | B51: 55815 | C51: IDT Energy, Inc. | D51: B | E51: Energy | F51: O | G51: PA | H51: Retail Power Marketer | I51: PJM | J51: 9697.8 | K51: 62215 | L51: 8055 | M51: 1217.7 | N51: 9006 | O51: 583 | P51: 0 | Q51: 0 | R51: 0 | S51: 0 | T51: 0 | U51: 0 | V51: 10915.5 | W51: 71221 | X51: 8638 | Y51: =IF(ISNUMBER($W51),$W51,0) | Z51: =IF(ISNUMBER(SEARCH("Adjustment",$C51)),"excluded",IF($H51="Behind the Meter","excluded",IF(NOT(OR($E51="Bundled",$E51="Energy")),"excluded",IF(OR($H51="Retail Power Marketer",$H51="Community Choice Aggregator",$E51="Energy"),"procurement",IF(OR($H51="Municipal",$H51="Cooperative",$H51="Federal",$H51="State",$H51="Political Subdivision"),"cost_service",IF($H51="Investor Owned",IF(AND(COUNTIF(Parameters!$A$4:$A$33,$G51)>0,COUNTIF(Parameters!$B$4:$B$33,$B51)=0),"procurement","cost_service"),"unclassified"))))))
A52: 2024 | B52: 55874 | C52: Energy Services Providers, Inc | D52: B | E52: Energy | F52: O | G52: PA | H52: Retail Power Marketer | I52: PJM | J52: 22360.9 | K52: 180759 | L52: 18092 | M52: 3126.3 | N52: 24798 | O52: 1166 | P52: 0 | Q52: 0 | R52: 0 | S52: 0 | T52: 0 | U52: 0 | V52: 25487.2 | W52: 205557 | X52: 19258 | Y52: =IF(ISNUMBER($W52),$W52,0) | Z52: =IF(ISNUMBER(SEARCH("Adjustment",$C52)),"excluded",IF($H52="Behind the Meter","excluded",IF(NOT(OR($E52="Bundled",$E52="Energy")),"excluded",IF(OR($H52="Retail Power Marketer",$H52="Community Choice Aggregator",$E52="Energy"),"procurement",IF(OR($H52="Municipal",$H52="Cooperative",$H52="Federal",$H52="State",$H52="Political Subdivision"),"cost_service",IF($H52="Investor Owned",IF(AND(COUNTIF(Parameters!$A$4:$A$33,$G52)>0,COUNTIF(Parameters!$B$4:$B$33,$B52)=0),"procurement","cost_service"),"unclassified"))))))
A53: 2024 | B53: 55878 | C53: Hudson Energy Services | D53: B | E53: Energy | F53: O | G53: PA | H53: Retail Power Marketer | I53: PJM | J53: 0 | K53: 0 | L53: 0 | M53: 30912.5 | N53: 375183 | O53: 4710 | P53: 0 | Q53: 0 | R53: 0 | S53: 0 | T53: 0 | U53: 0 | V53: 30912.5 | W53: 375183 | X53: 4710 | Y53: =IF(ISNUMBER($W53),$W53,0) | Z53: =IF(ISNUMBER(SEARCH("Adjustment",$C53)),"excluded",IF($H53="Behind the Meter","excluded",IF(NOT(OR($E53="Bundled",$E53="Energy")),"excluded",IF(OR($H53="Retail Power Marketer",$H53="Community Choice Aggregator",$E53="Energy"),"procurement",IF(OR($H53="Municipal",$H53="Cooperative",$H53="Federal",$H53="State",$H53="Political Subdivision"),"cost_service",IF($H53="Investor Owned",IF(AND(COUNTIF(Parameters!$A$4:$A$33,$G53)>0,COUNTIF(Parameters!$B$4:$B$33,$B53)=0),"procurement","cost_service"),"unclassified"))))))
A54: 2024 | B54: 56212 | C54: Ambit Energy Holdings, LLC | D54: B | E54: Energy | F54: O | G54: PA | H54: Retail Power Marketer | I54: PJM | J54: 24300.5 | K54: 182135 | L54: 17027 | M54: 6435.2 | N54: 66402 | O54: 3323 | P54: 0 | Q54: 0 | R54: 0 | S54: 0 | T54: 0 | U54: 0 | V54: 30735.7 | W54: 248537 | X54: 20350 | Y54: =IF(ISNUMBER($W54),$W54,0) | Z54: =IF(ISNUMBER(SEARCH("Adjustment",$C54)),"excluded",IF($H54="Behind the Meter","excluded",IF(NOT(OR($E54="Bundled",$E54="Energy")),"excluded",IF(OR($H54="Retail Power Marketer",$H54="Community Choice Aggregator",$E54="Energy"),"procurement",IF(OR($H54="Municipal",$H54="Cooperative",$H54="Federal",$H54="State",$H54="Political Subdivision"),"cost_service",IF($H54="Investor Owned",IF(AND(COUNTIF(Parameters!$A$4:$A$33,$G54)>0,COUNTIF(Parameters!$B$4:$B$33,$B54)=0),"procurement","cost_service"),"unclassified"))))))
... A56: 2024 | B56: 56265 | C56: Energy Plus Holdings LLC | D56: B | E56: Energy | F56: O | G56: PA | H56: Retail Power Marketer | I56: PJM | J56: 21440.7 | K56: 157470 | L56: 16977 | M56: 1090.6 | N56: 8011 | O56: 559 | P56: 0 | Q56: 0 | R56: 0 | S56: 0 | T56: 0 | U56: 0 | V56: 22531.3 | W56: 165481 | X56: 17536 | Y56: =IF(ISNUMBER($W56),$W56,0) | Z56: =IF(ISNUMBER(SEARCH("Adjustment",$C56)),"excluded",IF($H56="Behind the Meter","excluded",IF(NOT(OR($E56="Bundled",$E56="Energy")),"excluded",IF(OR($H56="Retail Power Marketer",$H56="Community Choice Aggregator",$E56="Energy"),"procurement",IF(OR($H56="Municipal",$H56="Cooperative",$H56="Federal",$H56="State",$H56="Political Subdivision"),"cost_service",IF($H56="Investor Owned",IF(AND(COUNTIF(Parameters!$A$4:$A$33,$G56)>0,COUNTIF(Parameters!$B$4:$B$33,$B56)=0),"procurement","cost_service"),"unclassified"))))))
A57: 2024 | B57: 56286 | C57: Frontier Utilities, LLC | D57: B | E57: Energy | F57: O | G57: PA | H57: Retail Power Marketer | I57: PJM | J57: 18072.4 | K57: 142607 | L57: 10754 | M57: 13.8 | N57: 78 | O57: 2 | P57: . | Q57: . | R57: . | S57: . | T57: . | U57: . | V57: 18086.2 | W57: 142685 | X57: 10756 | Y57: =IF(ISNUMBER($W57),$W57,0) | Z57: =IF(ISNUMBER(SEARCH("Adjustment",$C57)),"excluded",IF($H57="Behind the Meter","excluded",IF(NOT(OR($E57="Bundled",$E57="Energy")),"excluded",IF(OR($H57="Retail Power Marketer",$H57="Community Choice Aggregator",$E57="Energy"),"procurement",IF(OR($H57="Municipal",$H57="Cooperative",$H57="Federal",$H57="State",$H57="Political Subdivision"),"cost_service",IF($H57="Investor Owned",IF(AND(COUNTIF(Parameters!$A$4:$A$33,$G57)>0,COUNTIF(Parameters!$B$4:$B$33,$B57)=0),"procurement","cost_service"),"unclassified"))))))
A58: 2024 | B58: 56408 | C58: UGI Energy Services, LLC | D58: B | E58: Energy | F58: O | G58: PA | H58: Retail Power Marketer | I58: PJM | J58: 354.3 | K58: 4028 | L58: 537 | M58: 56154.3 | N58: 698430 | O58: 2482 | P58: 35877.4 | Q58: 466952 | R58: 475 | S58: 0 | T58: 0 | U58: 0 | V58: 92386 | W58: 1169410 | X58: 3494 | Y58: =IF(ISNUMBER($W58),$W58,0) | Z58: =IF(ISNUMBER(SEARCH("Adjustment",$C58)),"excluded",IF($H58="Behind the Meter","excluded",IF(NOT(OR($E58="Bundled",$E58="Energy")),"excluded",IF(OR($H58="Retail Power Marketer",$H58="Community Choice Aggregator",$E58="Energy"),"procurement",IF(OR($H58="Municipal",$H58="Cooperative",$H58="Federal",$H58="State",$H58="Political Subdivision"),"cost_service",IF($H58="Investor Owned",IF(AND(COUNTIF(Parameters!$A$4:$A$33,$G58)>0,COUNTIF(Parameters!$B$4:$B$33,$B58)=0),"procurement","cost_service"),"unclassified"))))))
A59: 2024 | B59: 56571 | C59: AP Holdings LLC | D59: B | E59: Energy | F59: O | G59: PA | H59: Retail Power Marketer | I59: PJM | J59: 18411.1 | K59: 169032 | L59: 16050 | M59: 23651.4 | N59: 251617 | O59: 4060 | P59: 0 | Q59: 0 | R59: 0 | S59: 0 | T59: 0 | U59: 0 | V59: 42062.5 | W59: 420649 | X59: 20110 | Y59: =IF(ISNUMBER($W59),$W59,0) | Z59: =IF(ISNUMBER(SEARCH("Adjustment",$C59)),"excluded",IF($H59="Behind the Meter","excluded",IF(NOT(OR($E59="Bundled",$E59="Energy")),"excluded",IF(OR($H59="Retail Power Marketer",$H59="Community Choice Aggregator",$E59="Energy"),"procurement",IF(OR($H59="Municipal",$H59="Cooperative",$H59="Federal",$H59="State",$H59="Political Subdivision"),"cost_service",IF($H59="Investor Owned",IF(AND(COUNTIF(Parameters!$A$4:$A$33,$G59)>0,COUNTIF(Parameters!$B$4:$B$33,$B59)=0),"procurement","cost_service"),"unclassified"))))))
A60: 2024 | B60: 56573 | C60: Palmco Power PA, LLC | D60: B | E60: Energy | F60: O | G60: PA | H60: Retail Power Marketer | I60: PJM | J60: 8420.7 | K60: 46634 | L60: 7072 | M60: 923.9 | N60: 8226 | O60: 175 | P60: 0 | Q60: 0 | R60: 0 | S60: 0 | T60: 0 | U60: 0 | V60: 9344.6 | W60: 54860 | X60: 7247 | Y60: =IF(ISNUMBER($W60),$W60,0) | Z60: =IF(ISNUMBER(SEARCH("Adjustment",$C60)),"excluded",IF($H60="Behind the Meter","excluded",IF(NOT(OR($E60="Bundled",$E60="Energy")),"excluded",IF(OR($H60="Retail Power Marketer",$H60="Community Choice Aggregator",$E60="Energy"),"procurement",IF(OR($H60="Municipal",$H60="Cooperative",$H60="Federal",$H60="State",$H60="Political Subdivision"),"cost_service",IF($H60="Investor Owned",IF(AND(COUNTIF(Parameters!$A$4:$A$33,$G60)>0,COUNTIF(Parameters!$B$4:$B$33,$B60)=0),"procurement","cost_service"),"unclassified"))))))
A61: 2024 | B61: 56737 | C61: Stream Energy Pennsylvania, LLC | D61: B | E61: Energy | F61: O | G61: PA | H61: Retail Power Marketer | I61: PJM | J61: 26890.2 | K61: 201547 | L61: 20591 | M61: 4045.6 | N61: 38456 | O61: 1067 | P61: 0 | Q61: 0 | R61: 0 | S61: 0 | T61: 0 | U61: 0 | V61: 30935.8 | W61: 240003 | X61: 21658 | Y61: =IF(ISNUMBER($W61),$W61,0) | Z61: =IF(ISNUMBER(SEARCH("Adjustment",$C61)),"excluded",IF($H61="Behind the Meter","excluded",IF(NOT(OR($E61="Bundled",$E61="Energy")),"excluded",IF(OR($H61="Retail Power Marketer",$H61="Community Choice Aggregator",$E61="Energy"),"procurement",IF(OR($H61="Municipal",$H61="Cooperative",$H61="Federal",$H61="State",$H61="Political Subdivision"),"cost_service",IF($H61="Investor Owned",IF(AND(COUNTIF(Parameters!$A$4:$A$33,$G61)>0,COUNTIF(Parameters!$B$4:$B$33,$B61)=0),"procurement","cost_service"),"unclassified"))))))
A62: 2024 | B62: 57037 | C62: Reliant Energy Northeast LLC | D62: B | E62: Energy | F62: O | G62: PA | H62: Retail Power Marketer | I62: PJM | J62: 183256 | K62: 1385072 | L62: 142526 | M62: 3904 | N62: 25290 | O62: 2019 | P62: 7059.3 | Q62: 115381 | R62: 17 | S62: 0 | T62: 0 | U62: 0 | V62: 194219.3 | W62: 1525743 | X62: 144562 | Y62: =IF(ISNUMBER($W62),$W62,0) | Z62: =IF(ISNUMBER(SEARCH("Adjustment",$C62)),"excluded",IF($H62="Behind the Meter","excluded",IF(NOT(OR($E62="Bundled",$E62="Energy")),"excluded",IF(OR($H62="Retail Power Marketer",$H62="Community Choice Aggregator",$E62="Energy"),"procurement",IF(OR($H62="Municipal",$H62="Cooperative",$H62="Federal",$H62="State",$H62="Political Subdivision"),"cost_service",IF($H62="Investor Owned",IF(AND(COUNTIF(Parameters!$A$4:$A$33,$G62)>0,COUNTIF(Parameters!$B$4:$B$33,$B62)=0),"procurement","cost_service"),"unclassified"))))))
A63: 2024 | B63: 57307 | C63: ENGIE Power & Gas LLC | D63: B | E63: Energy | F63: O | G63: PA | H63: Retail Power Marketer | I63: PJM | J63: 229.3 | K63: 1362 | L63: 178 | M63: 256.7 | N63: 2720 | O63: 38 | P63: 0 | Q63: 0 | R63: 0 | S63: 0 | T63: 0 | U63: 0 | V63: 486 | W63: 4082 | X63: 216 | Y63: =IF(ISNUMBER($W63),$W63,0) | Z63: =IF(ISNUMBER(SEARCH("Adjustment",$C63)),"excluded",IF($H63="Behind the Meter","excluded",IF(NOT(OR($E63="Bundled",$E63="Energy")),"excluded",IF(OR($H63="Retail Power Marketer",$H63="Community Choice Aggregator",$E63="Energy"),"procurement",IF(OR($H63="Municipal",$H63="Cooperative",$H63="Federal",$H63="State",$H63="Political Subdivision"),"cost_service",IF($H63="Investor Owned",IF(AND(COUNTIF(Parameters!$A$4:$A$33,$G63)>0,COUNTIF(Parameters!$B$4:$B$33,$B63)=0),"procurement","cost_service"),"unclassified"))))))
A64: 2024 | B64: 57313 | C64: Tesla Inc. | D64: A | E64: Bundled | F64: O | G64: PA | H64: Behind the Meter | I64: PJM | J64: 7546 | K64: 50653 | L64: 6956 | M64: 119 | N64: 1539 | O64: 8 | P64: 0 | Q64: 0 | R64: 0 | S64: 0 | T64: 0 | U64: 0 | V64: 7665 | W64: 52192 | X64: 6964 | Y64: =IF(ISNUMBER($W64),$W64,0) | Z64: =IF(ISNUMBER(SEARCH("Adjustment",$C64)),"excluded",IF($H64="Behind the Meter","excluded",IF(NOT(OR($E64="Bundled",$E64="Energy")),"excluded",IF(OR($H64="Retail Power Marketer",$H64="Community Choice Aggregator",$E64="Energy"),"procurement",IF(OR($H64="Municipal",$H64="Cooperative",$H64="Federal",$H64="State",$H64="Political Subdivision"),"cost_service",IF($H64="Investor Owned",IF(AND(COUNTIF(Parameters!$A$4:$A$33,$G64)>0,COUNTIF(Parameters!$B$4:$B$33,$B64)=0),"procurement","cost_service"),"unclassified"))))))
A65: 2024 | B65: 57453 | C65: Independence Energy Group LLC | D65: B | E65: Energy | F65: O | G65: PA | H65: Retail Power Marketer | I65: PJM | J65: 2566.2 | K65: 19402 | L65: 1857 | M65: 0 | N65: 0 | O65: 0 | P65: 0 | Q65: 0 | R65: 0 | S65: 0 | T65: 0 | U65: 0 | V65: 2566.2 | W65: 19402 | X65: 1857 | Y65: =IF(ISNUMBER($W65),$W65,0) | Z65: =IF(ISNUMBER(SEARCH("Adjustment",$C65)),"excluded",IF($H65="Behind the Meter","excluded",IF(NOT(OR($E65="Bundled",$E65="Energy")),"excluded",IF(OR($H65="Retail Power Marketer",$H65="Community Choice Aggregator",$E65="Energy"),"procurement",IF(OR($H65="Municipal",$H65="Cooperative",$H65="Federal",$H65="State",$H65="Political Subdivision"),"cost_service",IF($H65="Investor Owned",IF(AND(COUNTIF(Parameters!$A$4:$A$33,$G65)>0,COUNTIF(Parameters!$B$4:$B$33,$B65)=0),"procurement","cost_service"),"unclassified"))))))
A66: 2024 | B66: 58118 | C66: Public Power LLC (PA) | D66: B | E66: Energy | F66: O | G66: PA | H66: Retail Power Marketer | I66: PJM | J66: 5879.5 | K66: 60904 | L66: 6862 | M66: 7187.5 | N66: 63746 | O66: 1164 | P66: 0 | Q66: 0 | R66: 0 | S66: 0 | T66: 0 | U66: 0 | V66: 13067 | W66: 124650 | X66: 8026 | Y66: =IF(ISNUMBER($W66),$W66,0) | Z66: =IF(ISNUMBER(SEARCH("Adjustment",$C66)),"excluded",IF($H66="Behind the Meter","excluded",IF(NOT(OR($E66="Bundled",$E66="Energy")),"excluded",IF(OR($H66="Retail Power Marketer",$H66="Community Choice Aggregator",$E66="Energy"),"procurement",IF(OR($H66="Municipal",$H66="Cooperative",$H66="Federal",$H66="State",$H66="Political Subdivision"),"cost_service",IF($H66="Investor Owned",IF(AND(COUNTIF(Parameters!$A$4:$A$33,$G66)>0,COUNTIF(Parameters!$B$4:$B$33,$B66)=0),"procurement","cost_service"),"unclassified"))))))
A67: 2024 | B67: 58162 | C67: Viridian Energy PA LLC | D67: B | E67: Energy | F67: O | G67: PA | H67: Retail Power Marketer | I67: PJM | J67: 1284.7 | K67: 8481 | L67: 1373 | M67: 802.8 | N67: 5353 | O67: 191 | P67: 0 | Q67: 0 | R67: 0 | S67: 0 | T67: 0 | U67: 0 | V67: 2087.5 | W67: 13834 | X67: 1564 | Y67: =IF(ISNUMBER($W67),$W67,0) | Z67: =IF(ISNUMBER(SEARCH("Adjustment",$C67)),"excluded",IF($H67="Behind the Meter","excluded",IF(NOT(OR($E67="Bundled",$E67="Energy")),"excluded",IF(OR($H67="Retail Power Marketer",$H67="Community Choice Aggregator",$E67="Energy"),"procurement",IF(OR($H67="Municipal",$H67="Cooperative",$H67="Federal",$H67="State",$H67="Political Subdivision"),"cost_service",IF($H67="Investor Owned",IF(AND(COUNTIF(Parameters!$A$4:$A$33,$G67)>0,COUNTIF(Parameters!$B$4:$B$33,$B67)=0),"procurement","cost_service"),"unclassified"))))))
A68: 2024 | B68: 58339 | C68: XOOM Energy Pennsylvania, LLC | D68: B | E68: Energy | F68: O | G68: PA | H68: Retail Power Marketer | I68: PJM | J68: 15022 | K68: 136044 | L68: 12172 | M68: 7115 | N68: 64071 | O68: 2621 | P68: 0 | Q68: 0 | R68: 0 | S68: 0 | T68: 0 | U68: 0 | V68: 22137 | W68: 200115 | X68: 14793 | Y68: =IF(ISNUMBER($W68),$W68,0) | Z68: =IF(ISNUMBER(SEARCH("Adjustment",$C68)),"excluded",IF($H68="Behind the Meter","excluded",IF(NOT(OR($E68="Bundled",$E68="Energy")),"excluded",IF(OR($H68="Retail Power Marketer",$H68="Community Choice Aggregator",$E68="Energy"),"procurement",IF(OR($H68="Municipal",$H68="Cooperative",$H68="Federal",$H68="State",$H68="Political Subdivision"),"cost_service",IF($H68="Investor Owned",IF(AND(COUNTIF(Parameters!$A$4:$A$33,$G68)>0,COUNTIF(Parameters!$B$4:$B$33,$B68)=0),"procurement","cost_service"),"unclassified"))))))
A69: 2024 | B69: 58663 | C69: Respond Power LLC | D69: B | E69: Energy | F69: O | G69: PA | H69: Retail Power Marketer | I69: PJM | J69: 30799 | K69: 282689 | L69: 24648 | M69: 3339 | N69: 30078 | O69: 865 | P69: 0 | Q69: 0 | R69: 0 | S69: 0 | T69: 0 | U69: 0 | V69: 34138 | W69: 312767 | X69: 25513 | Y69: =IF(ISNUMBER($W69),$W69,0) | Z69: =IF(ISNUMBER(SEARCH("Adjustment",$C69)),"excluded",IF($H69="Behind the Meter","excluded",IF(NOT(OR($E69="Bundled",$E69="Energy")),"excluded",IF(OR($H69="Retail Power Marketer",$H69="Community Choice Aggregator",$E69="Energy"),"procurement",IF(OR($H69="Municipal",$H69="Cooperative",$H69="Federal",$H69="State",$H69="Political Subdivision"),"cost_service",IF($H69="Investor Owned",IF(AND(COUNTIF(Parameters!$A$4:$A$33,$G69)>0,COUNTIF(Parameters!$B$4:$B$33,$B69)=0),"procurement","cost_service"),"unclassified"))))))
... A72: 2024 | B72: 58952 | C72: Tomorrow Energy Corp. | D72: B | E72: Energy | F72: O | G72: PA | H72: Retail Power Marketer | I72: PJM | J72: 21294.4 | K72: 138215 | L72: 15646 | M72: 274.5 | N72: 1010 | O72: 99 | P72: 0 | Q72: 0 | R72: 0 | S72: 0 | T72: 0 | U72: 0 | V72: 21568.9 | W72: 139225 | X72: 15745 | Y72: =IF(ISNUMBER($W72),$W72,0) | Z72: =IF(ISNUMBER(SEARCH("Adjustment",$C72)),"excluded",IF($H72="Behind the Meter","excluded",IF(NOT(OR($E72="Bundled",$E72="Energy")),"excluded",IF(OR($H72="Retail Power Marketer",$H72="Community Choice Aggregator",$E72="Energy"),"procurement",IF(OR($H72="Municipal",$H72="Cooperative",$H72="Federal",$H72="State",$H72="Political Subdivision"),"cost_service",IF($H72="Investor Owned",IF(AND(COUNTIF(Parameters!$A$4:$A$33,$G72)>0,COUNTIF(Parameters!$B$4:$B$33,$B72)=0),"procurement","cost_service"),"unclassified"))))))
A73: 2024 | B73: 58956 | C73: SmartEnergy Holdings, LLC | D73: B | E73: Energy | F73: O | G73: PA | H73: Retail Power Marketer | I73: PJM | J73: 49055 | K73: 355206 | L73: 47969 | M73: . | N73: . | O73: . | P73: . | Q73: . | R73: . | S73: . | T73: . | U73: . | V73: 49055 | W73: 355206 | X73: 47969 | Y73: =IF(ISNUMBER($W73),$W73,0) | Z73: =IF(ISNUMBER(SEARCH("Adjustment",$C73)),"excluded",IF($H73="Behind the Meter","excluded",IF(NOT(OR($E73="Bundled",$E73="Energy")),"excluded",IF(OR($H73="Retail Power Marketer",$H73="Community Choice Aggregator",$E73="Energy"),"procurement",IF(OR($H73="Municipal",$H73="Cooperative",$H73="Federal",$H73="State",$H73="Political Subdivision"),"cost_service",IF($H73="Investor Owned",IF(AND(COUNTIF(Parameters!$A$4:$A$33,$G73)>0,COUNTIF(Parameters!$B$4:$B$33,$B73)=0),"procurement","cost_service"),"unclassified"))))))
A74: 2024 | B74: 58957 | C74: Interstate Gas Supply, Inc. | D74: B | E74: Energy | F74: O | G74: PA | H74: Retail Power Marketer | I74: PJM | J74: 63871 | K74: 495627 | L74: 53472 | M74: 118964 | N74: 1620623 | O74: 10092 | P74: . | Q74: . | R74: . | S74: . | T74: . | U74: . | V74: 182835 | W74: 2116250 | X74: 63564 | Y74: =IF(ISNUMBER($W74),$W74,0) | Z74: =IF(ISNUMBER(SEARCH("Adjustment",$C74)),"excluded",IF($H74="Behind the Meter","excluded",IF(NOT(OR($E74="Bundled",$E74="Energy")),"excluded",IF(OR($H74="Retail Power Marketer",$H74="Community Choice Aggregator",$E74="Energy"),"procurement",IF(OR($H74="Municipal",$H74="Cooperative",$H74="Federal",$H74="State",$H74="Political Subdivision"),"cost_service",IF($H74="Investor Owned",IF(AND(COUNTIF(Parameters!$A$4:$A$33,$G74)>0,COUNTIF(Parameters!$B$4:$B$33,$B74)=0),"procurement","cost_service"),"unclassified"))))))
A75: 2024 | B75: 58964 | C75: Alpha Gas and Electric, LLC | D75: B | E75: Energy | F75: O | G75: PA | H75: Retail Power Marketer | I75: PJM | J75: 896.4 | K75: 5767 | L75: 766 | M75: 0 | N75: 0 | O75: 0 | P75: 0 | Q75: 0 | R75: 0 | S75: 0 | T75: 0 | U75: 0 | V75: 896.4 | W75: 5767 | X75: 766 | Y75: =IF(ISNUMBER($W75),$W75,0) | Z75: =IF(ISNUMBER(SEARCH("Adjustment",$C75)),"excluded",IF($H75="Behind the Meter","excluded",IF(NOT(OR($E75="Bundled",$E75="Energy")),"excluded",IF(OR($H75="Retail Power Marketer",$H75="Community Choice Aggregator",$E75="Energy"),"procurement",IF(OR($H75="Municipal",$H75="Cooperative",$H75="Federal",$H75="State",$H75="Political Subdivision"),"cost_service",IF($H75="Investor Owned",IF(AND(COUNTIF(Parameters!$A$4:$A$33,$G75)>0,COUNTIF(Parameters!$B$4:$B$33,$B75)=0),"procurement","cost_service"),"unclassified"))))))
A76: 2024 | B76: 58966 | C76: Marathon Power LLC | D76: B | E76: Energy | F76: O | G76: PA | H76: Retail Power Marketer | I76: PJM | J76: 30.7 | K76: 321 | L76: 120 | M76: 1465.4 | N76: 17334 | O76: 594 | P76: 0 | Q76: 0 | R76: 0 | S76: 0 | T76: 0 | U76: 0 | V76: 1496.1 | W76: 17655 | X76: 714 | Y76: =IF(ISNUMBER($W76),$W76,0) | Z76: =IF(ISNUMBER(SEARCH("Adjustment",$C76)),"excluded",IF($H76="Behind the Meter","excluded",IF(NOT(OR($E76="Bundled",$E76="Energy")),"excluded",IF(OR($H76="Retail Power Marketer",$H76="Community Choice Aggregator",$E76="Energy"),"procurement",IF(OR($H76="Municipal",$H76="Cooperative",$H76="Federal",$H76="State",$H76="Political Subdivision"),"cost_service",IF($H76="Investor Owned",IF(AND(COUNTIF(Parameters!$A$4:$A$33,$G76)>0,COUNTIF(Parameters!$B$4:$B$33,$B76)=0),"procurement","cost_service"),"unclassified"))))))
A77: 2024 | B77: 58973 | C77: Town Square Energy East, LLC | D77: B | E77: Energy | F77: O | G77: PA | H77: Retail Power Marketer | I77: PJM | J77: 2004.1 | K77: 16984 | L77: 1533 | M77: 47.7 | N77: 391 | O77: 48 | P77: 0 | Q77: 0 | R77: 0 | S77: 0 | T77: 0 | U77: 0 | V77: 2051.8 | W77: 17375 | X77: 1581 | Y77: =IF(ISNUMBER($W77),$W77,0) | Z77: =IF(ISNUMBER(SEARCH("Adjustment",$C77)),"excluded",IF($H77="Behind the Meter","excluded",IF(NOT(OR($E77="Bundled",$E77="Energy")),"excluded",IF(OR($H77="Retail Power Marketer",$H77="Community Choice Aggregator",$E77="Energy"),"procurement",IF(OR($H77="Municipal",$H77="Cooperative",$H77="Federal",$H77="State",$H77="Political Subdivision"),"cost_service",IF($H77="Investor Owned",IF(AND(COUNTIF(Parameters!$A$4:$A$33,$G77)>0,COUNTIF(Parameters!$B$4:$B$33,$B77)=0),"procurement","cost_service"),"unclassified"))))))
A78: 2024 | B78: 58974 | C78: Clearview Electric Inc. | D78: B | E78: Energy | F78: O | G78: PA | H78: Retail Power Marketer | I78: PJM | J78: 18077.4 | K78: 146086 | L78: 12862 | M78: 1039.1 | N78: 10061 | O78: 291 | P78: 0 | Q78: 0 | R78: 0 | S78: 0 | T78: 0 | U78: 0 | V78: 19116.5 | W78: 156147 | X78: 13153 | Y78: =IF(ISNUMBER($W78),$W78,0) | Z78: =IF(ISNUMBER(SEARCH("Adjustment",$C78)),"excluded",IF($H78="Behind the Meter","excluded",IF(NOT(OR($E78="Bundled",$E78="Energy")),"excluded",IF(OR($H78="Retail Power Marketer",$H78="Community Choice Aggregator",$E78="Energy"),"procurement",IF(OR($H78="Municipal",$H78="Cooperative",$H78="Federal",$H78="State",$H78="Political Subdivision"),"cost_service",IF($H78="Investor Owned",IF(AND(COUNTIF(Parameters!$A$4:$A$33,$G78)>0,COUNTIF(Parameters!$B$4:$B$33,$B78)=0),"procurement","cost_service"),"unclassified"))))))
A79: 2024 | B79: 59054 | C79: Eligo Energy, LLC | D79: B | E79: Energy | F79: O | G79: PA | H79: Retail Power Marketer | I79: PJM | J79: 10504 | K79: 79842 | L79: 9053 | M79: 3950.7 | N79: 31087 | O79: 1537 | P79: . | Q79: . | R79: . | S79: . | T79: . | U79: . | V79: 14454.7 | W79: 110929 | X79: 10590 | Y79: =IF(ISNUMBER($W79),$W79,0) | Z79: =IF(ISNUMBER(SEARCH("Adjustment",$C79)),"excluded",IF($H79="Behind the Meter","excluded",IF(NOT(OR($E79="Bundled",$E79="Energy")),"excluded",IF(OR($H79="Retail Power Marketer",$H79="Community Choice Aggregator",$E79="Energy"),"procurement",IF(OR($H79="Municipal",$H79="Cooperative",$H79="Federal",$H79="State",$H79="Political Subdivision"),"cost_service",IF($H79="Investor Owned",IF(AND(COUNTIF(Parameters!$A$4:$A$33,$G79)>0,COUNTIF(Parameters!$B$4:$B$33,$B79)=0),"procurement","cost_service"),"unclassified"))))))
A80: 2024 | B80: 59055 | C80: Choice Energy, LLC | D80: B | E80: Energy | F80: O | G80: PA | H80: Retail Power Marketer | I80: PJM | J80: 9462.8 | K80: 79770 | L80: 8475 | M80: 0 | N80: 0 | O80: 0 | P80: 0 | Q80: 0 | R80: 0 | S80: 0 | T80: 0 | U80: 0 | V80: 9462.8 | W80: 79770 | X80: 8475 | Y80: =IF(ISNUMBER($W80),$W80,0) | Z80: =IF(ISNUMBER(SEARCH("Adjustment",$C80)),"excluded",IF($H80="Behind the Meter","excluded",IF(NOT(OR($E80="Bundled",$E80="Energy")),"excluded",IF(OR($H80="Retail Power Marketer",$H80="Community Choice Aggregator",$E80="Energy"),"procurement",IF(OR($H80="Municipal",$H80="Cooperative",$H80="Federal",$H80="State",$H80="Political Subdivision"),"cost_service",IF($H80="Investor Owned",IF(AND(COUNTIF(Parameters!$A$4:$A$33,$G80)>0,COUNTIF(Parameters!$B$4:$B$33,$B80)=0),"procurement","cost_service"),"unclassified"))))))
A81: 2024 | B81: 59064 | C81: Great American Power, LLC | D81: B | E81: Energy | F81: O | G81: PA | H81: Retail Power Marketer | I81: PJM | J81: 2091.5 | K81: 19030 | L81: 2695 | M81: 0 | N81: 0 | O81: 0 | P81: 0 | Q81: 0 | R81: 0 | S81: 0 | T81: 0 | U81: 0 | V81: 2091.5 | W81: 19030 | X81: 2695 | Y81: =IF(ISNUMBER($W81),$W81,0) | Z81: =IF(ISNUMBER(SEARCH("Adjustment",$C81)),"excluded",IF($H81="Behind the Meter","excluded",IF(NOT(OR($E81="Bundled",$E81="Energy")),"excluded",IF(OR($H81="Retail Power Marketer",$H81="Community Choice Aggregator",$E81="Energy"),"procurement",IF(OR($H81="Municipal",$H81="Cooperative",$H81="Federal",$H81="State",$H81="Political Subdivision"),"cost_service",IF($H81="Investor Owned",IF(AND(COUNTIF(Parameters!$A$4:$A$33,$G81)>0,COUNTIF(Parameters!$B$4:$B$33,$B81)=0),"procurement","cost_service"),"unclassified"))))))
A82: 2024 | B82: 59065 | C82: Titan Gas LLC | D82: B | E82: Energy | F82: O | G82: PA | H82: Retail Power Marketer | I82: PJM | J82: 32094.1 | K82: 237593 | L82: 23384 | M82: 7335.3 | N82: 72511 | O82: 2314 | P82: 0 | Q82: 0 | R82: 0 | S82: 0 | T82: 0 | U82: 0 | V82: 39429.4 | W82: 310104 | X82: 25698 | Y82: =IF(ISNUMBER($W82),$W82,0) | Z82: =IF(ISNUMBER(SEARCH("Adjustment",$C82)),"excluded",IF($H82="Behind the Meter","excluded",IF(NOT(OR($E82="Bundled",$E82="Energy")),"excluded",IF(OR($H82="Retail Power Marketer",$H82="Community Choice Aggregator",$E82="Energy"),"procurement",IF(OR($H82="Municipal",$H82="Cooperative",$H82="Federal",$H82="State",$H82="Political Subdivision"),"cost_service",IF($H82="Investor Owned",IF(AND(COUNTIF(Parameters!$A$4:$A$33,$G82)>0,COUNTIF(Parameters!$B$4:$B$33,$B82)=0),"procurement","cost_service"),"unclassified"))))))
A83: 2024 | B83: 59083 | C83: SFE Energy Pennsylvania, Inc. | D83: B | E83: Energy | F83: O | G83: PA | H83: Retail Power Marketer | I83: PJM | J83: 16555 | K83: 150374 | L83: 19133 | M83: 48252.8 | N83: 437818 | O83: 6796 | P83: . | Q83: . | R83: . | S83: . | T83: . | U83: . | V83: 64807.8 | W83: 588192 | X83: 25929 | Y83: =IF(ISNUMBER($W83),$W83,0) | Z83: =IF(ISNUMBER(SEARCH("Adjustment",$C83)),"excluded",IF($H83="Behind the Meter","excluded",IF(NOT(OR($E83="Bundled",$E83="Energy")),"excluded",IF(OR($H83="Retail Power Marketer",$H83="Community Choice Aggregator",$E83="Energy"),"procurement",IF(OR($H83="Municipal",$H83="Cooperative",$H83="Federal",$H83="State",$H83="Political Subdivision"),"cost_service",IF($H83="Investor Owned",IF(AND(COUNTIF(Parameters!$A$4:$A$33,$G83)>0,COUNTIF(Parameters!$B$4:$B$33,$B83)=0),"procurement","cost_service"),"unclassified"))))))
A84: 2024 | B84: 59088 | C84: Nordic Energy Services, LLC | D84: B | E84: Energy | F84: O | G84: PA | H84: Retail Power Marketer | I84: PJM | J84: 2301.9 | K84: 15827 | L84: 2756 | M84: 327.8 | N84: 2579 | O84: 91 | P84: 0 | Q84: 0 | R84: 0 | S84: 0 | T84: 0 | U84: 0 | V84: 2629.7 | W84: 18406 | X84: 2847 | Y84: =IF(ISNUMBER($W84),$W84,0) | Z84: =IF(ISNUMBER(SEARCH("Adjustment",$C84)),"excluded",IF($H84="Behind the Meter","excluded",IF(NOT(OR($E84="Bundled",$E84="Energy")),"excluded",IF(OR($H84="Retail Power Marketer",$H84="Community Choice Aggregator",$E84="Energy"),"procurement",IF(OR($H84="Municipal",$H84="Cooperative",$H84="Federal",$H84="State",$H84="Political Subdivision"),"cost_service",IF($H84="Investor Owned",IF(AND(COUNTIF(Parameters!$A$4:$A$33,$G84)>0,COUNTIF(Parameters!$B$4:$B$33,$B84)=0),"procurement","cost_service"),"unclassified"))))))
A85: 2024 | B85: 59310 | C85: Inspire Energy Holdings, LLC | D85: B | E85: Energy | F85: O | G85: PA | H85: Retail Power Marketer | I85: PJM | J85: 120071.1 | K85: 944862 | L85: 89889 | M85: 2042.4 | N85: 15920 | O85: 1088 | P85: . | Q85: . | R85: . | S85: . | T85: . | U85: . | V85: 122113.5 | W85: 960782 | X85: 90977 | Y85: =IF(ISNUMBER($W85),$W85,0) | Z85: =IF(ISNUMBER(SEARCH("Adjustment",$C85)),"excluded",IF($H85="Behind the Meter","excluded",IF(NOT(OR($E85="Bundled",$E85="Energy")),"excluded",IF(OR($H85="Retail Power Marketer",$H85="Community Choice Aggregator",$E85="Energy"),"procurement",IF(OR($H85="Municipal",$H85="Cooperative",$H85="Federal",$H85="State",$H85="Political Subdivision"),"cost_service",IF($H85="Investor Owned",IF(AND(COUNTIF(Parameters!$A$4:$A$33,$G85)>0,COUNTIF(Parameters!$B$4:$B$33,$B85)=0),"procurement","cost_service"),"unclassified"))))))
A86: 2024 | B86: 59385 | C86: Dynegy Energy Services, LLC | D86: B | E86: Energy | F86: O | G86: PA | H86: Retail Power Marketer | I86: PJM | J86: 47198.7 | K86: 509146 | L86: 37672 | M86: 203617.9 | N86: 2655840 | O86: 1921 | P86: 960.5 | Q86: 12528 | R86: 9 | S86: 0 | T86: 0 | U86: 0 | V86: 251777.1 | W86: 3177514 | X86: 39602 | Y86: =IF(ISNUMBER($W86),$W86,0) | Z86: =IF(ISNUMBER(SEARCH("Adjustment",$C86)),"excluded",IF($H86="Behind the Meter","excluded",IF(NOT(OR($E86="Bundled",$E86="Energy")),"excluded",IF(OR($H86="Retail Power Marketer",$H86="Community Choice Aggregator",$E86="Energy"),"procurement",IF(OR($H86="Municipal",$H86="Cooperative",$H86="Federal",$H86="State",$H86="Political Subdivision"),"cost_service",IF($H86="Investor Owned",IF(AND(COUNTIF(Parameters!$A$4:$A$33,$G86)>0,COUNTIF(Parameters!$B$4:$B$33,$B86)=0),"procurement","cost_service"),"unclassified"))))))
A87: 2024 | B87: 59410 | C87: Shipley Choice, LLC | D87: B | E87: Energy | F87: O | G87: PA | H87: Retail Power Marketer | I87: PJM | J87: 11531.1 | K87: 101932 | L87: 9886 | M87: 2839.3 | N87: 34098 | O87: 587 | P87: 0 | Q87: 0 | R87: 0 | S87: 0 | T87: 0 | U87: 0 | V87: 14370.4 | W87: 136030 | X87: 10473 | Y87: =IF(ISNUMBER($W87),$W87,0) | Z87: =IF(ISNUMBER(SEARCH("Adjustment",$C87)),"excluded",IF($H87="Behind the Meter","excluded",IF(NOT(OR($E87="Bundled",$E87="Energy")),"excluded",IF(OR($H87="Retail Power Marketer",$H87="Community Choice Aggregator",$E87="Energy"),"procurement",IF(OR($H87="Municipal",$H87="Cooperative",$H87="Federal",$H87="State",$H87="Political Subdivision"),"cost_service",IF($H87="Investor Owned",IF(AND(COUNTIF(Parameters!$A$4:$A$33,$G87)>0,COUNTIF(Parameters!$B$4:$B$33,$B87)=0),"procurement","cost_service"),"unclassified"))))))
A88: 2024 | B88: 59579 | C88: Sunnova | D88: A | E88: Bundled | F88: O | G88: PA | H88: Behind the Meter | I88: PJM | J88: 19594.1 | K88: 112774 | L88: 10759 | M88: . | N88: . | O88: . | P88: . | Q88: . | R88: . | S88: . | T88: . | U88: . | V88: 19594.1 | W88: 112774 | X88: 10759 | Y88: =IF(ISNUMBER($W88),$W88,0) | Z88: =IF(ISNUMBER(SEARCH("Adjustment",$C88)),"excluded",IF($H88="Behind the Meter","excluded",IF(NOT(OR($E88="Bundled",$E88="Energy")),"excluded",IF(OR($H88="Retail Power Marketer",$H88="Community Choice Aggregator",$E88="Energy"),"procurement",IF(OR($H88="Municipal",$H88="Cooperative",$H88="Federal",$H88="State",$H88="Political Subdivision"),"cost_service",IF($H88="Investor Owned",IF(AND(COUNTIF(Parameters!$A$4:$A$33,$G88)>0,COUNTIF(Parameters!$B$4:$B$33,$B88)=0),"procurement","cost_service"),"unclassified"))))))
A89: 2024 | B89: 59580 | C89: SunPower Capital, LLC | D89: A | E89: Bundled | F89: O | G89: PA | H89: Behind the Meter | I89: PJM | J89: 44.7 | K89: 270 | L89: 61 | M89: . | N89: . | O89: . | P89: . | Q89: . | R89: . | S89: . | T89: . | U89: . | V89: 44.7 | W89: 270 | X89: 61 | Y89: =IF(ISNUMBER($W89),$W89,0) | Z89: =IF(ISNUMBER(SEARCH("Adjustment",$C89)),"excluded",IF($H89="Behind the Meter","excluded",IF(NOT(OR($E89="Bundled",$E89="Energy")),"excluded",IF(OR($H89="Retail Power Marketer",$H89="Community Choice Aggregator",$E89="Energy"),"procurement",IF(OR($H89="Municipal",$H89="Cooperative",$H89="Federal",$H89="State",$H89="Political Subdivision"),"cost_service",IF($H89="Investor Owned",IF(AND(COUNTIF(Parameters!$A$4:$A$33,$G89)>0,COUNTIF(Parameters!$B$4:$B$33,$B89)=0),"procurement","cost_service"),"unclassified"))))))
A90: 2024 | B90: 59620 | C90: Verde Energy USA | D90: B | E90: Energy | F90: O | G90: PA | H90: Retail Power Marketer | I90: PJM | J90: 34278 | K90: 264675 | L90: 24769 | M90: 947 | N90: 7574 | O90: 513 | P90: 0 | Q90: 0 | R90: 0 | S90: 0 | T90: 0 | U90: 0 | V90: 35225 | W90: 272249 | X90: 25282 | Y90: =IF(ISNUMBER($W90),$W90,0) | Z90: =IF(ISNUMBER(SEARCH("Adjustment",$C90)),"excluded",IF($H90="Behind the Meter","excluded",IF(NOT(OR($E90="Bundled",$E90="Energy")),"excluded",IF(OR($H90="Retail Power Marketer",$H90="Community Choice Aggregator",$E90="Energy"),"procurement",IF(OR($H90="Municipal",$H90="Cooperative",$H90="Federal",$H90="State",$H90="Political Subdivision"),"cost_service",IF($H90="Investor Owned",IF(AND(COUNTIF(Parameters!$A$4:$A$33,$G90)>0,COUNTIF(Parameters!$B$4:$B$33,$B90)=0),"procurement","cost_service"),"unclassified"))))))
A91: 2024 | B91: 59622 | C91: Ahana Renewables, LLC | D91: A | E91: Bundled | F91: O | G91: PA | H91: Behind the Meter | I91: PJM | J91: 0 | K91: 0 | L91: 0 | M91: 63.9 | N91: 514 | O91: 1 | P91: 0 | Q91: 0 | R91: 0 | S91: 0 | T91: 0 | U91: 0 | V91: 63.9 | W91: 514 | X91: 1 | Y91: =IF(ISNUMBER($W91),$W91,0) | Z91: =IF(ISNUMBER(SEARCH("Adjustment",$C91)),"excluded",IF($H91="Behind the Meter","excluded",IF(NOT(OR($E91="Bundled",$E91="Energy")),"excluded",IF(OR($H91="Retail Power Marketer",$H91="Community Choice Aggregator",$E91="Energy"),"procurement",IF(OR($H91="Municipal",$H91="Cooperative",$H91="Federal",$H91="State",$H91="Political Subdivision"),"cost_service",IF($H91="Investor Owned",IF(AND(COUNTIF(Parameters!$A$4:$A$33,$G91)>0,COUNTIF(Parameters!$B$4:$B$33,$B91)=0),"procurement","cost_service"),"unclassified"))))))
A92: 2024 | B92: 59647 | C92: Sunrun Inc. | D92: A | E92: Bundled | F92: O | G92: PA | H92: Behind the Meter | I92: PJM | J92: 7086.2 | K92: 43966 | L92: 5072 | M92: . | N92: . | O92: . | P92: . | Q92: . | R92: . | S92: . | T92: . | U92: . | V92: 7086.2 | W92: 43966 | X92: 5072 | Y92: =IF(ISNUMBER($W92),$W92,0) | Z92: =IF(ISNUMBER(SEARCH("Adjustment",$C92)),"excluded",IF($H92="Behind the Meter","excluded",IF(NOT(OR($E92="Bundled",$E92="Energy")),"excluded",IF(OR($H92="Retail Power Marketer",$H92="Community Choice Aggregator",$E92="Energy"),"procurement",IF(OR($H92="Municipal",$H92="Cooperative",$H92="Federal",$H92="State",$H92="Political Subdivision"),"cost_service",IF($H92="Investor Owned",IF(AND(COUNTIF(Parameters!$A$4:$A$33,$G92)>0,COUNTIF(Parameters!$B$4:$B$33,$B92)=0),"procurement","cost_service"),"unclassified"))))))
A93: 2024 | B93: 59793 | C93: First Point Power, LLC | D93: B | E93: Energy | F93: O | G93: PA | H93: Retail Power Marketer | I93: PJM | J93: 18.9 | K93: 109 | L93: 16 | M93: 195 | N93: 1117 | O93: 45 | P93: 0 | Q93: 0 | R93: 0 | S93: 0 | T93: 0 | U93: 0 | V93: 213.9 | W93: 1226 | X93: 61 | Y93: =IF(ISNUMBER($W93),$W93,0) | Z93: =IF(ISNUMBER(SEARCH("Adjustment",$C93)),"excluded",IF($H93="Behind the Meter","excluded",IF(NOT(OR($E93="Bundled",$E93="Energy")),"excluded",IF(OR($H93="Retail Power Marketer",$H93="Community Choice Aggregator",$E93="Energy"),"procurement",IF(OR($H93="Municipal",$H93="Cooperative",$H93="Federal",$H93="State",$H93="Political Subdivision"),"cost_service",IF($H93="Investor Owned",IF(AND(COUNTIF(Parameters!$A$4:$A$33,$G93)>0,COUNTIF(Parameters!$B$4:$B$33,$B93)=0),"procurement","cost_service"),"unclassified"))))))
A94: 2024 | B94: 59797 | C94: Park Power LLC | D94: B | E94: Energy | F94: O | G94: PA | H94: Retail Power Marketer | I94: PJM | J94: 7425.1 | K94: 39933 | L94: 5198 | M94: 72.8 | N94: 664 | O94: 20 | P94: . | Q94: . | R94: . | S94: . | T94: . | U94: . | V94: 7497.9 | W94: 40597 | X94: 5218 | Y94: =IF(ISNUMBER($W94),$W94,0) | Z94: =IF(ISNUMBER(SEARCH("Adjustment",$C94)),"excluded",IF($H94="Behind the Meter","excluded",IF(NOT(OR($E94="Bundled",$E94="Energy")),"excluded",IF(OR($H94="Retail Power Marketer",$H94="Community Choice Aggregator",$E94="Energy"),"procurement",IF(OR($H94="Municipal",$H94="Cooperative",$H94="Federal",$H94="State",$H94="Political Subdivision"),"cost_service",IF($H94="Investor Owned",IF(AND(COUNTIF(Parameters!$A$4:$A$33,$G94)>0,COUNTIF(Parameters!$B$4:$B$33,$B94)=0),"procurement","cost_service"),"unclassified"))))))
A95: 2024 | B95: 59799 | C95: American Power & Gas | D95: B | E95: Energy | F95: O | G95: PA | H95: Retail Power Marketer | I95: PJM | J95: 39432.6 | K95: 315204 | L95: 25167 | M95: 46208.8 | N95: 302839 | O95: 16186 | P95: 0 | Q95: 0 | R95: 0 | S95: 0 | T95: 0 | U95: 0 | V95: 85641.4 | W95: 618043 | X95: 41353 | Y95: =IF(ISNUMBER($W95),$W95,0) | Z95: =IF(ISNUMBER(SEARCH("Adjustment",$C95)),"excluded",IF($H95="Behind the Meter","excluded",IF(NOT(OR($E95="Bundled",$E95="Energy")),"excluded",IF(OR($H95="Retail Power Marketer",$H95="Community Choice Aggregator",$E95="Energy"),"procurement",IF(OR($H95="Municipal",$H95="Cooperative",$H95="Federal",$H95="State",$H95="Political Subdivision"),"cost_service",IF($H95="Investor Owned",IF(AND(COUNTIF(Parameters!$A$4:$A$33,$G95)>0,COUNTIF(Parameters!$B$4:$B$33,$B95)=0),"procurement","cost_service"),"unclassified"))))))
A96: 2024 | B96: 59807 | C96: Rushmore Energy, LLC | D96: B | E96: Energy | F96: O | G96: PA | H96: Retail Power Marketer | I96: PJM | J96: 3058.1 | K96: 25780 | L96: 3346 | M96: 0 | N96: 0 | O96: 0 | P96: 0 | Q96: 0 | R96: 0 | S96: 0 | T96: 0 | U96: 0 | V96: 3058.1 | W96: 25780 | X96: 3346 | Y96: =IF(ISNUMBER($W96),$W96,0) | Z96: =IF(ISNUMBER(SEARCH("Adjustment",$C96)),"excluded",IF($H96="Behind the Meter","excluded",IF(NOT(OR($E96="Bundled",$E96="Energy")),"excluded",IF(OR($H96="Retail Power Marketer",$H96="Community Choice Aggregator",$E96="Energy"),"procurement",IF(OR($H96="Municipal",$H96="Cooperative",$H96="Federal",$H96="State",$H96="Political Subdivision"),"cost_service",IF($H96="Investor Owned",IF(AND(COUNTIF(Parameters!$A$4:$A$33,$G96)>0,COUNTIF(Parameters!$B$4:$B$33,$B96)=0),"procurement","cost_service"),"unclassified"))))))
A97: 2024 | B97: 59808 | C97: MP2 Energy LLC | D97: B | E97: Energy | F97: O | G97: PA | H97: Retail Power Marketer | I97: PJM | J97: 0 | K97: 0 | L97: 0 | M97: 100751.4 | N97: 1378626 | O97: 3430 | P97: 36274.3 | Q97: 479819 | R97: 275 | S97: 0 | T97: 0 | U97: 0 | V97: 137025.7 | W97: 1858445 | X97: 3705 | Y97: =IF(ISNUMBER($W97),$W97,0) | Z97: =IF(ISNUMBER(SEARCH("Adjustment",$C97)),"excluded",IF($H97="Behind the Meter","excluded",IF(NOT(OR($E97="Bundled",$E97="Energy")),"excluded",IF(OR($H97="Retail Power Marketer",$H97="Community Choice Aggregator",$E97="Energy"),"procurement",IF(OR($H97="Municipal",$H97="Cooperative",$H97="Federal",$H97="State",$H97="Political Subdivision"),"cost_service",IF($H97="Investor Owned",IF(AND(COUNTIF(Parameters!$A$4:$A$33,$G97)>0,COUNTIF(Parameters!$B$4:$B$33,$B97)=0),"procurement","cost_service"),"unclassified"))))))
A98: 2024 | B98: 59809 | C98: Residents Energy, LLC | D98: B | E98: Energy | F98: O | G98: PA | H98: Retail Power Marketer | I98: PJM | J98: 10683.7 | K98: 71442 | L98: 10067 | M98: 129.4 | N98: 913 | O98: 103 | P98: 0 | Q98: 0 | R98: 0 | S98: 0 | T98: 0 | U98: 0 | V98: 10813.1 | W98: 72355 | X98: 10170 | Y98: =IF(ISNUMBER($W98),$W98,0) | Z98: =IF(ISNUMBER(SEARCH("Adjustment",$C98)),"excluded",IF($H98="Behind the Meter","excluded",IF(NOT(OR($E98="Bundled",$E98="Energy")),"excluded",IF(OR($H98="Retail Power Marketer",$H98="Community Choice Aggregator",$E98="Energy"),"procurement",IF(OR($H98="Municipal",$H98="Cooperative",$H98="Federal",$H98="State",$H98="Political Subdivision"),"cost_service",IF($H98="Investor Owned",IF(AND(COUNTIF(Parameters!$A$4:$A$33,$G98)>0,COUNTIF(Parameters!$B$4:$B$33,$B98)=0),"procurement","cost_service"),"unclassified"))))))
A99: 2024 | B99: 59810 | C99: Greenlight Energy Inc. | D99: B | E99: Energy | F99: O | G99: PA | H99: Retail Power Marketer | I99: PJM | J99: 882 | K99: 6172 | L99: 858 | M99: 0 | N99: 0 | O99: 0 | P99: 0 | Q99: 0 | R99: 0 | S99: 0 | T99: 0 | U99: 0 | V99: 882 | W99: 6172 | X99: 858 | Y99: =IF(ISNUMBER($W99),$W99,0) | Z99: =IF(ISNUMBER(SEARCH("Adjustment",$C99)),"excluded",IF($H99="Behind the Meter","excluded",IF(NOT(OR($E99="Bundled",$E99="Energy")),"excluded",IF(OR($H99="Retail Power Marketer",$H99="Community Choice Aggregator",$E99="Energy"),"procurement",IF(OR($H99="Municipal",$H99="Cooperative",$H99="Federal",$H99="State",$H99="Political Subdivision"),"cost_service",IF($H99="Investor Owned",IF(AND(COUNTIF(Parameters!$A$4:$A$33,$G99)>0,COUNTIF(Parameters!$B$4:$B$33,$B99)=0),"procurement","cost_service"),"unclassified"))))))
A100: 2024 | B100: 59811 | C100: Santanna Energy Services | D100: B | E100: Energy | F100: O | G100: PA | H100: Retail Power Marketer | I100: PJM | J100: 6467.7 | K100: 71670 | L100: 4700 | M100: 965.7 | N100: 10331 | O100: 180 | P100: 0 | Q100: 0 | R100: 0 | S100: 0 | T100: 0 | U100: 0 | V100: 7433.4 | W100: 82001 | X100: 4880 | Y100: =IF(ISNUMBER($W100),$W100,0) | Z100: =IF(ISNUMBER(SEARCH("Adjustment",$C100)),"excluded",IF($H100="Behind the Meter","excluded",IF(NOT(OR($E100="Bundled",$E100="Energy")),"excluded",IF(OR($H100="Retail Power Marketer",$H100="Community Choice Aggregator",$E100="Energy"),"procurement",IF(OR($H100="Municipal",$H100="Cooperative",$H100="Federal",$H100="State",$H100="Political Subdivision"),"cost_service",IF($H100="Investor Owned",IF(AND(COUNTIF(Parameters!$A$4:$A$33,$G100)>0,COUNTIF(Parameters!$B$4:$B$33,$B100)=0),"procurement","cost_service"),"unclassified"))))))
A101: 2024 | B101: 59812 | C101: New Wave Energy Corporation | D101: B | E101: Energy | F101: O | G101: PA | H101: Retail Power Marketer | I101: PJM | J101: 7270 | K101: 75128 | L101: 6276 | M101: 9970 | N101: 90549 | O101: 2164 | P101: 0 | Q101: 0 | R101: 0 | S101: 0 | T101: 0 | U101: 0 | V101: 17240 | W101: 165677 | X101: 8440 | Y101: =IF(ISNUMBER($W101),$W101,0) | Z101: =IF(ISNUMBER(SEARCH("Adjustment",$C101)),"excluded",IF($H101="Behind the Meter","excluded",IF(NOT(OR($E101="Bundled",$E101="Energy")),"excluded",IF(OR($H101="Retail Power Marketer",$H101="Community Choice Aggregator",$E101="Energy"),"procurement",IF(OR($H101="Municipal",$H101="Cooperative",$H101="Federal",$H101="State",$H101="Political Subdivision"),"cost_service",IF($H101="Investor Owned",IF(AND(COUNTIF(Parameters!$A$4:$A$33,$G101)>0,COUNTIF(Parameters!$B$4:$B$33,$B101)=0),"procurement","cost_service"),"unclassified"))))))
A102: 2024 | B102: 59931 | C102: MidAmerican Energy Services, LLC | D102: B | E102: Energy | F102: O | G102: PA | H102: Retail Power Marketer | I102: PJM | J102: 160.4 | K102: 2220 | L102: 253 | M102: 21700.8 | N102: 331859 | O102: 2807 | P102: 15788.3 | Q102: 276982 | R102: 27 | S102: 0 | T102: 0 | U102: 0 | V102: 37649.5 | W102: 611061 | X102: 3087 | Y102: =IF(ISNUMBER($W102),$W102,0) | Z102: =IF(ISNUMBER(SEARCH("Adjustment",$C102)),"excluded",IF($H102="Behind the Meter","excluded",IF(NOT(OR($E102="Bundled",$E102="Energy")),"excluded",IF(OR($H102="Retail Power Marketer",$H102="Community Choice Aggregator",$E102="Energy"),"procurement",IF(OR($H102="Municipal",$H102="Cooperative",$H102="Federal",$H102="State",$H102="Political Subdivision"),"cost_service",IF($H102="Investor Owned",IF(AND(COUNTIF(Parameters!$A$4:$A$33,$G102)>0,COUNTIF(Parameters!$B$4:$B$33,$B102)=0),"procurement","cost_service"),"unclassified"))))))
A103: 2024 | B103: 59993 | C103: Discount Power Inc - (CT) | D103: B | E103: Energy | F103: O | G103: PA | H103: Retail Power Marketer | I103: PJM | J103: 4578.2 | K103: 21339 | L103: 3095 | M103: 71 | N103: 436 | O103: 19 | P103: 0 | Q103: 0 | R103: 0 | S103: 0 | T103: 0 | U103: 0 | V103: 4649.2 | W103: 21775 | X103: 3114 | Y103: =IF(ISNUMBER($W103),$W103,0) | Z103: =IF(ISNUMBER(SEARCH("Adjustment",$C103)),"excluded",IF($H103="Behind the Meter","excluded",IF(NOT(OR($E103="Bundled",$E103="Energy")),"excluded",IF(OR($H103="Retail Power Marketer",$H103="Community Choice Aggregator",$E103="Energy"),"procurement",IF(OR($H103="Municipal",$H103="Cooperative",$H103="Federal",$H103="State",$H103="Political Subdivision"),"cost_service",IF($H103="Investor Owned",IF(AND(COUNTIF(Parameters!$A$4:$A$33,$G103)>0,COUNTIF(Parameters!$B$4:$B$33,$B103)=0),"procurement","cost_service"),"unclassified"))))))
A104: 2024 | B104: 60124 | C104: Spring Energy RRH LLC | D104: B | E104: Energy | F104: O | G104: PA | H104: Retail Power Marketer | I104: PJM | J104: 5678 | K104: 40153 | L104: 5374 | M104: 133 | N104: 956 | O104: 31 | P104: 0 | Q104: 0 | R104: 0 | S104: 0 | T104: 0 | U104: 0 | V104: 5811 | W104: 41109 | X104: 5405 | Y104: =IF(ISNUMBER($W104),$W104,0) | Z104: =IF(ISNUMBER(SEARCH("Adjustment",$C104)),"excluded",IF($H104="Behind the Meter","excluded",IF(NOT(OR($E104="Bundled",$E104="Energy")),"excluded",IF(OR($H104="Retail Power Marketer",$H104="Community Choice Aggregator",$E104="Energy"),"procurement",IF(OR($H104="Municipal",$H104="Cooperative",$H104="Federal",$H104="State",$H104="Political Subdivision"),"cost_service",IF($H104="Investor Owned",IF(AND(COUNTIF(Parameters!$A$4:$A$33,$G104)>0,COUNTIF(Parameters!$B$4:$B$33,$B104)=0),"procurement","cost_service"),"unclassified"))))))
A105: 2024 | B105: 60218 | C105: MPower Energy NJ LLC | D105: B | E105: Energy | F105: O | G105: PA | H105: Retail Power Marketer | I105: PJM | J105: 8232.3 | K105: 46323 | L105: 6969 | M105: 260.5 | N105: 1364 | O105: 90 | P105: 0 | Q105: 0 | R105: 0 | S105: 0 | T105: 0 | U105: 0 | V105: 8492.8 | W105: 47687 | X105: 7059 | Y105: =IF(ISNUMBER($W105),$W105,0) | Z105: =IF(ISNUMBER(SEARCH("Adjustment",$C105)),"excluded",IF($H105="Behind the Meter","excluded",IF(NOT(OR($E105="Bundled",$E105="Energy")),"excluded",IF(OR($H105="Retail Power Marketer",$H105="Community Choice Aggregator",$E105="Energy"),"procurement",IF(OR($H105="Municipal",$H105="Cooperative",$H105="Federal",$H105="State",$H105="Political Subdivision"),"cost_service",IF($H105="Investor Owned",IF(AND(COUNTIF(Parameters!$A$4:$A$33,$G105)>0,COUNTIF(Parameters!$B$4:$B$33,$B105)=0),"procurement","cost_service"),"unclassified"))))))
A106: 2024 | B106: 60583 | C106: Atlantic Energy LLC | D106: B | E106: Energy | F106: O | G106: PA | H106: Retail Power Marketer | I106: PJM | J106: 1227.3 | K106: 6118 | L106: 922 | M106: 746.5 | N106: 3404 | O106: 112 | P106: 0 | Q106: 0 | R106: 0 | S106: 0 | T106: 0 | U106: 0 | V106: 1973.8 | W106: 9522 | X106: 1034 | Y106: =IF(ISNUMBER($W106),$W106,0) | Z106: =IF(ISNUMBER(SEARCH("Adjustment",$C106)),"excluded",IF($H106="Behind the Meter","excluded",IF(NOT(OR($E106="Bundled",$E106="Energy")),"excluded",IF(OR($H106="Retail Power Marketer",$H106="Community Choice Aggregator",$E106="Energy"),"procurement",IF(OR($H106="Municipal",$H106="Cooperative",$H106="Federal",$H106="State",$H106="Political Subdivision"),"cost_service",IF($H106="Investor Owned",IF(AND(COUNTIF(Parameters!$A$4:$A$33,$G106)>0,COUNTIF(Parameters!$B$4:$B$33,$B106)=0),"procurement","cost_service"),"unclassified"))))))
... A110: 2024 | B110: 61131 | C110: Freepoint Energy Solutions LLC | D110: B | E110: Energy | F110: O | G110: PA | H110: Retail Power Marketer | I110: PJM | J110: 0 | K110: 0 | L110: 0 | M110: 254101 | N110: 3036421 | O110: 2745 | P110: 0 | Q110: 0 | R110: 0 | S110: 0 | T110: 0 | U110: 0 | V110: 254101 | W110: 3036421 | X110: 2745 | Y110: =IF(ISNUMBER($W110),$W110,0) | Z110: =IF(ISNUMBER(SEARCH("Adjustment",$C110)),"excluded",IF($H110="Behind the Meter","excluded",IF(NOT(OR($E110="Bundled",$E110="Energy")),"excluded",IF(OR($H110="Retail Power Marketer",$H110="Community Choice Aggregator",$E110="Energy"),"procurement",IF(OR($H110="Municipal",$H110="Cooperative",$H110="Federal",$H110="State",$H110="Political Subdivision"),"cost_service",IF($H110="Investor Owned",IF(AND(COUNTIF(Parameters!$A$4:$A$33,$G110)>0,COUNTIF(Parameters!$B$4:$B$33,$B110)=0),"procurement","cost_service"),"unclassified"))))))
A111: 2024 | B111: 61353 | C111: Philadelphia Authority for Industrial Development | D111: A | E111: Bundled | F111: O | G111: PA | H111: Municipal | I111: PJM | J111: . | K111: . | L111: . | M111: 11857.8 | N111: 92551 | O111: 194 | P111: 15834.3 | Q111: 103276 | R111: 8 | S111: . | T111: . | U111: . | V111: 27692.1 | W111: 195827 | X111: 202 | Y111: =IF(ISNUMBER($W111),$W111,0) | Z111: =IF(ISNUMBER(SEARCH("Adjustment",$C111)),"excluded",IF($H111="Behind the Meter","excluded",IF(NOT(OR($E111="Bundled",$E111="Energy")),"excluded",IF(OR($H111="Retail Power Marketer",$H111="Community Choice Aggregator",$E111="Energy"),"procurement",IF(OR($H111="Municipal",$H111="Cooperative",$H111="Federal",$H111="State",$H111="Political Subdivision"),"cost_service",IF($H111="Investor Owned",IF(AND(COUNTIF(Parameters!$A$4:$A$33,$G111)>0,COUNTIF(Parameters!$B$4:$B$33,$B111)=0),"procurement","cost_service"),"unclassified"))))))
...

Sheet Share
A1: region | B1: cost_service_mwh | C1: procurement_mwh | D1: total_mwh | E1: share_cost_service | F1: share_procurement
A2: PA | B2: =SUMIFS('EIA-861 Sales 2024'!$Y$4:$Y$143,'EIA-861 Sales 2024'!$Z$4:$Z$143,"cost_service") | C2: =SUMIFS('EIA-861 Sales 2024'!$Y$4:$Y$143,'EIA-861 Sales 2024'!$Z$4:$Z$143,"procurement") | D2: =B2+C2 | E2: =IF($D2=0,0,B2/$D2) | F2: =IF($D2=0,0,C2/$D2)

Sheet SoEDtICoS
A1: Unit: dimensionless (% of demand) | B1: 2021 | C1: 2022 | D1: 2023 | E1: 2024 | F1: 2025 | G1: 2026 | H1: 2027 | I1: 2028 | J1: 2029 | K1: 2030 | L1: 2031 | M1: 2032 | N1: 2033 | O1: 2034 | P1: 2035 | Q1: 2036 | R1: 2037 | S1: 2038 | T1: 2039 | U1: 2040 | V1: 2041 | W1: 2042 | X1: 2043 | Y1: 2044 | Z1: 2045 | AA1: 2046 | AB1: 2047 | AC1: 2048 | AD1: 2049 | AE1: 2050
A2: Share that is Cost of Service | B2: =ROUND('Share'!$E$2,3) | C2: =ROUND('Share'!$E$2,3) | D2: =ROUND('Share'!$E$2,3) | E2: =ROUND('Share'!$E$2,3) | F2: =ROUND('Share'!$E$2,3) | G2: =ROUND('Share'!$E$2,3) | H2: =ROUND('Share'!$E$2,3) | I2: =ROUND('Share'!$E$2,3) | ... AE2: =ROUND('Share'!$E$2,3)
