Workbook

Sheet About
A1: FoGPbEaIC - Fraction of Goods Purchased by Entity and ISIC Code
A3: State: Pennsylvania (PA) Base year: 2019 Pipeline: EPS IO Pipeline — stateior-based
A4: Deflator: 2019 USD -> 2012 USD = 1.12266 (BEA chained GDP price index; 2012 = 100.000, 2019 = 112.266)
A6: =========================================================
A7: Methodology
A8: =========================================================
A9: Two outputs, both at 25-Industry-Category resolution (the subset of
A10: 42 ISIC codes that represent tradeable goods + utilities + construction):
A12: FoGPbEaIC-entity (25 rows x 4 entity cols):
A13: For each source ISIC, fraction of its output purchased by each of
A14: {government, domestic industries, labor and consumers, foreign
A15: entities}. Rows sum to 1.0 by construction.
... A115: - FoGPbEaIC-isic (values; matches FoGPbEaIC-isic.csv)

Sheet Keys
A1: category | B1: key | C1: value | D1: description
A2: deflator | B2: deflator_nominal_to_2012 | C2: 1.12266 | D2: Divide nominal 2019 USD by this to get 2012 USD. BEA chained GDP price index; 2012 = 100.000, 2019 = 112.266
A3: year | B3: base_year | C3: 2019 | D3: stateior base year; nominal-USD vintage of the source tabs
A4: numeric | B4: epsilon_div_floor | C4: 1e-09 | D4: Denominator floor for ratio outputs (DCS, ESoP): x/MAX(den, epsilon) avoids div-by-zero; mirrors pmax(den, 1e-9) in the R pipeline
A5: numeric | B5: fogp_denom_floor_usd | C5: 1 | D5: FoGP-entity denominator floor: total purchases per category floored at $1 (mirrors pmax(total, 1)); near-zero totals give near-zero fractions

Sheet 1_Gov_purchases_by_BEA
A1: BEA_Summary_code | B1: gov_purchases_USD
A2: 111CA | B2: 0
A3: 113FF | B3: 0
A4: 211 | B4: 0
A5: 212 | B5: 0
A6: 213 | B6: 0
A7: 22 | B7: 0
A8: 23 | B8: 1.3537904e+10
A9: 321 | B9: 1875579.8
A10: 327 | B10: 0
A11: 331 | B11: 0
A12: 332 | B12: 1.3377923e+08
A13: 333 | B13: 5.2551342e+08
... A74: Other | B74: 0

Sheet 2_HH_purchases_by_BEA
A1: BEA_Summary_code | B1: hh_purchases_USD
A2: 111CA | B2: 2.232004e+09
A3: 113FF | B3: 1.9574952e+08
A4: 211 | B4: 0
A5: 212 | B5: 4012188.9
A6: 213 | B6: 0
A7: 22 | B7: 9.5862178e+09
A8: 23 | B8: 0
A9: 321 | B9: 1.6162434e+08
A10: 327 | B10: 4.815399e+08
A11: 331 | B11: 51707519
A12: 332 | B12: 8.1038602e+08
A13: 333 | B13: 3.8532106e+08
... A74: Other | B74: -2.949457e+09

Sheet 3_Intl_purchases_by_BEA
A1: BEA_Summary_code | B1: intl_purchases_USD (F040)
A2: 111CA | B2: 2.0331536e+08
A3: 113FF | B3: 1.1285133e+08
A4: 211 | B4: 2.1873764e+08
A5: 212 | B5: 2.7103859e+09
A6: 213 | B6: 96875229
A7: 22 | B7: 1.4738181e+08
A8: 23 | B8: 3641953.5
A9: 321 | B9: 3.2404295e+08
A10: 327 | B10: 4.076399e+08
A11: 331 | B11: 2.1947827e+09
A12: 332 | B12: 1.1255971e+09
A13: 333 | B13: 2.944161e+09
... A74: Other | B74: 6.6474141e+09

Sheet 4_DomInd_purchases_by_BEA
A1: BEA_Summary_code | B1: domestic_industry_purchases_USD
A2: 111CA | B2: 7.6797977e+09
A3: 113FF | B3: 1.561488e+09
A4: 211 | B4: 3.0802972e+09
A5: 212 | B5: 1.8470904e+09
A6: 213 | B6: 1.496663e+09
A7: 22 | B7: 1.3093084e+10
A8: 23 | B8: 1.0031804e+10
A9: 321 | B9: 5.446772e+09
A10: 327 | B10: 6.195119e+09
A11: 331 | B11: 2.8332412e+10
A12: 332 | B12: 1.8213369e+10
A13: 333 | B13: 7.1503884e+09
... A74: Other | B74: 4.4540486e+09

Sheet 5_Total_purchases_by_BEA
A1: BEA_Summary_code | B1: total_purchases_USD (= gov+hh+intl+domInd)
A2: ='1_Gov_purchases_by_BEA'!A2 | B2: ='1_Gov_purchases_by_BEA'!B2+'2_HH_purchases_by_BEA'!B2+'3_Intl_purchases_by_BEA'!B2+'4_DomInd_purchases_by_BEA'!B2
A3: ='1_Gov_purchases_by_BEA'!A3 | B3: ='1_Gov_purchases_by_BEA'!B3+'2_HH_purchases_by_BEA'!B3+'3_Intl_purchases_by_BEA'!B3+'4_DomInd_purchases_by_BEA'!B3
A4: ='1_Gov_purchases_by_BEA'!A4 | B4: ='1_Gov_purchases_by_BEA'!B4+'2_HH_purchases_by_BEA'!B4+'3_Intl_purchases_by_BEA'!B4+'4_DomInd_purchases_by_BEA'!B4
A5: ='1_Gov_purchases_by_BEA'!A5 | B5: ='1_Gov_purchases_by_BEA'!B5+'2_HH_purchases_by_BEA'!B5+'3_Intl_purchases_by_BEA'!B5+'4_DomInd_purchases_by_BEA'!B5
A6: ='1_Gov_purchases_by_BEA'!A6 | B6: ='1_Gov_purchases_by_BEA'!B6+'2_HH_purchases_by_BEA'!B6+'3_Intl_purchases_by_BEA'!B6+'4_DomInd_purchases_by_BEA'!B6
A7: ='1_Gov_purchases_by_BEA'!A7 | B7: ='1_Gov_purchases_by_BEA'!B7+'2_HH_purchases_by_BEA'!B7+'3_Intl_purchases_by_BEA'!B7+'4_DomInd_purchases_by_BEA'!B7
A8: ='1_Gov_purchases_by_BEA'!A8 | B8: ='1_Gov_purchases_by_BEA'!B8+'2_HH_purchases_by_BEA'!B8+'3_Intl_purchases_by_BEA'!B8+'4_DomInd_purchases_by_BEA'!B8
A9: ='1_Gov_purchases_by_BEA'!A9 | B9: ='1_Gov_purchases_by_BEA'!B9+'2_HH_purchases_by_BEA'!B9+'3_Intl_purchases_by_BEA'!B9+'4_DomInd_purchases_by_BEA'!B9
A10: ='1_Gov_purchases_by_BEA'!A10 | B10: ='1_Gov_purchases_by_BEA'!B10+'2_HH_purchases_by_BEA'!B10+'3_Intl_purchases_by_BEA'!B10+'4_DomInd_purchases_by_BEA'!B10
A11: ='1_Gov_purchases_by_BEA'!A11 | B11: ='1_Gov_purchases_by_BEA'!B11+'2_HH_purchases_by_BEA'!B11+'3_Intl_purchases_by_BEA'!B11+'4_DomInd_purchases_by_BEA'!B11
A12: ='1_Gov_purchases_by_BEA'!A12 | B12: ='1_Gov_purchases_by_BEA'!B12+'2_HH_purchases_by_BEA'!B12+'3_Intl_purchases_by_BEA'!B12+'4_DomInd_purchases_by_BEA'!B12
A13: ='1_Gov_purchases_by_BEA'!A13 | B13: ='1_Gov_purchases_by_BEA'!B13+'2_HH_purchases_by_BEA'!B13+'3_Intl_purchases_by_BEA'!B13+'4_DomInd_purchases_by_BEA'!B13
... A74: ='1_Gov_purchases_by_BEA'!A74 | B74: ='1_Gov_purchases_by_BEA'!B74+'2_HH_purchases_by_BEA'!B74+'3_Intl_purchases_by_BEA'!B74+'4_DomInd_purchases_by_BEA'!B74

Sheet 1_Entity_totals
A1: Entity | B1: SoI_total_USD
A2: Government | B2: 3.3919559e+10
A3: Households | B3: 5.0036746e+10
A4: Intl Exports | B4: 2.2324089e+10
A5: Domestic Industries | B5: 1.7402937e+11

Sheet 2_Row_tot_by_ISIC
A1: ISIC_code | B1: total_consumption_USD
A2: 01T03 | B2: 1.3090834e+10
A3: 05 | B3: 1.9713873e+09
A4: 06 | B4: 6.4400289e+09
A5: 07T08 | B5: 1.3077935e+09
A6: 09 | B6: 8.1773639e+08
A7: 10T12 | B7: 1.4497726e+10
A8: 13T15 | B8: 2.3641273e+09
A9: 16 | B9: 4.4858052e+09
A10: 17T18 | B10: 1.0448547e+10
A11: 19 | B11: 1.1535414e+10
A12: 20 | B12: 1.1180973e+10
A13: 21 | B13: 1.3665634e+10
... A43: 97T98 | B43: 0

Sheet Src_Stateior_SoI_TotUse
A1: State-of-Interest Total Use matrix at BEA Summary resolution, from
A2: EPA stateior. Rows = commodities, columns = industries + final demand
A3: categories (F01* PCE, F02* investment, F06* fed nondefense, F07* fed
A4: defense, F10* state and local, F040 intl exports, F050 intl imports).
A5: Values in nominal 2019 USD. This is the raw input used to compute
A6: DCS, ESoP, government/household expenditures, and Leontief coefficients.
A9: commodity | B9: 111CA | C9: 113FF | D9: 211 | E9: 212 | F9: 213 | G9: 22 | H9: 23 | I9: 321 | J9: 327 | K9: 331 | L9: 332 | M9: 333 | N9: 334 | O9: 335 | P9: 3361MV | Q9: 3364OT | R9: 337 | S9: 339 | T9: 311FT | U9: 313TT | V9: 315AL | W9: 322 | X9: 323 | Y9: 324 | Z9: 325 | AA9: 326 | AB9: 42 | AC9: 441 | AD9: 445 | AE9: 452 | AF9: 4A0 | AG9: 481 | AH9: 482 | AI9: 483 | AJ9: 484 | AK9: 485 | AL9: 486 | AM9: 487OS | AN9: 493 | AO9: 511 | AP9: 512 | AQ9: 513 | AR9: 514 | AS9: 521CI | AT9: 523 | AU9: 524 | AV9: 525 | AW9: HS | AX9: ORE | AY9: 532RL | AZ9: 5411 | BA9: 5415 | BB9: 5412OP | BC9: 55 | BD9: 561 | BE9: 562 | BF9: 61 | BG9: 621 | BH9: 622 | BI9: 623 | BJ9: 624 | BK9: 711AS | BL9: 713 | BM9: 721 | BN9: 722 | BO9: 81 | BP9: GFGD | BQ9: GFGN | BR9: GFE | BS9: GSLG | BT9: GSLE | BU9: F010 | BV9: F02S | BW9: F02E | BX9: F02N | BY9: F02R | BZ9: F030 | CA9: F040 | CB9: F050 | CC9: F06C | CD9: F06S | CE9: F06E | CF9: F06N | CG9: F07C | CH9: F07S | CI9: F07E | CJ9: F07N | CK9: F10C | CL9: F10S | CM9: F10E | CN9: F10N
A10: 111CA | B10: 7.0095552e+08 | C10: 2321077.6 | D10: 0 | E10: 372256.47 | F10: 357267.6 | G10: 0 | H10: 20345495 | I10: 0 | J10: 0 | K10: 0 | L10: 0 | M10: 0 | N10: 0 | O10: 0 | P10: 0 | Q10: 0 | R10: 0 | S10: 4433491.9 | T10: 3.323525e+09 | U10: 14837353 | V10: 0 | W10: 0 | X10: 0 | Y10: 0 | Z10: 2.9246606e+08 | AA10: 0 | AB10: 10398928 | AC10: 10561469 | AD10: 15783719 | AE10: 2098249.7 | AF10: 5006485.5 | AG10: 0 | AH10: 0 | AI10: 0 | AJ10: 0 | AK10: 0 | AL10: 0 | AM10: 450771.91 | AN10: 0 | AO10: 0 | AP10: 0 | AQ10: 0 | AR10: 0 | AS10: 9562.8461 | AT10: 0 | AU10: 0 | AV10: 0 | AW10: 0 | AX10: 39605.093 | AY10: 0 | AZ10: 17640.122 | BA10: 0 | BB10: 16887712 | BC10: 548283.32 | BD10: 23820775 | BE10: 0 | BF10: 6886616.2 | BG10: 0 | BH10: 0 | BI10: 0 | BJ10: 0 | BK10: 0 | BL10: 10338146 | BM10: 537534.75 | BN10: 1.0802345e+08 | BO10: 282056.1 | BP10: 83861.626 | BQ10: -1988008 | BR10: 0 | BS10: 56184727 | BT10: 0 | BU10: 1.6724697e+09 | BV10: 0 | BW10: 0 | BX10: 0 | BY10: 0 | BZ10: -2.9101602e+08 | CA10: 2.0331536e+08 | CB10: -1.5871357e+09 | CC10: 0 | CD10: 0 | CE10: 0 | CF10: 0 | CG10: 0 | CH10: 0 | CI10: 0 | CJ10: 0 | CK10: 0 | CL10: 0 | CM10: 0 | CN10: 0
A11: 113FF | B11: 3.2535263e+08 | C11: 57223790 | D11: 0 | E11: 2467629.4 | F11: 0 | G11: 0 | H11: 0 | I11: 3.471188e+08 | J11: 0 | K11: 0 | L11: 0 | M11: 0 | N11: 0 | O11: 0 | P11: 0 | Q11: 0 | R11: 2971612.9 | S11: 7470976.8 | T11: 2.7830544e+08 | U11: 0 | V11: 1330179.3 | W11: 1.1946286e+08 | X11: 1010136.2 | Y11: 0 | Z11: 14867914 | AA11: 80529121 | AB11: 0 | AC11: 0 | AD11: 26546100 | AE11: 0 | AF11: 0 | AG11: 0 | AH11: 0 | AI11: 0 | AJ11: 0 | AK11: 0 | AL11: 0 | AM11: 28524.508 | AN11: 0 | AO11: 0 | AP11: 0 | AQ11: 0 | AR11: 0 | AS11: 0 | AT11: 0 | AU11: 0 | AV11: 0 | AW11: 0 | AX11: 0 | AY11: 0 | AZ11: 0 | BA11: 0 | BB11: 7966917.7 | BC11: 820900.2 | BD11: 62148.384 | BE11: 0 | BF11: 3435205.8 | BG11: 0 | BH11: 0 | BI11: 0 | BJ11: 0 | BK11: 0 | BL11: 7626784.9 | BM11: 8260209.2 | BN11: 1.5084375e+08 | BO11: 2945907.6 | BP11: 0 | BQ11: 888197.2 | BR11: 400237.48 | BS11: 1.0331598e+08 | BT11: 0 | BU11: 1.9497662e+08 | BV11: 0 | BW11: 0 | BX11: 0 | BY11: 0 | BZ11: 21908447 | CA11: 1.1285133e+08 | CB11: -6.7678292e+08 | CC11: 0 | CD11: 0 | CE11: 0 | CF11: 0 | CG11: 0 | CH11: 0 | CI11: 0 | CJ11: 0 | CK11: 0 | CL11: 0 | CM11: 0 | CN11: 0
A12: 211 | B12: 0 | C12: 0 | D12: 69777684 | E12: 0 | F12: 148449.29 | G12: 66186507 | H12: 0 | I12: 54332.662 | J12: 1366.7463 | K12: 10057.708 | L12: 0 | M12: 0 | N12: 0 | O12: 0 | P12: 370.55743 | Q12: 0 | R12: 0 | S12: 0 | T12: 1125.9568 | U12: 0 | V12: 0 | W12: 71385.292 | X12: 1682.6013 | Y12: 2.4625388e+09 | Z12: 16876661 | AA12: 0 | AB12: 37642.252 | AC12: 41368.072 | AD12: 0 | AE12: 1150.6356 | AF12: 62895.575 | AG12: 0 | AH12: 0 | AI12: 0 | AJ12: 0 | AK12: 0 | AL12: 327980.79 | AM12: 0 | AN12: 1877891.6 | AO12: 532232.54 | AP12: 0 | AQ12: 66701.373 | AR12: 69007.403 | AS12: 0 | AT12: 0 | AU12: 0 | AV12: 0 | AW12: 0 | AX12: 218795.91 | AY12: 0 | AZ12: 0 | BA12: 849.60807 | BB12: 41308.359 | BC12: 64320.826 | BD12: 0 | BE12: 41638.285 | BF12: 5330545.5 | BG12: 1371.0121 | BH12: 0 | BI12: 1846.9516 | BJ12: 0 | BK12: 0 | BL12: 329673.35 | BM12: 715.15626 | BN12: 962.10529 | BO12: 81772.457 | BP12: 0 | BQ12: 0 | BR12: 3528886.3 | BS12: 0 | BT12: 31746150 | BU12: 0 | BV12: 0 | BW12: 0 | BX12: 0 | BY12: 0 | BZ12: 13965843 | CA12: 2.1873764e+08 | CB12: -2.5448188e+09 | CC12: 0 | CD12: 0 | CE12: 0 | CF12: 0 | CG12: 0 | CH12: 0 | CI12: 0 | CJ12: 0 | CK12: 0 | CL12: 0 | CM12: 0 | CN12: 0
A13: 212 | B13: 13218714 | C13: 0 | D13: 1015113.7 | E13: 1.4443459e+08 | F13: 3572720.7 | G13: 97085587 | H13: 2.659323e+08 | I13: 195308.19 | J13: 2.1904627e+08 | K13: 4.7118225e+08 | L13: 12175695 | M13: 2178097.3 | N13: 86115.749 | O13: 3268580.1 | P13: 573738.44 | Q13: 902808.07 | R13: 274009.62 | S13: 2359099.1 | T13: 25621462 | U13: 448439.84 | V13: 0 | W13: 46844374 | X13: 0 | Y13: 28126913 | Z13: 1.6714932e+08 | AA13: 3365245.5 | AB13: 421757.17 | AC13: 0 | AD13: 0 | AE13: 0 | AF13: 44830.062 | AG13: 0 | AH13: 1959260.1 | AI13: 0 | AJ13: 132999.9 | AK13: 18148.399 | AL13: 0 | AM13: 13974.733 | AN13: 72571.228 | AO13: 209347.73 | AP13: 102285.41 | AQ13: 8603519.7 | AR13: 5703601 | AS13: 0 | AT13: 0 | AU13: 0 | AV13: 0 | AW13: 87346.14 | AX13: 0 | AY13: 0 | AZ13: 0 | BA13: 0 | BB13: 26352850 | BC13: 952336.65 | BD13: 12736556 | BE13: 951368.38 | BF13: 14330474 | BG13: 0 | BH13: 442846.55 | BI13: 902842.1 | BJ13: 3955614.7 | BK13: 4679366.2 | BL13: 12020654 | BM13: 1583588.5 | BN13: 10685313 | BO13: 21826825 | BP13: 0 | BQ13: 34514232 | BR13: 0 | BS13: 48444900 | BT13: 47103761 | BU13: 3830537.2 | BV13: 0 | BW13: 1638675.5 | BX13: 0 | BY13: 0 | BZ13: 29979700 | CA13: 2.7103859e+09 | CB13: -3.2053201e+08 | CC13: 0 | CD13: 0 | CE13: 0 | CF13: 0 | CG13: 0 | CH13: 0 | CI13: 0 | CJ13: 0 | CK13: 0 | CL13: 0 | CM13: 0 | CN13: 0
A14: 213 | B14: 0 | C14: 0 | D14: 4.8340927e+08 | E14: 44316813 | F14: 1.4450934e+08 | G14: 0 | H14: 0 | I14: 0 | J14: 0 | K14: 0 | L14: 0 | M14: 0 | N14: 0 | O14: 0 | P14: 0 | Q14: 0 | R14: 0 | S14: 0 | T14: 0 | U14: 0 | V14: 0 | W14: 0 | X14: 0 | Y14: 0 | Z14: 0 | AA14: 0 | AB14: 0 | AC14: 0 | AD14: 0 | AE14: 0 | AF14: 0 | AG14: 0 | AH14: 0 | AI14: 0 | AJ14: 0 | AK14: 0 | AL14: 0 | AM14: 0 | AN14: 0 | AO14: 0 | AP14: 0 | AQ14: 0 | AR14: 0 | AS14: 0 | AT14: 0 | AU14: 0 | AV14: 0 | AW14: 0 | AX14: 0 | AY14: 0 | AZ14: 0 | BA14: 0 | BB14: 903602.67 | BC14: 149684.13 | BD14: 0 | BE14: 0 | BF14: 0 | BG14: 0 | BH14: 0 | BI14: 0 | BJ14: 0 | BK14: 0 | BL14: 0 | BM14: 0 | BN14: 0 | BO14: 0 | BP14: 0 | BQ14: 0 | BR14: 0 | BS14: 0 | BT14: 0 | BU14: 0 | BV14: 6.7802856e+09 | BW14: 1.4400995e+08 | BX14: 0 | BY14: 0 | BZ14: -346407.19 | CA14: 96875229 | CB14: -40191362 | CC14: 0 | CD14: 0 | CE14: 0 | CF14: 0 | CG14: 0 | CH14: 0 | CI14: 0 | CJ14: 0 | CK14: 0 | CL14: 0 | CM14: 0 | CN14: 0
A15: 22 | B15: 51265167 | C15: 207368.96 | D15: 49977248 | E15: 50666489 | F15: 9381966 | G15: 2.9323438e+08 | H15: 81428732 | I15: 22107849 | J15: 46141618 | K15: 1.4410936e+08 | L15: 62521694 | M15: 24849409 | N15: 7815738.4 | O15: 12143692 | P15: 10063467 | Q15: 15875524 | R15: 6812158.2 | S15: 9447052.5 | T15: 88040447 | U15: 5679939.9 | V15: 222298.56 | W15: 1.0562848e+08 | X15: 17656470 | Y15: 30695082 | Z15: 1.9632191e+08 | AA15: 73736438 | AB15: 1.4068458e+08 | AC15: 45029310 | AD15: 1.1479811e+08 | AE15: 79254247 | AF15: 1.3207561e+08 | AG15: 8601366.3 | AH15: 614129.6 | AI15: 353690.77 | AJ15: 52791116 | AK15: 4439561 | AL15: 64889922 | AM15: 11090906 | AN15: 49165422 | AO15: 5632207.4 | AP15: 1535331.9 | AQ15: 1.035848e+08 | AR15: 16054723 | AS15: 21804690 | AT15: 9940719 | AU15: 7741160.1 | AV15: 1989404.8 | AW15: 1879478.5 | AX15: 1.9375409e+08 | AY15: 9547140.9 | AZ15: 8010165.2 | BA15: 6336190.7 | BB15: 58784085 | BC15: 85406124 | BD15: 26988944 | BE15: 15496293 | BF15: 1.0779896e+08 | BG15: 50519179 | BH15: 1.0862453e+08 | BI15: 60326553 | BJ15: 20202817 | BK15: 10845567 | BL15: 34690443 | BM15: 38252580 | BN15: 1.6623036e+08 | BO15: 76777205 | BP15: 9530671.5 | BQ15: 11827796 | BR15: 22463070 | BS15: 2.0177711e+08 | BT15: 19475292 | BU15: 2.5868563e+09 | BV15: 0 | BW15: 0 | BX15: 0 | BY15: 0 | BZ15: 0 | CA15: 1.4738181e+08 | CB15: -78501977 | CC15: 0 | CD15: 0 | CE15: 0 | CF15: 0 | CG15: 0 | CH15: 0 | CI15: 0 | CJ15: 0 | CK15: 0 | CL15: 0 | CM15: 0 | CN15: 0
A16: 23 | B16: 33096559 | C16: 307726.34 | D16: 4141723.6 | E16: 1.6205617e+08 | F16: 1.2900316e+08 | G16: 2.1933797e+08 | H16: 9795290.5 | I16: 15696964 | J16: 40355624 | K16: 1.1736342e+08 | L16: 70547113 | M16: 35188574 | N16: 10577199 | O16: 10167119 | P16: 10239842 | Q16: 9187511.1 | R16: 5808056.9 | S16: 12884766 | T16: 77037703 | U16: 2815211.7 | V16: 187691.03 | W16: 78452436 | X16: 17939100 | Y16: 1.6540424e+08 | Z16: 1.1621695e+08 | AA16: 47077374 | AB16: 1.3750818e+08 | AC16: 53572419 | AD16: 47140335 | AE16: 76738961 | AF16: 1.1370596e+08 | AG16: 7681228.2 | AH16: 82704205 | AI16: 370745.54 | AJ16: 24115813 | AK16: 21114841 | AL16: 1.5959433e+08 | AM16: 35997929 | AN16: 67028220 | AO16: 3544158 | AP16: 952557.46 | AQ16: 1.5436831e+08 | AR16: 15995725 | AS16: 1.5176116e+08 | AT16: 52158911 | AU16: 37946865 | AV16: 362962.96 | AW16: 3.1286599e+09 | AX16: 8.9274957e+08 | AY16: 24474762 | AZ16: 8987416.5 | BA16: 2285693.8 | BB16: 91192297 | BC16: 51749491 | BD16: 30173041 | BE16: 5941926.8 | BF16: 1.4941047e+08 | BG16: 34470816 | BH16: 64378880 | BI16: 41100272 | BJ16: 36111183 | BK16: 9392635.3 | BL16: 23742194 | BM16: 71139723 | BN16: 77107091 | BO16: 1.5182277e+08 | BP16: 91081144 | BQ16: 17297169 | BR16: 20871654 | BS16: 1.1860355e+09 | BT16: 1.1763793e+09 | BU16: 0 | BV16: 1.8450837e+10 | BW16: 0 | BX16: 0 | BY16: 2.3265896e+10 | BZ16: 0 | CA16: 3641953.5 | CB16: 0 | CC16: 0 | CD16: 0 | CE16: 0 | CF16: 0 | CG16: 0 | CH16: 3.8216541e+08 | CI16: 0 | CJ16: 0 | CK16: 0 | CL16: 1.3155739e+10 | CM16: 0 | CN16: 0
A17: 321 | B17: 7359517.1 | C17: 534825.93 | D17: 0 | E17: 4378353.3 | F17: 8762161.9 | G17: 109788.51 | H17: 9.3001847e+08 | I17: 7.7817645e+08 | J17: 5020477.7 | K17: 28882256 | L17: 6134622.7 | M17: 19484411 | N17: 3286546.1 | O17: 22675276 | P17: 23155023 | Q17: 2636133.3 | R17: 1.7174181e+08 | S17: 28263527 | T17: 8676856.1 | U17: 1001973 | V17: 0 | W17: 1.8336862e+08 | X17: 55885.045 | Y17: 0 | Z17: 8789163.8 | AA17: 69923788 | AB17: 1.3488629e+08 | AC17: 3285735 | AD17: 16401844 | AE17: 3477824.5 | AF17: 17433657 | AG17: 0 | AH17: 48230557 | AI17: 0 | AJ17: 4658568.8 | AK17: 0 | AL17: 1060440.5 | AM17: 949405.64 | AN17: 6103571.3 | AO17: 657886.89 | AP17: 646605.75 | AQ17: 30477566 | AR17: 11646946 | AS17: 4266208.1 | AT17: 127152.37 | AU17: 0 | AV17: 0 | AW17: 528112.18 | AX17: 95257495 | AY17: 7085717.9 | AZ17: 424665.85 | BA17: 702750.27 | BB17: 19670105 | BC17: 175733.1 | BD17: 19681279 | BE17: 827959.68 | BF17: 1765669 | BG17: 11334379 | BH17: 16257402 | BI17: 203496.82 | BJ17: 22984536 | BK17: 168840.51 | BL17: 3954411.9 | BM17: 14852541 | BN17: 17386057 | BO17: 9493855.3 | BP17: 157243.5 | BQ17: 839930.84 | BR17: 63457.51 | BS17: 53849964 | BT17: 4055481.3 | BU17: 1.1853331e+08 | BV17: 7075803.7 | BW17: 0 | BX17: 0 | BY17: 1.6868782e+08 | BZ17: 22522981 | CA17: 3.2404295e+08 | CB17: -7.9411079e+08 | CC17: 0 | CD17: 0 | CE17: 0 | CF17: 0 | CG17: 0 | CH17: 0 | CI17: 704915.75 | CJ17: 0 | CK17: 0 | CL17: 0 | CM17: 0 | CN17: 0
A18: 327 | B18: 225325.19 | C18: 495572.6 | D18: 18835056 | E18: 12092404 | F18: 30254716 | G18: 1222306 | H18: 1.4470147e+09 | I18: 29140964 | J18: 4.0453258e+08 | K18: 1.4327172e+08 | L18: 52707351 | M18: 43150746 | N18: 3915399.1 | O18: 66112244 | P18: 52801822 | Q18: 4124505.6 | R18: 9824525.9 | S18: 19770458 | T18: 92878051 | U18: 467190.79 | V18: 0 | W18: 18889129 | X18: 30637.995 | Y18: 19338929 | Z18: 50138118 | AA18: 69030936 | AB18: 2033679.8 | AC18: 5438067.9 | AD18: 1578577.9 | AE18: 6326211.7 | AF18: 11026239 | AG18: 0 | AH18: 309108.55 | AI18: 0 | AJ18: 3600142.6 | AK18: 0 | AL18: 0 | AM18: 241954.13 | AN18: 4381466.5 | AO18: 27560.601 | AP18: 7153.7385 | AQ18: 1.1340653e+08 | AR18: 7762317.9 | AS18: 548031.48 | AT18: 629849.32 | AU18: 1220839.8 | AV18: 0 | AW18: 2292647.3 | AX18: 816915.14 | AY18: 10420434 | AZ18: 0 | BA18: 2941210.2 | BB18: 1.1161838e+08 | BC18: 1866847.4 | BD18: 17741036 | BE18: 8197985.7 | BF18: 3905140.4 | BG18: 63078607 | BH18: 96972858 | BI18: 5563641 | BJ18: 15842121 | BK18: 282243.96 | BL18: 3337794.1 | BM18: 1489212.7 | BN18: 49405706 | BO18: 36689049 | BP18: 433457.67 | BQ18: 11966988 | BR18: 0 | BS18: 40136098 | BT18: 37585730 | BU18: 3.3480613e+08 | BV18: 0 | BW18: 0 | BX18: 0 | BY18: 0 | BZ18: 51903200 | CA18: 4.076399e+08 | CB18: -1.1091658e+09 | CC18: 0 | CD18: 0 | CE18: 0 | CF18: 0 | CG18: 0 | CH18: 0 | CI18: 0 | CJ18: 0 | CK18: 0 | CL18: 0 | CM18: 0 | CN18: 0
A19: 331 | B19: 1574541.9 | C19: 0 | D19: 81248073 | E19: 14339120 | F19: 19169216 | G19: 81385.037 | H19: 1.1444073e+08 | I19: 9224861.5 | J19: 44352126 | K19: 5.2656098e+09 | L19: 2.3321345e+09 | M19: 8.9440796e+08 | N19: 67951758 | O19: 5.5940732e+08 | P19: 3.3458077e+08 | Q19: 97599831 | R19: 90383146 | S19: 1.4420121e+08 | T19: 55668417 | U19: 1161240.8 | V19: 0 | W19: 47886663 | X19: 463539.4 | Y19: 184440.11 | Z19: 2197751.5 | AA19: 61076478 | AB19: 12778897 | AC19: 161819.84 | AD19: 0 | AE19: 0 | AF19: 11941349 | AG19: 0 | AH19: 13423746 | AI19: 0 | AJ19: 0 | AK19: 0 | AL19: 0 | AM19: 2790172.9 | AN19: 0 | AO19: 206639.16 | AP19: 80213.923 | AQ19: 17827911 | AR19: 7056156.9 | AS19: 0 | AT19: 0 | AU19: 0 | AV19: 0 | AW19: 23926.688 | AX19: 33974317 | AY19: 1590294.7 | AZ19: 0 | BA19: 0 | BB19: 42953233 | BC19: 1999433.9 | BD19: 12584722 | BE19: 8272512.7 | BF19: 8998152.3 | BG19: 5526510.6 | BH19: 867412.72 | BI19: 603090.08 | BJ19: 11439425 | BK19: 602735.15 | BL19: 8315950.4 | BM19: 551053.17 | BN19: 2469852 | BO19: 22769078 | BP19: 2441255.1 | BQ19: 11158644 | BR19: 0 | BS19: 2013009.2 | BT19: 10430918 | BU19: 16764367 | BV19: 0 | BW19: 0 | BX19: 0 | BY19: 0 | BZ19: 1.8781587e+08 | CA19: 2.1947827e+09 | CB19: -5.0126454e+09 | CC19: 0 | CD19: 0 | CE19: 0 | CF19: 0 | CG19: 0 | CH19: 0 | CI19: 0 | CJ19: 0 | CK19: 0 | CL19: 0 | CM19: 0 | CN19: 0
A20: 332 | B20: 25912635 | C20: 1110537.7 | D20: 1.4200249e+08 | E20: 28143387 | F20: 31713008 | G20: 19515831 | H20: 1.7317921e+09 | I20: 86581625 | J20: 46979385 | K20: 2.584808e+08 | L20: 1.0956007e+09 | M20: 5.4428002e+08 | N20: 77413513 | O20: 2.9835648e+08 | P20: 1.8119977e+08 | Q20: 1.4133784e+08 | R20: 1.0365726e+08 | S20: 95922812 | T20: 3.4819372e+08 | U20: 6438246 | V20: 642332.18 | W20: 2.355807e+08 | X20: 22528896 | Y20: 18994419 | Z20: 2.9631209e+08 | AA20: 2.4856202e+08 | AB20: 50526620 | AC20: 7702649.6 | AD20: 5705318.9 | AE20: 3216636.8 | AF20: 35235964 | AG20: 4416075.9 | AH20: 8350218.6 | AI20: 5207295.9 | AJ20: 45561895 | AK20: 8798475.1 | AL20: 1.4834512e+08 | AM20: 6705984 | AN20: 37828984 | AO20: 9180666.1 | AP20: 313902.67 | AQ20: 4.3309686e+08 | AR20: 18541045 | AS20: 6377587.1 | AT20: 3494159.8 | AU20: 0 | AV20: 109176.03 | AW20: 450974.62 | AX20: 24129768 | AY20: 25083563 | AZ20: 953375.64 | BA20: 42266155 | BB20: 1.2702422e+08 | BC20: 20996796 | BD20: 46981387 | BE20: 83074345 | BF20: 19619263 | BG20: 9290896.8 | BH20: 47454446 | BI20: 951171.88 | BJ20: 87021018 | BK20: 932227.91 | BL20: 12529962 | BM20: 21966697 | BN20: 62085435 | BO20: 1.0465807e+08 | BP20: 43904264 | BQ20: 25632775 | BR20: 4359464.1 | BS20: 75289689 | BT20: 64380808 | BU20: 4.7442042e+08 | BV20: 0 | BW20: 4.7740388e+08 | BX20: 0 | BY20: 0 | BZ20: 1.9877205e+08 | CA20: 1.1255971e+09 | CB20: -2.7443018e+09 | CC20: 0 | CD20: 0 | CE20: 0 | CF20: 0 | CG20: 0 | CH20: 0 | CI20: 1.0486779e+08 | CJ20: 0 | CK20: 0 | CL20: 0 | CM20: 6623278.6 | CN20: 0
A21: 333 | B21: 38278262 | C21: 346804.97 | D21: 1.3805662e+08 | E21: 1.120599e+08 | F21: 1.7085635e+08 | G21: 40313815 | H21: 6.7883854e+08 | I21: 13633899 | J21: 3204937 | K21: 51589094 | L21: 1.5166538e+08 | M21: 8.3853838e+08 | N21: 5723201 | O21: 79349387 | P21: 2.5740925e+08 | Q21: 42068282 | R21: 2785242 | S21: 19685069 | T21: 1.045116e+08 | U21: 410581.24 | V21: 11855.284 | W21: 62618596 | X21: 46348894 | Y21: 911409.47 | Z21: 1.4119121e+08 | AA21: 64013899 | AB21: 55596899 | AC21: 4739518.9 | AD21: 3281388.5 | AE21: 2515611.5 | AF21: 13737429 | AG21: 86334.187 | AH21: 954762.22 | AI21: 299589.09 | AJ21: 12086173 | AK21: 1183862.5 | AL21: 8714347.2 | AM21: 1.2605825e+08 | AN21: 68587531 | AO21: 937474.21 | AP21: 214016.86 | AQ21: 44387471 | AR21: 5796689.6 | AS21: 91268.59 | AT21: 653567.43 | AU21: 22467133 | AV21: 0 | AW21: 737138.8 | AX21: 1078883.1 | AY21: 10257657 | AZ21: 441519.94 | BA21: 45792828 | BB21: 68143893 | BC21: 13039880 | BD21: 88518363 | BE21: 1.4404367e+08 | BF21: 87251854 | BG21: 27998918 | BH21: 23863165 | BI21: 4838747.9 | BJ21: 5689025.5 | BK21: 544799.65 | BL21: 4101194.9 | BM21: 953897.43 | BN21: 11345233 | BO21: 1.4818404e+08 | BP21: 9057212.8 | BQ21: 4794167.3 | BR21: 1229140.5 | BS21: 97041915 | BT21: 36681103 | BU21: 2.7958915e+08 | BV21: 0 | BW21: 5.644646e+09 | BX21: 0 | BY21: 0 | BZ21: 1.33342e+08 | CA21: 2.944161e+09 | CB21: -6.7099476e+09 | CC21: 0 | CD21: 0 | CE21: 7043930.5 | CF21: 0 | CG21: 0 | CH21: 0 | CI21: 8641360.8 | CJ21: 0 | CK21: 0 | CL21: 0 | CM21: 2.7882009e+08 | CN21: 0
... A82: Other | B82: 20182411 | C82: 346192.14 | D82: 21840689 | E82: 926299.93 | F82: 20815995 | G82: 58975270 | H82: 52693105 | I82: 10065990 | J82: 13436743 | K82: 69705409 | L82: 36482935 | M82: 51830790 | N82: 48878602 | O82: 19864083 | P82: 27630342 | Q82: 9770845.1 | R82: 5033649.3 | S82: 16811189 | T82: 82722039 | U82: 2333978.9 | V82: 469227.57 | W82: 41046543 | X82: 13691836 | Y82: 1.1953281e+08 | Z82: 1.2841622e+08 | AA82: 37982231 | AB82: 2.5616357e+08 | AC82: 4409092 | AD82: 19926247 | AE82: 31719789 | AF82: 1.0260315e+08 | AG82: 3.9897481e+08 | AH82: 4402762.7 | AI82: 10826928 | AJ82: 44928710 | AK82: 777915.19 | AL82: 29585371 | AM82: 13805862 | AN82: 6517661.2 | AO82: 17494567 | AP82: 6733145.9 | AQ82: 3.9725235e+08 | AR82: 13329771 | AS82: 99716625 | AT82: 1.1405749e+09 | AU82: 68351497 | AV82: 737037.04 | AW82: 1025147.1 | AX82: 21213072 | AY82: 39534181 | AZ82: 9770934.8 | BA82: 56719067 | BB82: 1.2616134e+08 | BC82: 1.1460116e+08 | BD82: 44280724 | BE82: 4527182.3 | BF82: 32122509 | BG82: 0 | BH82: 0 | BI82: 19139231 | BJ82: 0 | BK82: 13089335 | BL82: 9024357.4 | BM82: 16294441 | BN82: 64548829 | BO82: 1.6082026e+08 | BP82: 80282160 | BQ82: 60459863 | BR82: 117586.78 | BS82: 0 | BT82: 0 | BU82: -2.949457e+09 | BV82: 0 | BW82: 0 | BX82: 3.0879851e+08 | BY82: 0 | BZ82: 0 | CA82: 6.6474141e+09 | CB82: -9.9197804e+09 | CC82: 0 | CD82: 0 | CE82: 0 | CF82: 0 | CG82: 0 | CH82: 0 | CI82: 0 | CJ82: 0 | CK82: 0 | CL82: 0 | CM82: 0 | CN82: 0

Sheet Src_Disagg_EIA_coal
A1: Raw EIA Annual Coal Report (Form EIA-7A) 2019 state production values,
A2: used as the numerator for the 212 BEA mining disagg split (05 coal vs
A3: 07T08 other mining). Source:
A4: https://www.eia.gov/coal/annual/
A6: THIS STATE: PA
A9: state | B9: short_tons | C9: short_tons_units | D9: value_usd | E9: source_notes
A10: AL | B10: 12031000 | C10: short tons | D10: 600000000 | E10: EIA Annual Coal Report 2019; AL avg ~$50/ton bituminous
A11: AK | B11: 1000000 | C11: short tons | D11: 40000000 | E11: EIA Annual Coal Report 2019; AK Usibelli ~$40/ton subbit
A12: AZ | B12: 4220000 | C12: short tons | D12: 125000000 | E12: EIA Annual Coal Report 2019; Kayenta mine closed 2019; partial year
A13: AR | B13: 0 | C13: short tons | D13: 0
A14: CA | B14: 0 | C14: short tons | D14: 0
A15: CO | B15: 10710000 | C15: short tons | D15: 330000000 | E15: EIA ~$31/ton
A16: CT | B16: 0 | C16: short tons | D16: 0
A17: DE | B17: 0 | C17: short tons | D17: 0
A18: DC | B18: 0 | C18: short tons | D18: 0
A19: FL | B19: 0 | C19: short tons | D19: 0
A20: GA | B20: 0 | C20: short tons | D20: 0
A21: HI | B21: 0 | C21: short tons | D21: 0
A22: ID | B22: 0 | C22: short tons | D22: 0
A23: IL | B23: 45919000 | C23: short tons | D23: 1950000000 | E23: IL Basin avg ~$42/ton
A24: IN | B24: 28820000 | C24: short tons | D24: 1210000000 | E24: IL Basin avg ~$42/ton
A25: IA | B25: 0 | C25: short tons | D25: 0
A26: KS | B26: 0 | C26: short tons | D26: 0
A27: KY | B27: 36140000 | C27: short tons | D27: 1730000000 | E27: KY split East (Central App ~$58/ton) + West (IL Basin ~$40/ton)
A28: LA | B28: 2720000 | C28: short tons | D28: 60000000 | E28: lignite ~$22/ton
A29: ME | B29: 0 | C29: short tons | D29: 0
A30: MD | B30: 1320000 | C30: short tons | D30: 70000000 | E30: NA Appalachia ~$55/ton
A31: MA | B31: 0 | C31: short tons | D31: 0
A32: MI | B32: 0 | C32: short tons | D32: 0
A33: MN | B33: 0 | C33: short tons | D33: 0
A34: MS | B34: 2800000 | C34: short tons | D34: 65000000 | E34: lignite
A35: MO | B35: 264000 | C35: short tons | D35: 12000000
A36: MT | B36: 38660000 | C36: short tons | D36: 590000000 | E36: PRB subbit ~$14/ton + some bituminous
A37: NE | B37: 0 | C37: short tons | D37: 0
A38: NV | B38: 0 | C38: short tons | D38: 0
A39: NH | B39: 0 | C39: short tons | D39: 0
A40: NJ | B40: 0 | C40: short tons | D40: 0
A41: NM | B41: 10720000 | C41: short tons | D41: 260000000 | E41: San Juan + McKinley ~$24/ton
A42: NY | B42: 0 | C42: short tons | D42: 0
A43: NC | B43: 0 | C43: short tons | D43: 0
A44: ND | B44: 27870000 | C44: short tons | D44: 560000000 | E44: lignite ~$20/ton
A45: OH | B45: 8220000 | C45: short tons | D45: 430000000 | E45: Central App/NA ~$52/ton
A46: OK | B46: 930000 | C46: short tons | D46: 40000000
A47: OR | B47: 0 | C47: short tons | D47: 0
A48: PA | B48: 50110000 | C48: short tons | D48: 3000000000 | E48: anthracite + NA Appalachia; avg ~$60/ton
A49: RI | B49: 0 | C49: short tons | D49: 0
A50: SC | B50: 0 | C50: short tons | D50: 0
A51: SD | B51: 0 | C51: short tons | D51: 0
A52: TN | B52: 400000 | C52: short tons | D52: 22000000 | E52: Central App small; ~$55/ton
A53: TX | B53: 22820000 | C53: short tons | D53: 500000000 | E53: lignite ~$22/ton
A54: UT | B54: 12810000 | C54: short tons | D54: 380000000 | E54: ~$30/ton
A55: VT | B55: 0 | C55: short tons | D55: 0
A56: VA | B56: 11480000 | C56: short tons | D56: 620000000 | E56: Central App ~$54/ton
A57: WA | B57: 3050000 | C57: short tons | D57: 90000000 | E57: Centralia closed 2020
A58: WV | B58: 93320000 | C58: short tons | D58: 5050000000 | E58: Central App + NA ~$54/ton avg; largest-after-WY
A59: WI | B59: 0 | C59: short tons | D59: 0
A60: WY | B60: 276040000 | C60: short tons | D60: 3690000000 | E60: PRB subbit ~$13/ton

Sheet Src_Disagg_heuristics
A1: Hand-curated heuristic tables used as layer-3 fallback for BEA 327
A2: (nonmetallic) / 331 (primary metals) / 325 (chemicals) disaggregation
A3: when Census ASM is suppressed and GHGRP lacks coverage.
A5: Sources:
A6: - cement-heavy state list: GHGRP Subpart H 2019 facility presence
A7: + USGS Minerals Yearbook 2019 cement production rankings
A8: - glass-heavy state list: Census ASM 2017 NAICS 3272 top-6 states
A9: - steel_share: Census ASM 2017 NAICS 331 VA breakdown (2021 SUSB
A10: supplement where suppressed) + industry knowledge
A11: - pharma_share: Census ASM 2017 NAICS 325 VA breakdown +
A12: BLS QCEW 2019 NAICS 3254 employment share
A14: See R/build_state_overrides.R for the applied logic.
... A23: 331 / 325 heuristic split shares (used only where Census ASM / GHGRP unavailable):
A25: state | B25: 331_steel_share (-> ISIC 241) | C25: 331_other_share (-> ISIC 242) | D25: 325_pharma_share (-> ISIC 21) | E25: 325_chem_share (-> ISIC 20)
A26: AK | B26: 0.4 | C26: 0.6 | D26: 0.3 | E26: 0.7
A27: AL | B27: 0.7 | C27: 0.3 | D27: 0.15 | E27: 0.85
A28: AR | B28: 0.5 | C28: 0.5 | D28: 0.1 | E28: 0.9
A29: AZ | B29: 0.3 | C29: 0.7 | D29: 0.2 | E29: 0.8
A30: CA | B30: 0.35 | C30: 0.65 | D30: 0.55 | E30: 0.45
A31: CO | B31: 0.5 | C31: 0.5 | D31: 0.3 | E31: 0.7
A32: CT | B32: 0.4 | C32: 0.6 | D32: 0.5 | E32: 0.5
A33: DC | B33: 0.4 | C33: 0.6 | D33: 0.3 | E33: 0.7
A34: DE | B34: 0.5 | C34: 0.5 | D34: 0.4 | E34: 0.6
A35: FL | B35: 0.35 | C35: 0.65 | D35: 0.4 | E35: 0.6
A36: GA | B36: 0.5 | C36: 0.5 | D36: 0.3 | E36: 0.7
A37: HI | B37: 0.4 | C37: 0.6 | D37: 0.3 | E37: 0.7
... A76: WY | B76: 0.3 | C76: 0.7 | D76: 0.1 | E76: 0.9

Sheet Crosswalk_BEA_to_ISIC
A1: BEA Summary (post-disagg) -> 42-ISIC crosswalk, applied to state PA.
A3: Rows with allocation_weight != 1.0 represent BEA sectors that are split
A4: across multiple ISIC codes (e.g. BEA 22 utilities -> 351/352T353/36T39).
A5: State-specific overrides are loaded from crosswalks/state_overrides/<ST>/splits.csv.
A8: BEA_code | B8: BEA_name | C8: ISIC_code | D8: ISIC_name | E8: allocation_weight | F8: notes | G8: source
A9: 111CA | B9: Farms | C9: 01T03 | D9: Agriculture, forestry, fishing | E9: 1
A10: 113FF | B10: Forestry, fishing, related | C10: 01T03 | D10: Agriculture, forestry, fishing | E10: 1
A11: 211 | B11: Oil and gas extraction | C11: 06 | D11: Extraction of crude petroleum and natural gas | E11: 1
A12: 213 | B12: Support activities for mining | C12: 09 | D12: Mining support service activities | E12: 1
A13: 22 | B13: Utilities | C13: 351 | D13: Electricity | E13: 0.72 | F13: BEA 2012 Detail: electric ~72% of 22 output
A14: 22 | B14: Utilities | C14: 352T353 | D14: Gas, steam, AC | E14: 0.2 | F14: BEA Detail: gas distribution ~20%
A15: 22 | B15: Utilities | C15: 36T39 | D15: Water, sewerage, waste | E15: 0.08 | F15: BEA Detail: water/sewage ~8%
A16: 23 | B16: Construction | C16: 41T43 | D16: Construction | E16: 1
A17: 311FT | B17: Food, beverage, tobacco | C17: 10T12 | D17: Food, beverages, tobacco | E17: 1
A18: 313TT | B18: Textile mills and textile product mills | C18: 13T15 | D18: Textiles, apparel, leather | E18: 1
A19: 315AL | B19: Apparel and leather | C19: 13T15 | D19: Textiles, apparel, leather | E19: 1
A20: 321 | B20: Wood products | C20: 16 | D20: Wood and products of wood and cork | E20: 1
A21: 322 | B21: Paper products | C21: 17T18 | D21: Paper products and printing | E21: 1
A22: 323 | B22: Printing and related | C22: 17T18 | D22: Paper products and printing | E22: 1
A23: 324 | B23: Petroleum and coal products | C23: 19 | D23: Coke and refined petroleum products | E23: 0.961 | F23: BEA 2024 Detail: 324110 refineries + 324121/324122 asphalt = ~96.1% of 324 output ($601,241M / $625,936M)
A24: 324 | B24: Petroleum and coal products | C24: 241 | D24: Iron and steel (incl. coal coking) | E24: 0.039 | F24: EPS modeling convention: route NAICS 324190 (Other petroleum and coal products mfg, includes coal coking) to 241 to consolidate coke with iron and steel; matches eps-us national model
A25: 326 | B25: Plastics and rubber products | C25: 22 | D25: Rubber and plastics products | E25: 1
A26: 332 | B26: Fabricated metal products | C26: 25 | D26: Fabricated metal products | E26: 1
A27: 333 | B27: Machinery | C27: 28 | D27: Machinery and equipment n.e.c. | E27: 1
A28: 334 | B28: Computer and electronic products | C28: 26 | D28: Computer, electronic and optical products | E28: 1
A29: 335 | B29: Electrical equipment, appliances | C29: 27 | D29: Electrical equipment | E29: 1
A30: 3361MV | B30: Motor vehicles, bodies, trailers, parts | C30: 29 | D30: Motor vehicles, trailers, semi-trailers | E30: 1
A31: 3364OT | B31: Other transportation equipment | C31: 30 | D31: Other transport equipment | E31: 1
A32: 337 | B32: Furniture and related products | C32: 31T33 | D32: Furniture; other manufacturing; repair | E32: 1
A33: 339 | B33: Miscellaneous manufacturing | C33: 31T33 | D33: Furniture; other manufacturing; repair | E33: 1
A34: 42 | B34: Wholesale trade | C34: 45T47 | D34: Wholesale and retail trade | E34: 1
A35: 441 | B35: Motor vehicle and parts dealers | C35: 45T47 | D35: Wholesale and retail trade | E35: 1
A36: 445 | B36: Food and beverage stores | C36: 45T47 | D36: Wholesale and retail trade | E36: 1
... A43: 485 | B43: Transit and ground passenger | C43: 49T53 | D43: Transportation and storage | E43: 1
A44: 486 | B44: Pipeline transportation | C44: 352T353 | D44: Gas, steam, AC (incl. pipelines per EPS energy-side convention) | E44: 1 | F44: Reclassified from 49T53 (staff decision 2026-07-16): EPS 352T353 = 'energy pipelines and gas processing'; industrial-energy side sources pipeline fuel (AEO T36 / NAICS 486) here, so IO dollars follow. NOTE: diverges from eps-us national io-model (tags 486 -> 49T53); national files to be corrected separately.
A45: 487OS | B45: Other transportation and support | C45: 49T53 | D45: Transportation and storage | E45: 1
A46: 493 | B46: Warehousing and storage | C46: 49T53 | D46: Transportation and storage | E46: 1
A47: 511 | B47: Publishing industries (incl software) | C47: 58T60 | D47: Publishing, audiovisual, broadcasting | E47: 1
A48: 512 | B48: Motion picture and sound recording | C48: 58T60 | D48: Publishing, audiovisual, broadcasting | E48: 1
A49: 513 | B49: Broadcasting and telecom | C49: 58T60 | D49: Publishing, audiovisual, broadcasting | E49: 0.25 | F49: Placeholder ~25/75 broadcast/telecom per \u00a74.6
A50: 513 | B50: Broadcasting and telecom | C50: 61 | D50: Telecommunications | E50: 0.75
A51: 514 | B51: Data processing, hosting, other info | C51: 62T63 | D51: IT and other information services | E51: 1
A52: 521CI | B52: Federal Reserve banks, credit intermediation | C52: 64T66 | D52: Finance and insurance | E52: 1
A53: 523 | B53: Securities, commodity contracts, investments | C53: 64T66 | D53: Finance and insurance | E53: 1
A54: 524 | B54: Insurance carriers and related | C54: 64T66 | D54: Finance and insurance | E54: 1
A55: 525 | B55: Funds, trusts, other financial vehicles | C55: 64T66 | D55: Finance and insurance | E55: 1
A56: HS | B56: Housing (owner-occupied) | C56: 68 | D56: Real estate activities | E56: 1
A57: ORE | B57: Other real estate | C57: 68 | D57: Real estate activities | E57: 1
A58: 532RL | B58: Rental and leasing (excl real estate) | C58: 69T82 | D58: Prof/admin/support services | E58: 1 | F58: ISIC 77 not in 42-ISIC; \u00a74.7
A59: 5411 | B59: Legal services | C59: 69T82 | D59: Prof/admin/support services | E59: 1
A60: 5412OP | B60: Misc professional, scientific, technical services | C60: 69T82 | D60: Prof/admin/support services | E60: 1
A61: 5415 | B61: Computer systems design | C61: 62T63 | D61: IT and other information services | E61: 1 | F61: Resolves \u00a74.7 at stateior's Summary resolution
A62: 55 | B62: Management of companies and enterprises | C62: 69T82 | D62: Prof/admin/support services | E62: 1
A63: 561 | B63: Administrative and support services | C63: 69T82 | D63: Prof/admin/support services | E63: 1
A64: 562 | B64: Waste management and remediation | C64: 36T39 | D64: Water supply; sewerage; waste mgmt | E64: 1
A65: 61 | B65: Educational services | C65: 85 | D65: Education | E65: 1
A66: 621 | B66: Ambulatory health care | C66: 86T88 | D66: Human health and social work | E66: 1
A67: 622 | B67: Hospitals | C67: 86T88 | D67: Human health and social work | E67: 1
A68: 623 | B68: Nursing and residential care | C68: 86T88 | D68: Human health and social work | E68: 1
A69: 624 | B69: Social assistance | C69: 86T88 | D69: Human health and social work | E69: 1
A70: 711AS | B70: Performing arts, spectator sports, museums | C70: 90T96 | D70: Arts, entertainment and other services | E70: 1
A71: 713 | B71: Amusements, gambling, recreation | C71: 90T96 | D71: Arts, entertainment and other services | E71: 1
A72: 721 | B72: Accommodation | C72: 55T56 | D72: Accommodation and food services | E72: 1
A73: 722 | B73: Food services and drinking places | C73: 55T56 | D73: Accommodation and food services | E73: 1
... A79: GSLE | B79: State and local government enterprises | C79: 84 | D79: Public administration and defense | E79: 1
A80: 212 | B80: Mining, except oil and gas | C80: 05 | D80: Mining of coal and lignite | E80: 0.60118286 | G80: coal/(coal+nonfuel) mine-value share, 2012 USD: EIA coal 2019 $2672M + USGS T3 nonfuel 2021 $1773M [nonfuel partial total] -> coal share 0.601 (applied to stateior 212 $4914M)
A81: 212 | B81: Mining, except oil and gas | C81: 07T08 | D81: Other mining and quarrying | E81: 0.39881714 | G81: coal/(coal+nonfuel) mine-value share, 2012 USD: EIA coal 2019 $2672M + USGS T3 nonfuel 2021 $1773M [nonfuel partial total] -> coal share 0.601 (applied to stateior 212 $4914M)
A82: 327 | B82: Nonmetallic minerals | C82: 231 | D82: Glass | E82: 0.25 | G82: HEURISTIC (GHGRP Subpart H cement state list + glass industry profile; Census ASM suppressed or missing)
A83: 327 | B83: Nonmetallic minerals | C83: 239 | D83: Cement, lime, other nonmetallic | E83: 0.75 | G83: HEURISTIC (GHGRP Subpart H cement state list + glass industry profile; Census ASM suppressed or missing)
A84: 331 | B84: Primary metals | C84: 241 | D84: Iron and steel (incl. coal coking) | E84: 0.75 | G84: HEURISTIC (no ASM or GHGRP data pulled yet)
A85: 331 | B85: Primary metals | C85: 242 | D85: Aluminum, nonferrous, foundries | E85: 0.25 | G85: HEURISTIC (no ASM or GHGRP data pulled yet)
A86: 325 | B86: Chemicals | C86: 20 | D86: Chemicals and chemical products | E86: 0.45 | G86: HEURISTIC (Census ASM suppressed or unpulled)
A87: 325 | B87: Chemicals | C87: 21 | D87: Pharmaceuticals | E87: 0.55 | G87: HEURISTIC (Census ASM suppressed or unpulled)

Sheet State_disagg_splits
A1: State-specific disaggregation ratios applied for PA.
A3: Five BEA Summary sectors are split into finer ISIC children. Ratios
A4: come from the layered proxy strategy in the migration plan (sec 4.0):
A5: 1. Pulled-from-source data (EIA-7A, Census ASM, GHGRP) where available
A6: 2. GHGRP emissions proxy where Census is suppressed
A7: 3. Hand-curated heuristic table (from industry knowledge)
A8: 4. National fallback ratio (last resort)
A11: BEA_code | B11: ISIC_code | C11: allocation_weight | D11: source
A12: 212 | B12: 05 | C12: 0.60118286 | D12: coal/(coal+nonfuel) mine-value share, 2012 USD: EIA coal 2019 $2672M + USGS T3 nonfuel 2021 $1773M [nonfuel partial total] -> coal share 0.601 (applied to stateior 212 $4914M)
A13: 212 | B13: 07T08 | C13: 0.39881714 | D13: coal/(coal+nonfuel) mine-value share, 2012 USD: EIA coal 2019 $2672M + USGS T3 nonfuel 2021 $1773M [nonfuel partial total] -> coal share 0.601 (applied to stateior 212 $4914M)
A14: 327 | B14: 231 | C14: 0.25 | D14: HEURISTIC (GHGRP Subpart H cement state list + glass industry profile; Census ASM suppressed or missing)
A15: 327 | B15: 239 | C15: 0.75 | D15: HEURISTIC (GHGRP Subpart H cement state list + glass industry profile; Census ASM suppressed or missing)
A16: 331 | B16: 241 | C16: 0.75 | D16: HEURISTIC (no ASM or GHGRP data pulled yet)
A17: 331 | B17: 242 | C17: 0.25 | D17: HEURISTIC (no ASM or GHGRP data pulled yet)
A18: 325 | B18: 20 | C18: 0.45 | D18: HEURISTIC (Census ASM suppressed or unpulled)
A19: 325 | B19: 21 | C19: 0.55 | D19: HEURISTIC (Census ASM suppressed or unpulled)

Sheet NAICS_to_ISIC_Key
A1: Concise NAICS Summary -> ISIC Rev 4 mapping used by this pipeline.
A2: See US Census Bureau NAICS 2017 to ISIC Rev 4 concordance for the full
A3: detail-level mapping:
A4: https://www.census.gov/naics/concordances/2017_NAICS_to_ISIC_4.xlsx
A7: ISIC Rev 4 code | B7: Title (42-ISIC scheme) | C7: BEA Summary sources (examples)
A8: 01T03 | B8: Agriculture, forestry and fishing | C8: 111CA Farms; 113FF Forestry/fishing/related
A9: 05 | B9: Mining of coal and lignite | C9: 212/coal (NAICS 2121)
A10: 06 | B10: Extraction of crude petroleum and natural gas | C10: 211 Oil and gas extraction
A11: 07T08 | B11: Mining of metal ores; other mining and quarrying | C11: 212/other (NAICS 2122+2123)
A12: 09 | B12: Mining support service activities | C12: 213 Support activities for mining
A13: 10T12 | B13: Food products, beverages and tobacco | C13: 311FT Food/beverage/tobacco
A14: 13T15 | B14: Textiles, wearing apparel, leather and related products | C14: 313TT Textile mills; 315AL Apparel/leather
A15: 16 | B15: Wood and products of wood and cork, except furniture | C15: 321 Wood products
A16: 17T18 | B16: Paper products and printing | C16: 322 Paper; 323 Printing
A17: 19 | B17: Coke and refined petroleum products | C17: 324 Petroleum and coal products
A18: 20 | B18: Chemicals and chemical products (excl. pharmaceuticals) | C18: 325/chem (NAICS 3251-3259 excl. 3254)
... A49: 97T98 | B49: Households as employers; undifferentiated production (zero in EPS) | C49: Designed zero row: households as employers (NAICS 814)

Sheet 6_Calc_Gov_ISIC
A1: STEP 1 - read BEA code / ISIC code / weight live from the Crosswalk tab, pull each BEA value from the source tab, then weight it
A2: BEA_code | B2: ISIC_code | C2: allocation_weight | D2: BEA_value_nominal | E2: weighted_nominal
A3: ='Crosswalk_BEA_to_ISIC'!A9 | B3: ='Crosswalk_BEA_to_ISIC'!C9 | C3: ='Crosswalk_BEA_to_ISIC'!E9 | D3: =IFERROR(INDEX('1_Gov_purchases_by_BEA'!$B$2:$B$74, MATCH($A3, '1_Gov_purchases_by_BEA'!$A$2:$A$74, 0)), 0) | E3: =C3*D3
A4: ='Crosswalk_BEA_to_ISIC'!A10 | B4: ='Crosswalk_BEA_to_ISIC'!C10 | C4: ='Crosswalk_BEA_to_ISIC'!E10 | D4: =IFERROR(INDEX('1_Gov_purchases_by_BEA'!$B$2:$B$74, MATCH($A4, '1_Gov_purchases_by_BEA'!$A$2:$A$74, 0)), 0) | E4: =C4*D4
A5: ='Crosswalk_BEA_to_ISIC'!A11 | B5: ='Crosswalk_BEA_to_ISIC'!C11 | C5: ='Crosswalk_BEA_to_ISIC'!E11 | D5: =IFERROR(INDEX('1_Gov_purchases_by_BEA'!$B$2:$B$74, MATCH($A5, '1_Gov_purchases_by_BEA'!$A$2:$A$74, 0)), 0) | E5: =C5*D5
A6: ='Crosswalk_BEA_to_ISIC'!A12 | B6: ='Crosswalk_BEA_to_ISIC'!C12 | C6: ='Crosswalk_BEA_to_ISIC'!E12 | D6: =IFERROR(INDEX('1_Gov_purchases_by_BEA'!$B$2:$B$74, MATCH($A6, '1_Gov_purchases_by_BEA'!$A$2:$A$74, 0)), 0) | E6: =C6*D6
A7: ='Crosswalk_BEA_to_ISIC'!A13 | B7: ='Crosswalk_BEA_to_ISIC'!C13 | C7: ='Crosswalk_BEA_to_ISIC'!E13 | D7: =IFERROR(INDEX('1_Gov_purchases_by_BEA'!$B$2:$B$74, MATCH($A7, '1_Gov_purchases_by_BEA'!$A$2:$A$74, 0)), 0) | E7: =C7*D7
A8: ='Crosswalk_BEA_to_ISIC'!A14 | B8: ='Crosswalk_BEA_to_ISIC'!C14 | C8: ='Crosswalk_BEA_to_ISIC'!E14 | D8: =IFERROR(INDEX('1_Gov_purchases_by_BEA'!$B$2:$B$74, MATCH($A8, '1_Gov_purchases_by_BEA'!$A$2:$A$74, 0)), 0) | E8: =C8*D8
A9: ='Crosswalk_BEA_to_ISIC'!A15 | B9: ='Crosswalk_BEA_to_ISIC'!C15 | C9: ='Crosswalk_BEA_to_ISIC'!E15 | D9: =IFERROR(INDEX('1_Gov_purchases_by_BEA'!$B$2:$B$74, MATCH($A9, '1_Gov_purchases_by_BEA'!$A$2:$A$74, 0)), 0) | E9: =C9*D9
A10: ='Crosswalk_BEA_to_ISIC'!A16 | B10: ='Crosswalk_BEA_to_ISIC'!C16 | C10: ='Crosswalk_BEA_to_ISIC'!E16 | D10: =IFERROR(INDEX('1_Gov_purchases_by_BEA'!$B$2:$B$74, MATCH($A10, '1_Gov_purchases_by_BEA'!$A$2:$A$74, 0)), 0) | E10: =C10*D10
A11: ='Crosswalk_BEA_to_ISIC'!A17 | B11: ='Crosswalk_BEA_to_ISIC'!C17 | C11: ='Crosswalk_BEA_to_ISIC'!E17 | D11: =IFERROR(INDEX('1_Gov_purchases_by_BEA'!$B$2:$B$74, MATCH($A11, '1_Gov_purchases_by_BEA'!$A$2:$A$74, 0)), 0) | E11: =C11*D11
A12: ='Crosswalk_BEA_to_ISIC'!A18 | B12: ='Crosswalk_BEA_to_ISIC'!C18 | C12: ='Crosswalk_BEA_to_ISIC'!E18 | D12: =IFERROR(INDEX('1_Gov_purchases_by_BEA'!$B$2:$B$74, MATCH($A12, '1_Gov_purchases_by_BEA'!$A$2:$A$74, 0)), 0) | E12: =C12*D12
A13: ='Crosswalk_BEA_to_ISIC'!A19 | B13: ='Crosswalk_BEA_to_ISIC'!C19 | C13: ='Crosswalk_BEA_to_ISIC'!E19 | D13: =IFERROR(INDEX('1_Gov_purchases_by_BEA'!$B$2:$B$74, MATCH($A13, '1_Gov_purchases_by_BEA'!$A$2:$A$74, 0)), 0) | E13: =C13*D13
A14: ='Crosswalk_BEA_to_ISIC'!A20 | B14: ='Crosswalk_BEA_to_ISIC'!C20 | C14: ='Crosswalk_BEA_to_ISIC'!E20 | D14: =IFERROR(INDEX('1_Gov_purchases_by_BEA'!$B$2:$B$74, MATCH($A14, '1_Gov_purchases_by_BEA'!$A$2:$A$74, 0)), 0) | E14: =C14*D14
... A81: ='Crosswalk_BEA_to_ISIC'!A87 | B81: ='Crosswalk_BEA_to_ISIC'!C87 | C81: ='Crosswalk_BEA_to_ISIC'!E87 | D81: =IFERROR(INDEX('1_Gov_purchases_by_BEA'!$B$2:$B$74, MATCH($A81, '1_Gov_purchases_by_BEA'!$A$2:$A$74, 0)), 0) | E81: =C81*D81
A83: STEP 2 - aggregate weighted values to 42 ISIC (no deflation; passthrough column C = B)
A84: ISIC_code | B84: aggregated_nominal | C84: value (no deflation)
A85: 01T03 | B85: =SUMIFS('6_Calc_Gov_ISIC'!$E$3:$E$81, '6_Calc_Gov_ISIC'!$B$3:$B$81, $A85) | C85: =B85
A86: 05 | B86: =SUMIFS('6_Calc_Gov_ISIC'!$E$3:$E$81, '6_Calc_Gov_ISIC'!$B$3:$B$81, $A86) | C86: =B86
A87: 06 | B87: =SUMIFS('6_Calc_Gov_ISIC'!$E$3:$E$81, '6_Calc_Gov_ISIC'!$B$3:$B$81, $A87) | C87: =B87
A88: 07T08 | B88: =SUMIFS('6_Calc_Gov_ISIC'!$E$3:$E$81, '6_Calc_Gov_ISIC'!$B$3:$B$81, $A88) | C88: =B88
A89: 10T12 | B89: =SUMIFS('6_Calc_Gov_ISIC'!$E$3:$E$81, '6_Calc_Gov_ISIC'!$B$3:$B$81, $A89) | C89: =B89
A90: 13T15 | B90: =SUMIFS('6_Calc_Gov_ISIC'!$E$3:$E$81, '6_Calc_Gov_ISIC'!$B$3:$B$81, $A90) | C90: =B90
A91: 16 | B91: =SUMIFS('6_Calc_Gov_ISIC'!$E$3:$E$81, '6_Calc_Gov_ISIC'!$B$3:$B$81, $A91) | C91: =B91
A92: 17T18 | B92: =SUMIFS('6_Calc_Gov_ISIC'!$E$3:$E$81, '6_Calc_Gov_ISIC'!$B$3:$B$81, $A92) | C92: =B92
A93: 19 | B93: =SUMIFS('6_Calc_Gov_ISIC'!$E$3:$E$81, '6_Calc_Gov_ISIC'!$B$3:$B$81, $A93) | C93: =B93
A94: 20 | B94: =SUMIFS('6_Calc_Gov_ISIC'!$E$3:$E$81, '6_Calc_Gov_ISIC'!$B$3:$B$81, $A94) | C94: =B94
A95: 22 | B95: =SUMIFS('6_Calc_Gov_ISIC'!$E$3:$E$81, '6_Calc_Gov_ISIC'!$B$3:$B$81, $A95) | C95: =B95
A96: 231 | B96: =SUMIFS('6_Calc_Gov_ISIC'!$E$3:$E$81, '6_Calc_Gov_ISIC'!$B$3:$B$81, $A96) | C96: =B96
... A109: 41T43 | B109: =SUMIFS('6_Calc_Gov_ISIC'!$E$3:$E$81, '6_Calc_Gov_ISIC'!$B$3:$B$81, $A109) | C109: =B109

Sheet 7_Calc_HH_ISIC
A1: STEP 1 - read BEA code / ISIC code / weight live from the Crosswalk tab, pull each BEA value from the source tab, then weight it
A2: BEA_code | B2: ISIC_code | C2: allocation_weight | D2: BEA_value_nominal | E2: weighted_nominal
A3: ='Crosswalk_BEA_to_ISIC'!A9 | B3: ='Crosswalk_BEA_to_ISIC'!C9 | C3: ='Crosswalk_BEA_to_ISIC'!E9 | D3: =IFERROR(INDEX('2_HH_purchases_by_BEA'!$B$2:$B$74, MATCH($A3, '2_HH_purchases_by_BEA'!$A$2:$A$74, 0)), 0) | E3: =C3*D3
A4: ='Crosswalk_BEA_to_ISIC'!A10 | B4: ='Crosswalk_BEA_to_ISIC'!C10 | C4: ='Crosswalk_BEA_to_ISIC'!E10 | D4: =IFERROR(INDEX('2_HH_purchases_by_BEA'!$B$2:$B$74, MATCH($A4, '2_HH_purchases_by_BEA'!$A$2:$A$74, 0)), 0) | E4: =C4*D4
A5: ='Crosswalk_BEA_to_ISIC'!A11 | B5: ='Crosswalk_BEA_to_ISIC'!C11 | C5: ='Crosswalk_BEA_to_ISIC'!E11 | D5: =IFERROR(INDEX('2_HH_purchases_by_BEA'!$B$2:$B$74, MATCH($A5, '2_HH_purchases_by_BEA'!$A$2:$A$74, 0)), 0) | E5: =C5*D5
A6: ='Crosswalk_BEA_to_ISIC'!A12 | B6: ='Crosswalk_BEA_to_ISIC'!C12 | C6: ='Crosswalk_BEA_to_ISIC'!E12 | D6: =IFERROR(INDEX('2_HH_purchases_by_BEA'!$B$2:$B$74, MATCH($A6, '2_HH_purchases_by_BEA'!$A$2:$A$74, 0)), 0) | E6: =C6*D6
A7: ='Crosswalk_BEA_to_ISIC'!A13 | B7: ='Crosswalk_BEA_to_ISIC'!C13 | C7: ='Crosswalk_BEA_to_ISIC'!E13 | D7: =IFERROR(INDEX('2_HH_purchases_by_BEA'!$B$2:$B$74, MATCH($A7, '2_HH_purchases_by_BEA'!$A$2:$A$74, 0)), 0) | E7: =C7*D7
A8: ='Crosswalk_BEA_to_ISIC'!A14 | B8: ='Crosswalk_BEA_to_ISIC'!C14 | C8: ='Crosswalk_BEA_to_ISIC'!E14 | D8: =IFERROR(INDEX('2_HH_purchases_by_BEA'!$B$2:$B$74, MATCH($A8, '2_HH_purchases_by_BEA'!$A$2:$A$74, 0)), 0) | E8: =C8*D8
A9: ='Crosswalk_BEA_to_ISIC'!A15 | B9: ='Crosswalk_BEA_to_ISIC'!C15 | C9: ='Crosswalk_BEA_to_ISIC'!E15 | D9: =IFERROR(INDEX('2_HH_purchases_by_BEA'!$B$2:$B$74, MATCH($A9, '2_HH_purchases_by_BEA'!$A$2:$A$74, 0)), 0) | E9: =C9*D9
A10: ='Crosswalk_BEA_to_ISIC'!A16 | B10: ='Crosswalk_BEA_to_ISIC'!C16 | C10: ='Crosswalk_BEA_to_ISIC'!E16 | D10: =IFERROR(INDEX('2_HH_purchases_by_BEA'!$B$2:$B$74, MATCH($A10, '2_HH_purchases_by_BEA'!$A$2:$A$74, 0)), 0) | E10: =C10*D10
A11: ='Crosswalk_BEA_to_ISIC'!A17 | B11: ='Crosswalk_BEA_to_ISIC'!C17 | C11: ='Crosswalk_BEA_to_ISIC'!E17 | D11: =IFERROR(INDEX('2_HH_purchases_by_BEA'!$B$2:$B$74, MATCH($A11, '2_HH_purchases_by_BEA'!$A$2:$A$74, 0)), 0) | E11: =C11*D11
A12: ='Crosswalk_BEA_to_ISIC'!A18 | B12: ='Crosswalk_BEA_to_ISIC'!C18 | C12: ='Crosswalk_BEA_to_ISIC'!E18 | D12: =IFERROR(INDEX('2_HH_purchases_by_BEA'!$B$2:$B$74, MATCH($A12, '2_HH_purchases_by_BEA'!$A$2:$A$74, 0)), 0) | E12: =C12*D12
A13: ='Crosswalk_BEA_to_ISIC'!A19 | B13: ='Crosswalk_BEA_to_ISIC'!C19 | C13: ='Crosswalk_BEA_to_ISIC'!E19 | D13: =IFERROR(INDEX('2_HH_purchases_by_BEA'!$B$2:$B$74, MATCH($A13, '2_HH_purchases_by_BEA'!$A$2:$A$74, 0)), 0) | E13: =C13*D13
A14: ='Crosswalk_BEA_to_ISIC'!A20 | B14: ='Crosswalk_BEA_to_ISIC'!C20 | C14: ='Crosswalk_BEA_to_ISIC'!E20 | D14: =IFERROR(INDEX('2_HH_purchases_by_BEA'!$B$2:$B$74, MATCH($A14, '2_HH_purchases_by_BEA'!$A$2:$A$74, 0)), 0) | E14: =C14*D14
... A81: ='Crosswalk_BEA_to_ISIC'!A87 | B81: ='Crosswalk_BEA_to_ISIC'!C87 | C81: ='Crosswalk_BEA_to_ISIC'!E87 | D81: =IFERROR(INDEX('2_HH_purchases_by_BEA'!$B$2:$B$74, MATCH($A81, '2_HH_purchases_by_BEA'!$A$2:$A$74, 0)), 0) | E81: =C81*D81
A83: STEP 2 - aggregate weighted values to 42 ISIC (no deflation; passthrough column C = B)
A84: ISIC_code | B84: aggregated_nominal | C84: value (no deflation)
A85: 01T03 | B85: =SUMIFS('7_Calc_HH_ISIC'!$E$3:$E$81, '7_Calc_HH_ISIC'!$B$3:$B$81, $A85) | C85: =B85
A86: 05 | B86: =SUMIFS('7_Calc_HH_ISIC'!$E$3:$E$81, '7_Calc_HH_ISIC'!$B$3:$B$81, $A86) | C86: =B86
A87: 06 | B87: =SUMIFS('7_Calc_HH_ISIC'!$E$3:$E$81, '7_Calc_HH_ISIC'!$B$3:$B$81, $A87) | C87: =B87
A88: 07T08 | B88: =SUMIFS('7_Calc_HH_ISIC'!$E$3:$E$81, '7_Calc_HH_ISIC'!$B$3:$B$81, $A88) | C88: =B88
A89: 10T12 | B89: =SUMIFS('7_Calc_HH_ISIC'!$E$3:$E$81, '7_Calc_HH_ISIC'!$B$3:$B$81, $A89) | C89: =B89
A90: 13T15 | B90: =SUMIFS('7_Calc_HH_ISIC'!$E$3:$E$81, '7_Calc_HH_ISIC'!$B$3:$B$81, $A90) | C90: =B90
A91: 16 | B91: =SUMIFS('7_Calc_HH_ISIC'!$E$3:$E$81, '7_Calc_HH_ISIC'!$B$3:$B$81, $A91) | C91: =B91
A92: 17T18 | B92: =SUMIFS('7_Calc_HH_ISIC'!$E$3:$E$81, '7_Calc_HH_ISIC'!$B$3:$B$81, $A92) | C92: =B92
A93: 19 | B93: =SUMIFS('7_Calc_HH_ISIC'!$E$3:$E$81, '7_Calc_HH_ISIC'!$B$3:$B$81, $A93) | C93: =B93
A94: 20 | B94: =SUMIFS('7_Calc_HH_ISIC'!$E$3:$E$81, '7_Calc_HH_ISIC'!$B$3:$B$81, $A94) | C94: =B94
A95: 22 | B95: =SUMIFS('7_Calc_HH_ISIC'!$E$3:$E$81, '7_Calc_HH_ISIC'!$B$3:$B$81, $A95) | C95: =B95
A96: 231 | B96: =SUMIFS('7_Calc_HH_ISIC'!$E$3:$E$81, '7_Calc_HH_ISIC'!$B$3:$B$81, $A96) | C96: =B96
... A109: 41T43 | B109: =SUMIFS('7_Calc_HH_ISIC'!$E$3:$E$81, '7_Calc_HH_ISIC'!$B$3:$B$81, $A109) | C109: =B109

Sheet 8_Calc_Intl_ISIC
A1: STEP 1 - read BEA code / ISIC code / weight live from the Crosswalk tab, pull each BEA value from the source tab, then weight it
A2: BEA_code | B2: ISIC_code | C2: allocation_weight | D2: BEA_value_nominal | E2: weighted_nominal
A3: ='Crosswalk_BEA_to_ISIC'!A9 | B3: ='Crosswalk_BEA_to_ISIC'!C9 | C3: ='Crosswalk_BEA_to_ISIC'!E9 | D3: =IFERROR(INDEX('3_Intl_purchases_by_BEA'!$B$2:$B$74, MATCH($A3, '3_Intl_purchases_by_BEA'!$A$2:$A$74, 0)), 0) | E3: =C3*D3
A4: ='Crosswalk_BEA_to_ISIC'!A10 | B4: ='Crosswalk_BEA_to_ISIC'!C10 | C4: ='Crosswalk_BEA_to_ISIC'!E10 | D4: =IFERROR(INDEX('3_Intl_purchases_by_BEA'!$B$2:$B$74, MATCH($A4, '3_Intl_purchases_by_BEA'!$A$2:$A$74, 0)), 0) | E4: =C4*D4
A5: ='Crosswalk_BEA_to_ISIC'!A11 | B5: ='Crosswalk_BEA_to_ISIC'!C11 | C5: ='Crosswalk_BEA_to_ISIC'!E11 | D5: =IFERROR(INDEX('3_Intl_purchases_by_BEA'!$B$2:$B$74, MATCH($A5, '3_Intl_purchases_by_BEA'!$A$2:$A$74, 0)), 0) | E5: =C5*D5
A6: ='Crosswalk_BEA_to_ISIC'!A12 | B6: ='Crosswalk_BEA_to_ISIC'!C12 | C6: ='Crosswalk_BEA_to_ISIC'!E12 | D6: =IFERROR(INDEX('3_Intl_purchases_by_BEA'!$B$2:$B$74, MATCH($A6, '3_Intl_purchases_by_BEA'!$A$2:$A$74, 0)), 0) | E6: =C6*D6
A7: ='Crosswalk_BEA_to_ISIC'!A13 | B7: ='Crosswalk_BEA_to_ISIC'!C13 | C7: ='Crosswalk_BEA_to_ISIC'!E13 | D7: =IFERROR(INDEX('3_Intl_purchases_by_BEA'!$B$2:$B$74, MATCH($A7, '3_Intl_purchases_by_BEA'!$A$2:$A$74, 0)), 0) | E7: =C7*D7
A8: ='Crosswalk_BEA_to_ISIC'!A14 | B8: ='Crosswalk_BEA_to_ISIC'!C14 | C8: ='Crosswalk_BEA_to_ISIC'!E14 | D8: =IFERROR(INDEX('3_Intl_purchases_by_BEA'!$B$2:$B$74, MATCH($A8, '3_Intl_purchases_by_BEA'!$A$2:$A$74, 0)), 0) | E8: =C8*D8
A9: ='Crosswalk_BEA_to_ISIC'!A15 | B9: ='Crosswalk_BEA_to_ISIC'!C15 | C9: ='Crosswalk_BEA_to_ISIC'!E15 | D9: =IFERROR(INDEX('3_Intl_purchases_by_BEA'!$B$2:$B$74, MATCH($A9, '3_Intl_purchases_by_BEA'!$A$2:$A$74, 0)), 0) | E9: =C9*D9
A10: ='Crosswalk_BEA_to_ISIC'!A16 | B10: ='Crosswalk_BEA_to_ISIC'!C16 | C10: ='Crosswalk_BEA_to_ISIC'!E16 | D10: =IFERROR(INDEX('3_Intl_purchases_by_BEA'!$B$2:$B$74, MATCH($A10, '3_Intl_purchases_by_BEA'!$A$2:$A$74, 0)), 0) | E10: =C10*D10
A11: ='Crosswalk_BEA_to_ISIC'!A17 | B11: ='Crosswalk_BEA_to_ISIC'!C17 | C11: ='Crosswalk_BEA_to_ISIC'!E17 | D11: =IFERROR(INDEX('3_Intl_purchases_by_BEA'!$B$2:$B$74, MATCH($A11, '3_Intl_purchases_by_BEA'!$A$2:$A$74, 0)), 0) | E11: =C11*D11
A12: ='Crosswalk_BEA_to_ISIC'!A18 | B12: ='Crosswalk_BEA_to_ISIC'!C18 | C12: ='Crosswalk_BEA_to_ISIC'!E18 | D12: =IFERROR(INDEX('3_Intl_purchases_by_BEA'!$B$2:$B$74, MATCH($A12, '3_Intl_purchases_by_BEA'!$A$2:$A$74, 0)), 0) | E12: =C12*D12
A13: ='Crosswalk_BEA_to_ISIC'!A19 | B13: ='Crosswalk_BEA_to_ISIC'!C19 | C13: ='Crosswalk_BEA_to_ISIC'!E19 | D13: =IFERROR(INDEX('3_Intl_purchases_by_BEA'!$B$2:$B$74, MATCH($A13, '3_Intl_purchases_by_BEA'!$A$2:$A$74, 0)), 0) | E13: =C13*D13
A14: ='Crosswalk_BEA_to_ISIC'!A20 | B14: ='Crosswalk_BEA_to_ISIC'!C20 | C14: ='Crosswalk_BEA_to_ISIC'!E20 | D14: =IFERROR(INDEX('3_Intl_purchases_by_BEA'!$B$2:$B$74, MATCH($A14, '3_Intl_purchases_by_BEA'!$A$2:$A$74, 0)), 0) | E14: =C14*D14
... A81: ='Crosswalk_BEA_to_ISIC'!A87 | B81: ='Crosswalk_BEA_to_ISIC'!C87 | C81: ='Crosswalk_BEA_to_ISIC'!E87 | D81: =IFERROR(INDEX('3_Intl_purchases_by_BEA'!$B$2:$B$74, MATCH($A81, '3_Intl_purchases_by_BEA'!$A$2:$A$74, 0)), 0) | E81: =C81*D81
A83: STEP 2 - aggregate weighted values to 42 ISIC (no deflation; passthrough column C = B)
A84: ISIC_code | B84: aggregated_nominal | C84: value (no deflation)
A85: 01T03 | B85: =SUMIFS('8_Calc_Intl_ISIC'!$E$3:$E$81, '8_Calc_Intl_ISIC'!$B$3:$B$81, $A85) | C85: =B85
A86: 05 | B86: =SUMIFS('8_Calc_Intl_ISIC'!$E$3:$E$81, '8_Calc_Intl_ISIC'!$B$3:$B$81, $A86) | C86: =B86
A87: 06 | B87: =SUMIFS('8_Calc_Intl_ISIC'!$E$3:$E$81, '8_Calc_Intl_ISIC'!$B$3:$B$81, $A87) | C87: =B87
A88: 07T08 | B88: =SUMIFS('8_Calc_Intl_ISIC'!$E$3:$E$81, '8_Calc_Intl_ISIC'!$B$3:$B$81, $A88) | C88: =B88
A89: 10T12 | B89: =SUMIFS('8_Calc_Intl_ISIC'!$E$3:$E$81, '8_Calc_Intl_ISIC'!$B$3:$B$81, $A89) | C89: =B89
A90: 13T15 | B90: =SUMIFS('8_Calc_Intl_ISIC'!$E$3:$E$81, '8_Calc_Intl_ISIC'!$B$3:$B$81, $A90) | C90: =B90
A91: 16 | B91: =SUMIFS('8_Calc_Intl_ISIC'!$E$3:$E$81, '8_Calc_Intl_ISIC'!$B$3:$B$81, $A91) | C91: =B91
A92: 17T18 | B92: =SUMIFS('8_Calc_Intl_ISIC'!$E$3:$E$81, '8_Calc_Intl_ISIC'!$B$3:$B$81, $A92) | C92: =B92
A93: 19 | B93: =SUMIFS('8_Calc_Intl_ISIC'!$E$3:$E$81, '8_Calc_Intl_ISIC'!$B$3:$B$81, $A93) | C93: =B93
A94: 20 | B94: =SUMIFS('8_Calc_Intl_ISIC'!$E$3:$E$81, '8_Calc_Intl_ISIC'!$B$3:$B$81, $A94) | C94: =B94
A95: 22 | B95: =SUMIFS('8_Calc_Intl_ISIC'!$E$3:$E$81, '8_Calc_Intl_ISIC'!$B$3:$B$81, $A95) | C95: =B95
A96: 231 | B96: =SUMIFS('8_Calc_Intl_ISIC'!$E$3:$E$81, '8_Calc_Intl_ISIC'!$B$3:$B$81, $A96) | C96: =B96
... A109: 41T43 | B109: =SUMIFS('8_Calc_Intl_ISIC'!$E$3:$E$81, '8_Calc_Intl_ISIC'!$B$3:$B$81, $A109) | C109: =B109

Sheet 9_Calc_Total_ISIC
A1: STEP 1 - read BEA code / ISIC code / weight live from the Crosswalk tab, pull each BEA value from the source tab, then weight it
A2: BEA_code | B2: ISIC_code | C2: allocation_weight | D2: BEA_value_nominal | E2: weighted_nominal
A3: ='Crosswalk_BEA_to_ISIC'!A9 | B3: ='Crosswalk_BEA_to_ISIC'!C9 | C3: ='Crosswalk_BEA_to_ISIC'!E9 | D3: =IFERROR(INDEX('5_Total_purchases_by_BEA'!$B$2:$B$74, MATCH($A3, '5_Total_purchases_by_BEA'!$A$2:$A$74, 0)), 0) | E3: =C3*D3
A4: ='Crosswalk_BEA_to_ISIC'!A10 | B4: ='Crosswalk_BEA_to_ISIC'!C10 | C4: ='Crosswalk_BEA_to_ISIC'!E10 | D4: =IFERROR(INDEX('5_Total_purchases_by_BEA'!$B$2:$B$74, MATCH($A4, '5_Total_purchases_by_BEA'!$A$2:$A$74, 0)), 0) | E4: =C4*D4
A5: ='Crosswalk_BEA_to_ISIC'!A11 | B5: ='Crosswalk_BEA_to_ISIC'!C11 | C5: ='Crosswalk_BEA_to_ISIC'!E11 | D5: =IFERROR(INDEX('5_Total_purchases_by_BEA'!$B$2:$B$74, MATCH($A5, '5_Total_purchases_by_BEA'!$A$2:$A$74, 0)), 0) | E5: =C5*D5
A6: ='Crosswalk_BEA_to_ISIC'!A12 | B6: ='Crosswalk_BEA_to_ISIC'!C12 | C6: ='Crosswalk_BEA_to_ISIC'!E12 | D6: =IFERROR(INDEX('5_Total_purchases_by_BEA'!$B$2:$B$74, MATCH($A6, '5_Total_purchases_by_BEA'!$A$2:$A$74, 0)), 0) | E6: =C6*D6
A7: ='Crosswalk_BEA_to_ISIC'!A13 | B7: ='Crosswalk_BEA_to_ISIC'!C13 | C7: ='Crosswalk_BEA_to_ISIC'!E13 | D7: =IFERROR(INDEX('5_Total_purchases_by_BEA'!$B$2:$B$74, MATCH($A7, '5_Total_purchases_by_BEA'!$A$2:$A$74, 0)), 0) | E7: =C7*D7
A8: ='Crosswalk_BEA_to_ISIC'!A14 | B8: ='Crosswalk_BEA_to_ISIC'!C14 | C8: ='Crosswalk_BEA_to_ISIC'!E14 | D8: =IFERROR(INDEX('5_Total_purchases_by_BEA'!$B$2:$B$74, MATCH($A8, '5_Total_purchases_by_BEA'!$A$2:$A$74, 0)), 0) | E8: =C8*D8
A9: ='Crosswalk_BEA_to_ISIC'!A15 | B9: ='Crosswalk_BEA_to_ISIC'!C15 | C9: ='Crosswalk_BEA_to_ISIC'!E15 | D9: =IFERROR(INDEX('5_Total_purchases_by_BEA'!$B$2:$B$74, MATCH($A9, '5_Total_purchases_by_BEA'!$A$2:$A$74, 0)), 0) | E9: =C9*D9
A10: ='Crosswalk_BEA_to_ISIC'!A16 | B10: ='Crosswalk_BEA_to_ISIC'!C16 | C10: ='Crosswalk_BEA_to_ISIC'!E16 | D10: =IFERROR(INDEX('5_Total_purchases_by_BEA'!$B$2:$B$74, MATCH($A10, '5_Total_purchases_by_BEA'!$A$2:$A$74, 0)), 0) | E10: =C10*D10
A11: ='Crosswalk_BEA_to_ISIC'!A17 | B11: ='Crosswalk_BEA_to_ISIC'!C17 | C11: ='Crosswalk_BEA_to_ISIC'!E17 | D11: =IFERROR(INDEX('5_Total_purchases_by_BEA'!$B$2:$B$74, MATCH($A11, '5_Total_purchases_by_BEA'!$A$2:$A$74, 0)), 0) | E11: =C11*D11
A12: ='Crosswalk_BEA_to_ISIC'!A18 | B12: ='Crosswalk_BEA_to_ISIC'!C18 | C12: ='Crosswalk_BEA_to_ISIC'!E18 | D12: =IFERROR(INDEX('5_Total_purchases_by_BEA'!$B$2:$B$74, MATCH($A12, '5_Total_purchases_by_BEA'!$A$2:$A$74, 0)), 0) | E12: =C12*D12
A13: ='Crosswalk_BEA_to_ISIC'!A19 | B13: ='Crosswalk_BEA_to_ISIC'!C19 | C13: ='Crosswalk_BEA_to_ISIC'!E19 | D13: =IFERROR(INDEX('5_Total_purchases_by_BEA'!$B$2:$B$74, MATCH($A13, '5_Total_purchases_by_BEA'!$A$2:$A$74, 0)), 0) | E13: =C13*D13
A14: ='Crosswalk_BEA_to_ISIC'!A20 | B14: ='Crosswalk_BEA_to_ISIC'!C20 | C14: ='Crosswalk_BEA_to_ISIC'!E20 | D14: =IFERROR(INDEX('5_Total_purchases_by_BEA'!$B$2:$B$74, MATCH($A14, '5_Total_purchases_by_BEA'!$A$2:$A$74, 0)), 0) | E14: =C14*D14
... A81: ='Crosswalk_BEA_to_ISIC'!A87 | B81: ='Crosswalk_BEA_to_ISIC'!C87 | C81: ='Crosswalk_BEA_to_ISIC'!E87 | D81: =IFERROR(INDEX('5_Total_purchases_by_BEA'!$B$2:$B$74, MATCH($A81, '5_Total_purchases_by_BEA'!$A$2:$A$74, 0)), 0) | E81: =C81*D81
A83: STEP 2 - aggregate weighted values to 42 ISIC (no deflation; passthrough column C = B)
A84: ISIC_code | B84: aggregated_nominal | C84: value (no deflation)
A85: 01T03 | B85: =SUMIFS('9_Calc_Total_ISIC'!$E$3:$E$81, '9_Calc_Total_ISIC'!$B$3:$B$81, $A85) | C85: =B85
A86: 05 | B86: =SUMIFS('9_Calc_Total_ISIC'!$E$3:$E$81, '9_Calc_Total_ISIC'!$B$3:$B$81, $A86) | C86: =B86
A87: 06 | B87: =SUMIFS('9_Calc_Total_ISIC'!$E$3:$E$81, '9_Calc_Total_ISIC'!$B$3:$B$81, $A87) | C87: =B87
A88: 07T08 | B88: =SUMIFS('9_Calc_Total_ISIC'!$E$3:$E$81, '9_Calc_Total_ISIC'!$B$3:$B$81, $A88) | C88: =B88
A89: 10T12 | B89: =SUMIFS('9_Calc_Total_ISIC'!$E$3:$E$81, '9_Calc_Total_ISIC'!$B$3:$B$81, $A89) | C89: =B89
A90: 13T15 | B90: =SUMIFS('9_Calc_Total_ISIC'!$E$3:$E$81, '9_Calc_Total_ISIC'!$B$3:$B$81, $A90) | C90: =B90
A91: 16 | B91: =SUMIFS('9_Calc_Total_ISIC'!$E$3:$E$81, '9_Calc_Total_ISIC'!$B$3:$B$81, $A91) | C91: =B91
A92: 17T18 | B92: =SUMIFS('9_Calc_Total_ISIC'!$E$3:$E$81, '9_Calc_Total_ISIC'!$B$3:$B$81, $A92) | C92: =B92
A93: 19 | B93: =SUMIFS('9_Calc_Total_ISIC'!$E$3:$E$81, '9_Calc_Total_ISIC'!$B$3:$B$81, $A93) | C93: =B93
A94: 20 | B94: =SUMIFS('9_Calc_Total_ISIC'!$E$3:$E$81, '9_Calc_Total_ISIC'!$B$3:$B$81, $A94) | C94: =B94
A95: 22 | B95: =SUMIFS('9_Calc_Total_ISIC'!$E$3:$E$81, '9_Calc_Total_ISIC'!$B$3:$B$81, $A95) | C95: =B95
A96: 231 | B96: =SUMIFS('9_Calc_Total_ISIC'!$E$3:$E$81, '9_Calc_Total_ISIC'!$B$3:$B$81, $A96) | C96: =B96
... A109: 41T43 | B109: =SUMIFS('9_Calc_Total_ISIC'!$E$3:$E$81, '9_Calc_Total_ISIC'!$B$3:$B$81, $A109) | C109: =B109

Sheet 10_Calc_Entity_fractions
A1: Entity fractions per Industry Category: component / MAX(total, Keys fogp floor); domestic industries = MAX(0, 1 - gov - hh - intl) so rows sum to 1
A2: ISIC_code | B2: gov_ISIC | C2: hh_ISIC | D2: intl_ISIC | E2: total_ISIC | F2: denom (floored) | G2: gov_frac | H2: hh_frac (labor and consumers) | I2: intl_frac (foreign entities) | J2: domind_frac (residual)
A3: 01T03 | B3: =IFERROR(INDEX('6_Calc_Gov_ISIC'!$C$85:$C$109, MATCH($A3, '6_Calc_Gov_ISIC'!$A$85:$A$109, 0)), 0) | C3: =IFERROR(INDEX('7_Calc_HH_ISIC'!$C$85:$C$109, MATCH($A3, '7_Calc_HH_ISIC'!$A$85:$A$109, 0)), 0) | D3: =IFERROR(INDEX('8_Calc_Intl_ISIC'!$C$85:$C$109, MATCH($A3, '8_Calc_Intl_ISIC'!$A$85:$A$109, 0)), 0) | E3: =IFERROR(INDEX('9_Calc_Total_ISIC'!$C$85:$C$109, MATCH($A3, '9_Calc_Total_ISIC'!$A$85:$A$109, 0)), 0) | F3: =MAX(E3, Keys!$C$5) | G3: =B3/F3 | H3: =C3/F3 | I3: =D3/F3 | J3: =MAX(0, 1-G3-H3-I3)
A4: 05 | B4: =IFERROR(INDEX('6_Calc_Gov_ISIC'!$C$85:$C$109, MATCH($A4, '6_Calc_Gov_ISIC'!$A$85:$A$109, 0)), 0) | C4: =IFERROR(INDEX('7_Calc_HH_ISIC'!$C$85:$C$109, MATCH($A4, '7_Calc_HH_ISIC'!$A$85:$A$109, 0)), 0) | D4: =IFERROR(INDEX('8_Calc_Intl_ISIC'!$C$85:$C$109, MATCH($A4, '8_Calc_Intl_ISIC'!$A$85:$A$109, 0)), 0) | E4: =IFERROR(INDEX('9_Calc_Total_ISIC'!$C$85:$C$109, MATCH($A4, '9_Calc_Total_ISIC'!$A$85:$A$109, 0)), 0) | F4: =MAX(E4, Keys!$C$5) | G4: =B4/F4 | H4: =C4/F4 | I4: =D4/F4 | J4: =MAX(0, 1-G4-H4-I4)
A5: 06 | B5: =IFERROR(INDEX('6_Calc_Gov_ISIC'!$C$85:$C$109, MATCH($A5, '6_Calc_Gov_ISIC'!$A$85:$A$109, 0)), 0) | C5: =IFERROR(INDEX('7_Calc_HH_ISIC'!$C$85:$C$109, MATCH($A5, '7_Calc_HH_ISIC'!$A$85:$A$109, 0)), 0) | D5: =IFERROR(INDEX('8_Calc_Intl_ISIC'!$C$85:$C$109, MATCH($A5, '8_Calc_Intl_ISIC'!$A$85:$A$109, 0)), 0) | E5: =IFERROR(INDEX('9_Calc_Total_ISIC'!$C$85:$C$109, MATCH($A5, '9_Calc_Total_ISIC'!$A$85:$A$109, 0)), 0) | F5: =MAX(E5, Keys!$C$5) | G5: =B5/F5 | H5: =C5/F5 | I5: =D5/F5 | J5: =MAX(0, 1-G5-H5-I5)
A6: 07T08 | B6: =IFERROR(INDEX('6_Calc_Gov_ISIC'!$C$85:$C$109, MATCH($A6, '6_Calc_Gov_ISIC'!$A$85:$A$109, 0)), 0) | C6: =IFERROR(INDEX('7_Calc_HH_ISIC'!$C$85:$C$109, MATCH($A6, '7_Calc_HH_ISIC'!$A$85:$A$109, 0)), 0) | D6: =IFERROR(INDEX('8_Calc_Intl_ISIC'!$C$85:$C$109, MATCH($A6, '8_Calc_Intl_ISIC'!$A$85:$A$109, 0)), 0) | E6: =IFERROR(INDEX('9_Calc_Total_ISIC'!$C$85:$C$109, MATCH($A6, '9_Calc_Total_ISIC'!$A$85:$A$109, 0)), 0) | F6: =MAX(E6, Keys!$C$5) | G6: =B6/F6 | H6: =C6/F6 | I6: =D6/F6 | J6: =MAX(0, 1-G6-H6-I6)
A7: 10T12 | B7: =IFERROR(INDEX('6_Calc_Gov_ISIC'!$C$85:$C$109, MATCH($A7, '6_Calc_Gov_ISIC'!$A$85:$A$109, 0)), 0) | C7: =IFERROR(INDEX('7_Calc_HH_ISIC'!$C$85:$C$109, MATCH($A7, '7_Calc_HH_ISIC'!$A$85:$A$109, 0)), 0) | D7: =IFERROR(INDEX('8_Calc_Intl_ISIC'!$C$85:$C$109, MATCH($A7, '8_Calc_Intl_ISIC'!$A$85:$A$109, 0)), 0) | E7: =IFERROR(INDEX('9_Calc_Total_ISIC'!$C$85:$C$109, MATCH($A7, '9_Calc_Total_ISIC'!$A$85:$A$109, 0)), 0) | F7: =MAX(E7, Keys!$C$5) | G7: =B7/F7 | H7: =C7/F7 | I7: =D7/F7 | J7: =MAX(0, 1-G7-H7-I7)
A8: 13T15 | B8: =IFERROR(INDEX('6_Calc_Gov_ISIC'!$C$85:$C$109, MATCH($A8, '6_Calc_Gov_ISIC'!$A$85:$A$109, 0)), 0) | C8: =IFERROR(INDEX('7_Calc_HH_ISIC'!$C$85:$C$109, MATCH($A8, '7_Calc_HH_ISIC'!$A$85:$A$109, 0)), 0) | D8: =IFERROR(INDEX('8_Calc_Intl_ISIC'!$C$85:$C$109, MATCH($A8, '8_Calc_Intl_ISIC'!$A$85:$A$109, 0)), 0) | E8: =IFERROR(INDEX('9_Calc_Total_ISIC'!$C$85:$C$109, MATCH($A8, '9_Calc_Total_ISIC'!$A$85:$A$109, 0)), 0) | F8: =MAX(E8, Keys!$C$5) | G8: =B8/F8 | H8: =C8/F8 | I8: =D8/F8 | J8: =MAX(0, 1-G8-H8-I8)
A9: 16 | B9: =IFERROR(INDEX('6_Calc_Gov_ISIC'!$C$85:$C$109, MATCH($A9, '6_Calc_Gov_ISIC'!$A$85:$A$109, 0)), 0) | C9: =IFERROR(INDEX('7_Calc_HH_ISIC'!$C$85:$C$109, MATCH($A9, '7_Calc_HH_ISIC'!$A$85:$A$109, 0)), 0) | D9: =IFERROR(INDEX('8_Calc_Intl_ISIC'!$C$85:$C$109, MATCH($A9, '8_Calc_Intl_ISIC'!$A$85:$A$109, 0)), 0) | E9: =IFERROR(INDEX('9_Calc_Total_ISIC'!$C$85:$C$109, MATCH($A9, '9_Calc_Total_ISIC'!$A$85:$A$109, 0)), 0) | F9: =MAX(E9, Keys!$C$5) | G9: =B9/F9 | H9: =C9/F9 | I9: =D9/F9 | J9: =MAX(0, 1-G9-H9-I9)
A10: 17T18 | B10: =IFERROR(INDEX('6_Calc_Gov_ISIC'!$C$85:$C$109, MATCH($A10, '6_Calc_Gov_ISIC'!$A$85:$A$109, 0)), 0) | C10: =IFERROR(INDEX('7_Calc_HH_ISIC'!$C$85:$C$109, MATCH($A10, '7_Calc_HH_ISIC'!$A$85:$A$109, 0)), 0) | D10: =IFERROR(INDEX('8_Calc_Intl_ISIC'!$C$85:$C$109, MATCH($A10, '8_Calc_Intl_ISIC'!$A$85:$A$109, 0)), 0) | E10: =IFERROR(INDEX('9_Calc_Total_ISIC'!$C$85:$C$109, MATCH($A10, '9_Calc_Total_ISIC'!$A$85:$A$109, 0)), 0) | F10: =MAX(E10, Keys!$C$5) | G10: =B10/F10 | H10: =C10/F10 | I10: =D10/F10 | J10: =MAX(0, 1-G10-H10-I10)
A11: 19 | B11: =IFERROR(INDEX('6_Calc_Gov_ISIC'!$C$85:$C$109, MATCH($A11, '6_Calc_Gov_ISIC'!$A$85:$A$109, 0)), 0) | C11: =IFERROR(INDEX('7_Calc_HH_ISIC'!$C$85:$C$109, MATCH($A11, '7_Calc_HH_ISIC'!$A$85:$A$109, 0)), 0) | D11: =IFERROR(INDEX('8_Calc_Intl_ISIC'!$C$85:$C$109, MATCH($A11, '8_Calc_Intl_ISIC'!$A$85:$A$109, 0)), 0) | E11: =IFERROR(INDEX('9_Calc_Total_ISIC'!$C$85:$C$109, MATCH($A11, '9_Calc_Total_ISIC'!$A$85:$A$109, 0)), 0) | F11: =MAX(E11, Keys!$C$5) | G11: =B11/F11 | H11: =C11/F11 | I11: =D11/F11 | J11: =MAX(0, 1-G11-H11-I11)
A12: 20 | B12: =IFERROR(INDEX('6_Calc_Gov_ISIC'!$C$85:$C$109, MATCH($A12, '6_Calc_Gov_ISIC'!$A$85:$A$109, 0)), 0) | C12: =IFERROR(INDEX('7_Calc_HH_ISIC'!$C$85:$C$109, MATCH($A12, '7_Calc_HH_ISIC'!$A$85:$A$109, 0)), 0) | D12: =IFERROR(INDEX('8_Calc_Intl_ISIC'!$C$85:$C$109, MATCH($A12, '8_Calc_Intl_ISIC'!$A$85:$A$109, 0)), 0) | E12: =IFERROR(INDEX('9_Calc_Total_ISIC'!$C$85:$C$109, MATCH($A12, '9_Calc_Total_ISIC'!$A$85:$A$109, 0)), 0) | F12: =MAX(E12, Keys!$C$5) | G12: =B12/F12 | H12: =C12/F12 | I12: =D12/F12 | J12: =MAX(0, 1-G12-H12-I12)
A13: 22 | B13: =IFERROR(INDEX('6_Calc_Gov_ISIC'!$C$85:$C$109, MATCH($A13, '6_Calc_Gov_ISIC'!$A$85:$A$109, 0)), 0) | C13: =IFERROR(INDEX('7_Calc_HH_ISIC'!$C$85:$C$109, MATCH($A13, '7_Calc_HH_ISIC'!$A$85:$A$109, 0)), 0) | D13: =IFERROR(INDEX('8_Calc_Intl_ISIC'!$C$85:$C$109, MATCH($A13, '8_Calc_Intl_ISIC'!$A$85:$A$109, 0)), 0) | E13: =IFERROR(INDEX('9_Calc_Total_ISIC'!$C$85:$C$109, MATCH($A13, '9_Calc_Total_ISIC'!$A$85:$A$109, 0)), 0) | F13: =MAX(E13, Keys!$C$5) | G13: =B13/F13 | H13: =C13/F13 | I13: =D13/F13 | J13: =MAX(0, 1-G13-H13-I13)
A14: 231 | B14: =IFERROR(INDEX('6_Calc_Gov_ISIC'!$C$85:$C$109, MATCH($A14, '6_Calc_Gov_ISIC'!$A$85:$A$109, 0)), 0) | C14: =IFERROR(INDEX('7_Calc_HH_ISIC'!$C$85:$C$109, MATCH($A14, '7_Calc_HH_ISIC'!$A$85:$A$109, 0)), 0) | D14: =IFERROR(INDEX('8_Calc_Intl_ISIC'!$C$85:$C$109, MATCH($A14, '8_Calc_Intl_ISIC'!$A$85:$A$109, 0)), 0) | E14: =IFERROR(INDEX('9_Calc_Total_ISIC'!$C$85:$C$109, MATCH($A14, '9_Calc_Total_ISIC'!$A$85:$A$109, 0)), 0) | F14: =MAX(E14, Keys!$C$5) | G14: =B14/F14 | H14: =C14/F14 | I14: =D14/F14 | J14: =MAX(0, 1-G14-H14-I14)
... A27: 41T43 | B27: =IFERROR(INDEX('6_Calc_Gov_ISIC'!$C$85:$C$109, MATCH($A27, '6_Calc_Gov_ISIC'!$A$85:$A$109, 0)), 0) | C27: =IFERROR(INDEX('7_Calc_HH_ISIC'!$C$85:$C$109, MATCH($A27, '7_Calc_HH_ISIC'!$A$85:$A$109, 0)), 0) | D27: =IFERROR(INDEX('8_Calc_Intl_ISIC'!$C$85:$C$109, MATCH($A27, '8_Calc_Intl_ISIC'!$A$85:$A$109, 0)), 0) | E27: =IFERROR(INDEX('9_Calc_Total_ISIC'!$C$85:$C$109, MATCH($A27, '9_Calc_Total_ISIC'!$A$85:$A$109, 0)), 0) | F27: =MAX(E27, Keys!$C$5) | G27: =B27/F27 | H27: =C27/F27 | I27: =D27/F27 | J27: =MAX(0, 1-G27-H27-I27)

Sheet FoGPbEaIC-entity
A1: label | B1: government | C1: domestic industries | D1: labor and consumers | E1: foreign entities
A2: agriculture and forestry 01T03 | B2: ='10_Calc_Entity_fractions'!G3 | C2: ='10_Calc_Entity_fractions'!J3 | D2: ='10_Calc_Entity_fractions'!H3 | E2: ='10_Calc_Entity_fractions'!I3
A3: coal mining 05 | B3: ='10_Calc_Entity_fractions'!G4 | C3: ='10_Calc_Entity_fractions'!J4 | D3: ='10_Calc_Entity_fractions'!H4 | E3: ='10_Calc_Entity_fractions'!I4
A4: oil and gas extraction 06 | B4: ='10_Calc_Entity_fractions'!G5 | C4: ='10_Calc_Entity_fractions'!J5 | D4: ='10_Calc_Entity_fractions'!H5 | E4: ='10_Calc_Entity_fractions'!I5
A5: other mining and quarrying 07T08 | B5: ='10_Calc_Entity_fractions'!G6 | C5: ='10_Calc_Entity_fractions'!J6 | D5: ='10_Calc_Entity_fractions'!H6 | E5: ='10_Calc_Entity_fractions'!I6
A6: food beverage and tobacco 10T12 | B6: ='10_Calc_Entity_fractions'!G7 | C6: ='10_Calc_Entity_fractions'!J7 | D6: ='10_Calc_Entity_fractions'!H7 | E6: ='10_Calc_Entity_fractions'!I7
A7: textiles apparel and leather 13T15 | B7: ='10_Calc_Entity_fractions'!G8 | C7: ='10_Calc_Entity_fractions'!J8 | D7: ='10_Calc_Entity_fractions'!H8 | E7: ='10_Calc_Entity_fractions'!I8
A8: wood products 16 | B8: ='10_Calc_Entity_fractions'!G9 | C8: ='10_Calc_Entity_fractions'!J9 | D8: ='10_Calc_Entity_fractions'!H9 | E8: ='10_Calc_Entity_fractions'!I9
A9: pulp paper and printing 17T18 | B9: ='10_Calc_Entity_fractions'!G10 | C9: ='10_Calc_Entity_fractions'!J10 | D9: ='10_Calc_Entity_fractions'!H10 | E9: ='10_Calc_Entity_fractions'!I10
A10: refined petroleum and coke 19 | B10: ='10_Calc_Entity_fractions'!G11 | C10: ='10_Calc_Entity_fractions'!J11 | D10: ='10_Calc_Entity_fractions'!H11 | E10: ='10_Calc_Entity_fractions'!I11
A11: chemicals 20 | B11: ='10_Calc_Entity_fractions'!G12 | C11: ='10_Calc_Entity_fractions'!J12 | D11: ='10_Calc_Entity_fractions'!H12 | E11: ='10_Calc_Entity_fractions'!I12
A12: rubber and plastic products 22 | B12: ='10_Calc_Entity_fractions'!G13 | C12: ='10_Calc_Entity_fractions'!J13 | D12: ='10_Calc_Entity_fractions'!H13 | E12: ='10_Calc_Entity_fractions'!I13
A13: glass and glass products 231 | B13: ='10_Calc_Entity_fractions'!G14 | C13: ='10_Calc_Entity_fractions'!J14 | D13: ='10_Calc_Entity_fractions'!H14 | E13: ='10_Calc_Entity_fractions'!I14
... A26: construction 41T43 | B26: ='10_Calc_Entity_fractions'!G27 | C26: ='10_Calc_Entity_fractions'!J27 | D26: ='10_Calc_Entity_fractions'!H27 | E26: ='10_Calc_Entity_fractions'!I27

Sheet FoGPbEaIC-isic
A1: label | B1: ISIC 01T03 | C1: ISIC 05 | D1: ISIC 06 | E1: ISIC 07T08 | F1: ISIC 09 | G1: ISIC 10T12 | H1: ISIC 13T15 | I1: ISIC 16 | J1: ISIC 17T18 | K1: ISIC 19 | L1: ISIC 20 | M1: ISIC 21 | N1: ISIC 22 | O1: ISIC 231 | P1: ISIC 239 | Q1: ISIC 241 | R1: ISIC 242 | S1: ISIC 25 | T1: ISIC 26 | U1: ISIC 27 | V1: ISIC 28 | W1: ISIC 29 | X1: ISIC 30 | Y1: ISIC 31T33 | Z1: ISIC 351 | AA1: ISIC 352T353 | AB1: ISIC 36T39 | AC1: ISIC 41T43 | AD1: ISIC 45T47 | AE1: ISIC 49T53 | AF1: ISIC 55T56 | AG1: ISIC 58T60 | AH1: ISIC 61 | AI1: ISIC 62T63 | AJ1: ISIC 64T66 | AK1: ISIC 68 | AL1: ISIC 69T82 | AM1: ISIC 84 | AN1: ISIC 85 | AO1: ISIC 86T88 | AP1: ISIC 90T96 | AQ1: ISIC 97T98
A2: agriculture and forestry 01T03 | B2: 0.17579435 | C2: 0.0002764021 | D2: 0 | E2: 0.00018336167 | F2: 5.7839894e-05 | G2: 0.5831189 | H2: 0.0026174452 | I2: 0.056196852 | J2: 0.019503994 | K2: 0 | L2: 0.022390147 | M2: 0.027365735 | N2: 0.013037275 | O2: 0 | P2: 0 | Q2: 0 | R2: 0 | S2: 0 | T2: 0 | U2: 0 | V2: 0 | W2: 0 | X2: 0 | Y2: 0.0024083656 | Z2: 0 | AA2: 0 | AB2: 0 | AC2: 0.0032938371 | AD2: 0.011396602 | AE2: 7.7595769e-05 | AF2: 0.043333657 | AG2: 0 | AH2: 0 | AI2: 0 | AJ2: 1.5481785e-06 | AK2: 6.4118727e-06 | AL2: 0.008114894 | AM2: 0.025722711 | AN2: 0.001671053 | AO2: 0 | AP2: 0.003431027 | AQ2: 0
A3: coal mining 05 | B3: 0.0074770292 | C3: 0.049115397 | D3: 0.0005741886 | E3: 0.032582537 | F3: 0.0020208726 | G3: 0.014492516 | H3: 0.00025365537 | I3: 0.00011047406 | J3: 0.026497037 | K3: 0.01528922 | L3: 0.042545829 | M3: 0.052000458 | N3: 0.0019035164 | O3: 0.030975315 | P3: 0.092925946 | Q3: 0.20051001 | R3: 0.066629845 | S3: 0.0068870562 | T3: 4.8710485e-05 | U3: 0.0018488386 | V3: 0.0012320182 | W3: 0.00032452923 | X3: 0.00051066407 | Y3: 0.0014893908 | Z3: 0.039539132 | AA3: 0.010983092 | AB3: 0.0049313686 | AC3: 0.15042186 | AD3: 0.00026392025 | AE3: 0.0012426846 | AF3: 0.0069397776 | AG3: 0.0013928951 | AH3: 0.0036498691 | AI3: 0.003226183 | AJ3: 0 | AK3: 4.9406443e-05 | AL3: 0.022649199 | AM3: 0.073568734 | AN3: 0.0081058845 | AO3: 0.0029986276 | AP3: 0.021792312 | AQ3: 0
A4: oil and gas extraction 06 | B4: 0 | C4: 0 | D4: 0.026231481 | E4: 0 | F4: 5.5806449e-05 | G4: 4.2328021e-07 | H4: 0 | I4: 2.0425243e-05 | J4: 2.7468367e-05 | K4: 0.88963678 | L4: 0.0028549945 | M4: 0.0034894378 | N4: 0 | O4: 1.2845002e-07 | P4: 3.8535006e-07 | Q4: 0.036106722 | R4: 9.4524692e-07 | S4: 0 | T4: 0 | U4: 0 | V4: 0 | W4: 1.3930342e-07 | X4: 0 | Y4: 0 | Z4: 0.017914645 | AA4: 0.005099588 | AB4: 0.0020061692 | AC4: 0 | AD4: 5.3779153e-05 | AE4: 0.0007059546 | AF4: 6.3053188e-07 | AG4: 0.00020635059 | AH4: 1.8806254e-05 | AI4: 2.6261302e-05 | AJ4: 0 | AK4: 8.2251808e-05 | AL4: 3.9709113e-05 | AM4: 0.013260922 | AN4: 0.0020039086 | AO4: 1.209727e-06 | AP4: 0.00015467456 | AQ4: 0
A5: other mining and quarrying 07T08 | B5: 0.0074770292 | C5: 0.049115397 | D5: 0.0005741886 | E5: 0.032582537 | F5: 0.0020208726 | G5: 0.014492516 | H5: 0.00025365537 | I5: 0.00011047406 | J5: 0.026497037 | K5: 0.01528922 | L5: 0.042545829 | M5: 0.052000458 | N5: 0.0019035164 | O5: 0.030975315 | P5: 0.092925946 | Q5: 0.20051001 | R5: 0.066629845 | S5: 0.0068870562 | T5: 4.8710485e-05 | U5: 0.0018488386 | V5: 0.0012320182 | W5: 0.00032452923 | X5: 0.00051066407 | Y5: 0.0014893908 | Z5: 0.039539132 | AA5: 0.010983092 | AB5: 0.0049313686 | AC5: 0.15042186 | AD5: 0.00026392025 | AE5: 0.0012426846 | AF5: 0.0069397776 | AG5: 0.0013928951 | AH5: 0.0036498691 | AI5: 0.003226183 | AJ5: 0 | AK5: 4.9406443e-05 | AL5: 0.022649199 | AM5: 0.073568734 | AN5: 0.0081058845 | AO5: 0.0029986276 | AP5: 0.021792312 | AQ5: 0
A6: food beverage and tobacco 10T12 | B6: 0.037240845 | C6: 0 | D6: 0 | E6: 0 | F6: 0 | G6: 0.44231656 | H6: 0.00033490959 | I6: 6.6727247e-05 | J6: 0.002765341 | K6: 0.00068670667 | L6: 0.0094755404 | M6: 0.011581216 | N6: 0.00091436859 | O6: 0.00037544468 | P6: 0.001126334 | Q6: 5.261535e-05 | R6: 8.2489739e-06 | S6: 0 | T6: 0 | U6: 0 | V6: 0 | W6: 0 | X6: 0 | Y6: 1.7157328e-05 | Z6: 0 | AA6: 0 | AB6: 0 | AC6: 0 | AD6: 0.018120223 | AE6: 0.0013729081 | AF6: 0.17480192 | AG6: 7.151715e-05 | AH6: 0 | AI6: 0.00021828922 | AJ6: 0 | AK6: 0 | AL6: 0.012403024 | AM6: 0.13072012 | AN6: 0.027576044 | AO6: 0.10644939 | AP6: 0.021304549 | AQ6: 0
A7: textiles apparel and leather 13T15 | B7: 0.0013950406 | C7: 1.8337817e-05 | D7: 0 | E7: 1.2165077e-05 | F7: 0 | G7: 0.0032592926 | H7: 0.094951545 | I7: 0.0071348454 | J7: 0.13797097 | K7: 0.0002189767 | L7: 2.3687732e-05 | M7: 2.8951673e-05 | N7: 0.063121916 | O7: 0.00096918061 | P7: 0.0029075418 | Q7: 8.8866713e-06 | R7: 0 | S7: 7.0200256e-06 | T7: 5.3680407e-06 | U7: 0 | V7: 0.0048511427 | W7: 0.01689395 | X7: 0.0071009246 | Y7: 0.065106111 | Z7: 0 | AA7: 0.00011082821 | AB7: 0.0045267116 | AC7: 0.015864443 | AD7: 0.13696711 | AE7: 0.00077524449 | AF7: 0.041997359 | AG7: 0.013781152 | AH7: 0.033378061 | AI7: 1.12545e-05 | AJ7: 0 | AK7: 0.0006211964 | AL7: 0.014426802 | AM7: 0.10232079 | AN7: 0.0034901987 | AO7: 0.1705058 | AP7: 0.055237193 | AQ7: 0
A8: wood products 16 | B8: 0.0027236268 | C8: 0.00090813203 | D8: 0 | E8: 0.00060244336 | F8: 0.0030230329 | G8: 0.0029936015 | H8: 0.00034569065 | I8: 0.2684786 | J8: 0.063283275 | K8: 0 | L8: 0.001364557 | M8: 0.0016677919 | N8: 0.024124402 | O8: 0.00043302867 | P8: 0.001299086 | Q8: 0.0074734989 | R8: 0.0024911663 | S8: 0.0021165058 | T8: 0.0011338911 | U8: 0.0078231954 | V8: 0.0067223155 | W8: 0.0079887131 | X8: 0.00090949219 | Y8: 0.069003827 | Z8: 2.727225e-05 | AA8: 0.00037343812 | AB8: 0.00028868456 | AC8: 0.32086561 | AD8: 0.060544189 | AE8: 0.020680621 | AF8: 0.011122636 | AG8: 0.0030788287 | AH8: 0.0078862973 | AI8: 0.004260768 | AJ8: 0.001515753 | AK8: 0.033046986 | AL8: 0.016228405 | AM8: 0.020343882 | AN8: 0.00060917333 | AO8: 0.01751954 | AP8: 0.0046980374 | AQ8: 0
A9: pulp paper and printing 17T18 | B9: 0.0010397253 | C9: 0.00036057132 | D9: 0.00020096538 | E9: 0.00023919848 | F9: 0.00031335487 | G9: 0.07605948 | H9: 0.00072505919 | I9: 0.0037558428 | J9: 0.32861431 | K9: 0.00055371598 | L9: 0.012005546 | M9: 0.014673445 | N9: 0.019818216 | O9: 0.001286023 | P9: 0.0038580691 | Q9: 0.0079896725 | R9: 0.0026557337 | S9: 0.0073932991 | T9: 0.00088838522 | U9: 0.0052571984 | V9: 0.0053844839 | W9: 0.0043011999 | X9: 0.0007274899 | Y9: 0.0098259931 | Z9: 7.6735907e-05 | AA9: 0.0010744823 | AB9: 0.001235436 | AC9: 0.0081354995 | AD9: 0.10391507 | AE9: 0.014677862 | AF9: 0.025625781 | AG9: 0.018223596 | AH9: 0.0045127306 | AI9: 0.0119251 | AJ9: 0.040410846 | AK9: 0.0019032877 | AL9: 0.084117269 | AM9: 0.080572223 | AN9: 0.0085936868 | AO9: 0.072027824 | AP9: 0.015045593 | AQ9: 0
A10: refined petroleum and coke 19 | B10: 0.017180967 | C10: 0.0081910605 | D10: 0.011914155 | E10: 0.0054338464 | F10: 0.011761487 | G10: 0.0092599598 | H10: 0.00015624417 | I10: 0.0035373561 | J10: 0.01177299 | K10: 0.032714101 | L10: 0.020924632 | M10: 0.025574551 | N10: 0.0036645341 | O10: 0.00055604164 | P10: 0.0016681249 | Q10: 0.011592226 | R10: 0.003421533 | S10: 0.0052950309 | T10: 0.00027049154 | U10: 0.0029940326 | V10: 0.0028333153 | W10: 0.00046084378 | X10: 0.00030461815 | Y10: 0.0039009734 | Z10: 0.038253121 | AA10: 0.013365917 | AB10: 0.0096662453 | AC10: 0.11774808 | AD10: 0.023067749 | AE10: 0.20413292 | AF10: 0.012352351 | AG10: 0.0017998644 | AH10: 0.0025069725 | AI10: 0.0038893437 | AJ10: 0.018964353 | AK10: 0.010251532 | AL10: 0.029398513 | AM10: 0.28099453 | AN10: 0.0080545129 | AO10: 0.018360551 | AP10: 0.011810331 | AQ10: 0
A11: chemicals 20 | B11: 0.01786932 | C11: 0.0018067199 | D11: 0.0060471627 | E11: 0.0011985552 | F11: 0.0035733058 | G11: 0.011585564 | H11: 0.0097751781 | I11: 0.0052601978 | J11: 0.026931687 | K11: 0.021938202 | L11: 0.20839595 | M11: 0.25470616 | N11: 0.1318986 | O11: 0.0014931954 | P11: 0.0044795862 | Q11: 0.0046216272 | R11: 0.0012437717 | S11: 0.010614234 | T11: 0.0015360772 | U11: 0.0044042087 | V11: 0.0030940071 | W11: 0.004493158 | X11: 0.00081021176 | Y11: 0.011375397 | Z11: 0.00090494008 | AA11: 0.0002727641 | AB11: 0.0028097702 | AC11: 0.015410712 | AD11: 0.003546504 | AE11: 0.0017459 | AF11: 0.0017062143 | AG11: 0.0010261942 | AH11: 0.0016900624 | AI11: 0.00075116409 | AJ11: 0.00024729761 | AK11: 0.010112427 | AL11: 0.062458902 | AM11: 0.044337973 | AN11: 0.0019749256 | AO11: 0.092513814 | AP11: 0.0093383581 | AQ11: 0
A12: rubber and plastic products 22 | B12: 0.0045914138 | C12: 0.0049016185 | D12: 0.00027737645 | E12: 0.003251672 | F12: 0.0070704353 | G12: 0.077285114 | H12: 0.001182923 | I12: 0.0065123048 | J12: 0.036289118 | K12: 0.0013035183 | L12: 0.02706082 | M12: 0.033074336 | N12: 0.11909689 | O12: 0.0013098498 | P12: 0.0039295493 | Q12: 0.0051208102 | R12: 0.0016893033 | S12: 0.013522571 | T12: 0.0058361044 | U12: 0.013265728 | V12: 0.043786084 | W12: 0.03117749 | X12: 0.0065029593 | Y12: 0.032228534 | Z12: 7.2284433e-05 | AA12: 0.0031559256 | AB12: 0.0019039624 | AC12: 0.11551148 | AD12: 0.097036686 | AE12: 0.016544326 | AF12: 0.023134041 | AG12: 0.0092775395 | AH12: 0.025223462 | AI12: 0.006711686 | AJ12: 0.0062313824 | AK12: 0.0015273243 | AL12: 0.04427493 | AM12: 0.061580135 | AN12: 0.0058134158 | AO12: 0.086277352 | AP12: 0.015457544 | AQ12: 0
A13: glass and glass products 231 | B13: 0.00022036456 | C13: 0.0022222212 | D13: 0.0057575136 | E13: 0.0014741936 | F13: 0.0092482834 | G13: 0.02839103 | H13: 0.00014281122 | I13: 0.0089078309 | J13: 0.0057834081 | K13: 0.0056809877 | L13: 0.0068968153 | M13: 0.0084294409 | N13: 0.021101426 | O13: 0.030914452 | P13: 0.092743357 | Q13: 0.033077102 | R13: 0.010948851 | S13: 0.016111621 | T13: 0.001196862 | U13: 0.020209238 | V13: 0.013190351 | W13: 0.016140499 | X13: 0.0012607819 | Y13: 0.009046616 | Z13: 0.00026901748 | AA13: 7.4727079e-05 | AB13: 0.002535857 | AC13: 0.44232449 | AD13: 0.0080708197 | AE13: 0.0026082733 | AF13: 0.015557595 | AG13: 0.0086771586 | AH13: 0.025999641 | AI13: 0.0032718622 | AJ13: 0.00073324265 | AK13: 0.00095053329 | AL13: 0.043298666 | AM13: 0.027548642 | AN13: 0.0011937261 | AO13: 0.055467976 | AP13: 0.012321711 | AQ13: 0
... A26: construction 41T43 | B26: 0.0033298382 | C26: 0.0097116522 | D26: 0.00041285929 | E26: 0.0064425878 | F26: 0.012859418 | G26: 0.0076793468 | H26: 0.00029933825 | I26: 0.0015647199 | J26: 0.0096085942 | K26: 0.015844954 | L26: 0.0052131826 | M26: 0.0063716676 | N26: 0.0046928123 | O26: 0.0010056921 | P26: 0.0030170762 | Q26: 0.0094173819 | R26: 0.0029247835 | S26: 0.0070323455 | T26: 0.0010543665 | U26: 0.0010134886 | V26: 0.0035077015 | W26: 0.0010207378 | X26: 0.00091583836 | Y26: 0.0018633561 | Z26: 0.015742267 | AA26: 0.020281688 | AB26: 0.0023414497 | AC26: 0.00097642361 | AD26: 0.042730684 | AE26: 0.023825523 | AF26: 0.014777682 | AG26: 0.0042952188 | AH26: 0.011540918 | AI26: 0.001822346 | AJ26: 0.024146195 | AK26: 0.40086602 | AL26: 0.020592209 | AM26: 0.24837654 | AN26: 0.014893679 | AO26: 0.017550298 | AP26: 0.018437122 | AQ26: 0
